Workbook

Sheet 资金总览
A1: Blocky · 近期必要投入与阶段资金
A3: 近期以12个月完善产品及小范围教育验证为基准；后续OPC、企业与多端按关口续投。
A5: 当前情景 | B5: =INDEX(预算输入!D8:F8,1,预算输入!B5) -> 基准
A7: 资金项目（万元） | B7: 6个月 | C7: 12个月 | D7: 24个月
A8: 团队工资及附加 | B8: =SUM(月度预算!F8:F13)/10000 -> 45 | C8: =SUM(月度预算!F8:F19)/10000 -> 90 | D8: =SUM(月度预算!F8:F31)/10000 -> 180
A9: 5席Pro订阅 | B9: =SUM(月度预算!G8:G13)/10000 -> 10.5 | C9: =SUM(月度预算!G8:G19)/10000 -> 21 | D9: =SUM(月度预算!G8:G31)/10000 -> 42
A10: 研发API测试 | B10: =SUM(月度预算!H8:H13)/10000 -> 0.5616 | C10: =SUM(月度预算!H8:H19)/10000 -> 1.1232 | D10: =SUM(月度预算!H8:H31)/10000 -> 2.2464
A11: 基础设施 | B11: =SUM(月度预算!I8:I13)/10000 -> 0.336 | C11: =SUM(月度预算!I8:I19)/10000 -> 1.02 | D11: =SUM(月度预算!I8:I31)/10000 -> 3.408
A12: 一般运营 | B12: =SUM(月度预算!J8:J13)/10000 -> 1.8 | C12: =SUM(月度预算!J8:J19)/10000 -> 3.6 | D12: =SUM(月度预算!J8:J31)/10000 -> 7.2
A13: 专项技术交付 | B13: =SUM(月度预算!K8:K13)/10000 -> 3 | C13: =SUM(月度预算!K8:K19)/10000 -> 6 | D13: =SUM(月度预算!K8:K31)/10000 -> 12
A14: 教学验证材料 | B14: =SUM(月度预算!L8:L13)/10000 -> 0 | C14: =SUM(月度预算!L8:L19)/10000 -> 2 | D14: =SUM(月度预算!L8:L31)/10000 -> 6
A15: 条件试用API | B15: =SUM(月度预算!M8:M13)/10000 -> 0 | C15: =SUM(月度预算!M8:M19)/10000 -> 0.48324056 | D15: =SUM(月度预算!M8:M31)/10000 -> 5.023085
A16: 增量测试设备 | B16: =SUM(月度预算!N8:N13)/10000 -> 3 | C16: =SUM(月度预算!N8:N19)/10000 -> 5 | D16: =SUM(月度预算!N8:N31)/10000 -> 5
A17: 预算现金支出 | B17: =SUM(月度预算!O8:O13)/10000 -> 64.1976 | C17: =SUM(月度预算!O8:O19)/10000 -> 130.22644 | D17: =SUM(月度预算!O8:O31)/10000 -> 262.87749
A18: 支出风险预留 | B18: =(SUM(B8:B16)+预算输入!C29/10000)*预算输入!C26 -> 6.41976 | C18: =(SUM(C8:C16)+预算输入!C29/10000)*预算输入!C26 -> 13.022644 | D18: =(SUM(D8:D16)+预算输入!C29/10000)*预算输入!C26 -> 26.287749
A19: 正常运营现金储备 | B19: =月度预算!Q13*预算输入!C27/10000 -> 29.0988 | C19: =月度预算!Q19*预算输入!C27/10000 -> 29.59496 | D19: =月度预算!Q31*预算输入!C27/10000 -> 31.041081
A20: 最低追加资金 | B20: =MAX(0,SUM(B17:B19)-(预算输入!C28+预算输入!C32)/10000) -> 99.71616 | C20: =MAX(0,SUM(C17:C19)-(预算输入!C28+预算输入!C32)/10000) -> 172.84404 | D20: =MAX(0,SUM(D17:D19)-(预算输入!C28+预算输入!C32)/10000) -> 320.20631
A21: 取整覆盖目标 | B21: =ROUNDUP(B20/10,0)*10 -> 100 | C21: =ROUNDUP(C20/10,0)*10 -> 180 | D21: =ROUNDUP(D20/10,0)*10 -> 330
A22: 取整余量 | B22: =B21-B20 -> 0.28384 | C22: =C21-C20 -> 7.155955 | D22: =D21-D20 -> 9.793685
A24: 资金目标＝预算现金＋风险预留＋期末经常性月成本×储备月数－确认现金，按10万元向上取整。6/12/24月为不同覆盖期，不能相加。合作费、预付、保证金目前未报价；预付与使用成本不双算。设备只计增量采购现金，折旧不重复相加。
A28: 情景快照（万元） | B28: 12月现金 | C28: 12月最低 | D28: 12月覆盖目标 | E28: 24月覆盖目标
A29: 节约 | B29: 103.02106 | C29: 137.44471 | D29: 140 | E29: 260
A30: 基准 | B30: 130.22644 | C30: 172.84404 | D30: 180 | E30: 330
A31: 高投入 | B31: 190.56376 | C31: 283.20278 | D31: 290 | E31: 700
A34: 三情景快照由B5选择器逐次重算并保存，日期2026-10-10；修改输入后请逐项选择并刷新快照。上方当前情景输出实时联动。基准税前1.2万元、附加25%与汇率7为假设；不包含融资交易及创始人股权估值。未知收入不抵减。

Sheet 预算输入
A1: 五人团队 · 可调整预算输入
A3: 修改B5选择情景（1节约、2基准、3高投入）；蓝色数字可编辑。C列由同一选择器驱动。
A5: 选择情景 | B5: 2
A8: 参数 | B8: 单位 | C8: 当前情景 | D8: 节约 | E8: 基准 | F8: 高投入 | G8: 依据与边界
A9: 团队人数 | B9: 人 | C9: =INDEX(D9:F9,1,$B$5) -> 5 | D9: 5 | E9: 5 | F9: 5 | G9: 按5个需计薪资源及5个独立订阅席位规划
A10: 每人税前月薪 | B10: 元/人月 | C10: =INDEX(D10:F10,1,$B$5) -> 12000 | D10: 10000 | E10: 12000 | F10: 16000 | G10: 工资未确认；基准1.2万元为假设，W1仅参照
A11: 雇主附加成本比例 | B11: 比例 | C11: =INDEX(D11:F11,1,$B$5) -> 0.25 | D11: 0.2 | E11: 0.25 | F11: 0.25 | G11: 社保公积金等预算比例，非地方缴费法定费率
A12: 每人Pro月费 | B12: 美元/人月 | C12: =INDEX(D12:F12,1,$B$5) -> 500 | D12: 500 | E12: 500 | F12: 500 | G12: O1/O2；用户高用量方向按当前最高Pro500核算
A13: 预算汇率 | B13: 元/美元 | C13: =INDEX(D13:F13,1,$B$5) -> 7 | D13: 6.8 | E13: 7 | F13: 7.5 | G13: 规划汇率，非即期汇率；税费及额外额度需按实收修订
A14: 研发API任务量 | B14: 任务/人月 | C14: =INDEX(D14:F14,1,$B$5) -> 100 | D14: 50 | E14: 100 | F14: 200 | G14: 独立于Pro订阅的产品模型回归预算，不是实际账单
A15: 研发API每任务调用 | B15: 调用/任务 | C15: =INDEX(D15:F15,1,$B$5) -> 8 | D15: 4 | E15: 8 | F15: 16 | G15: 假设；包括已规划重试，实际新增调用需计入
A16: 每调用计费输入 | B16: Token/调用 | C16: =INDEX(D16:F16,1,$B$5) -> 20000 | D16: 20000 | E16: 20000 | F16: 20000 | G16: 累计输入含上下文；示例每轮均计费，无缓存折扣
A17: 每调用计费输出 | B17: Token/调用 | C17: =INDEX(D17:F17,1,$B$5) -> 2000 | D17: 2000 | E17: 2000 | F17: 2000 | G17: 累计输出预算；含供应商计费思考Token时应计入
A18: 专业任务频次 | B18: 任务/人月 | C18: =INDEX(D18:F18,1,$B$5) -> 20 | D18: 10 | E18: 20 | F18: 100 | G18: 暂无专业长任务账单；情景参数，不使用工具订阅反推
A19: 专业每任务调用 | B19: 调用/任务 | C19: =INDEX(D19:F19,1,$B$5) -> 8 | D19: 4 | E19: 8 | F19: 32 | G19: 多轮任务情景；按总计费输入/输出重算
A20: 条件试用人数倍数 | B20: 倍 | C20: =INDEX(D20:F20,1,$B$5) -> 1 | D20: 0.5 | E20: 1 | F20: 2 | G20: 仅平台承担的短期试用用户；BYOK和本地用户不计
... A33: 条件试用启动开关 | B33: 0/1 | C33: =INDEX(D33:F33,1,$B$5) -> 1 | D33: 1 | E33: 1 | F33: 1 | G33: 第7月为最早规划窗口；未通过产品关口设0或推迟人数
A36: 基础设施：普通CPU服务与数据库，不自建大模型GPU集群
A38: 月份阶段 | B38: 应用实例数 | C38: 数据库实例数 | D38: 实例单价元/月 | E38: 其他资源预留元/月 | F38: 说明
A39: 1–6月 | B39: 1 | C39: 1 | D39: 80 | E39: 400 | F39: 备份、存储、下载及监控额度预留
A40: 7–12月 | B40: 2 | C40: 1 | D40: 80 | E40: 900 | F40: 普通轻量实例；不承诺高可用SLA
A41: 13–24月 | B41: 2 | C41: 1 | D41: 230 | E41: 1300 | F41: 按实际流量、并发及数据库需求扩容
A44: 最早月份 | B44: 学生条件人数 | C44: 教师条件人数 | D44: 专业条件人数
A45: 7 | B45: 30 | C45: 3 | D45: 10
A46: 10 | B46: 60 | C46: 6 | D46: 20
A47: 13 | B47: 120 | C47: 12 | D47: 50
A48: 19 | B48: 240 | C48: 24 | D48: 100
A51: 5人均计薪、各自独立Pro订阅。工资与已有设备尚未确认；本表不是工资账本。客户规模和专业用量未实测，采购前用实际账单替换。第7月试用须产品、内容、许可和组织关口通过；未通过时关闭开关或后移人数。

Sheet 月度预算
A1: 24个月单一月度模型（金额：人民币元）
A3: 2026-11至2028-10；全部为规划月份。预付余额按API消耗抵扣，保证金占用现金，不加入费用。所有金额未以未知收入抵减。
A7: 月序 | B7: 月份 | C7: 学生 | D7: 教师 | E7: 专业 | F7: 人力总成本 | G7: Pro订阅 | H7: 研发API成本 | I7: 基础设施 | J7: 一般运营 | K7: 专项交付 | L7: 教学验证 | M7: 试用API成本 | N7: 设备购置 | O7: 现金支出 | P7: 累计现金 | Q7: 经常性月成本 | R7: 预付抵扣 | S7: 期末预付余额 | T7: API现金付费
A8: =1 -> 1 | B8: =DATE(2026,10+A8,1) -> 46327 | C8: =0 -> 0 | D8: =0 -> 0 | E8: =0 -> 0 | F8: =预算输入!$C$9*预算输入!$C$10*(1+预算输入!$C$11) -> 75000 | G8: =预算输入!$C$9*预算输入!$C$12*预算输入!$C$13 -> 17500 | H8: =用量测算!$B$17 -> 936 | I8: =(预算输入!B39+预算输入!C39)*预算输入!D39+预算输入!E39*预算输入!$C$21 -> 560 | J8: =预算输入!$C$22 -> 3000 | K8: =IF(MOD(A8,3)=0,预算输入!$C$24/4,0) -> 0 | L8: =IF(OR(A8=8,A8=11),预算输入!$C$25/2,IF(OR(A8=16,A8=22),预算输入!$C$25,0)) -> 0 | M8: =C8*用量测算!$B$14+D8*用量测算!$B$15+E8*用量测算!$B$16 -> 0 | N8: =IF(A8=1,预算输入!$C$23*0.6,IF(A8=7,预算输入!$C$23*0.4,0)) -> 30000 | O8: =SUM(F8:N8)-R8+IF(A8=1,SUM(预算输入!$C$29:$C$31),0) -> 126996 | P8: =SUM($O$8:O8) -> 126996 | Q8: =SUM(F8:J8)+M8 -> 96996 | R8: =MIN(预算输入!$C$30,H8+M8) -> 0 | S8: =预算输入!$C$30-R8 -> 0 | T8: =H8+M8-R8 -> 936
A9: =2 -> 2 | B9: =DATE(2026,10+A9,1) -> 46357 | C9: =0 -> 0 | D9: =0 -> 0 | E9: =0 -> 0 | F9: =预算输入!$C$9*预算输入!$C$10*(1+预算输入!$C$11) -> 75000 | G9: =预算输入!$C$9*预算输入!$C$12*预算输入!$C$13 -> 17500 | H9: =用量测算!$B$17 -> 936 | I9: =(预算输入!B39+预算输入!C39)*预算输入!D39+预算输入!E39*预算输入!$C$21 -> 560 | J9: =预算输入!$C$22 -> 3000 | K9: =IF(MOD(A9,3)=0,预算输入!$C$24/4,0) -> 0 | L9: =IF(OR(A9=8,A9=11),预算输入!$C$25/2,IF(OR(A9=16,A9=22),预算输入!$C$25,0)) -> 0 | M9: =C9*用量测算!$B$14+D9*用量测算!$B$15+E9*用量测算!$B$16 -> 0 | N9: =IF(A9=1,预算输入!$C$23*0.6,IF(A9=7,预算输入!$C$23*0.4,0)) -> 0 | O9: =SUM(F9:N9)-R9+IF(A9=1,SUM(预算输入!$C$29:$C$31),0) -> 96996 | P9: =SUM($O$8:O9) -> 223992 | Q9: =SUM(F9:J9)+M9 -> 96996 | R9: =MIN(S8,H9+M9) -> 0 | S9: =S8-R9 -> 0 | T9: =H9+M9-R9 -> 936
A10: =3 -> 3 | B10: =DATE(2026,10+A10,1) -> 46388 | C10: =0 -> 0 | D10: =0 -> 0 | E10: =0 -> 0 | F10: =预算输入!$C$9*预算输入!$C$10*(1+预算输入!$C$11) -> 75000 | G10: =预算输入!$C$9*预算输入!$C$12*预算输入!$C$13 -> 17500 | H10: =用量测算!$B$17 -> 936 | I10: =(预算输入!B39+预算输入!C39)*预算输入!D39+预算输入!E39*预算输入!$C$21 -> 560 | J10: =预算输入!$C$22 -> 3000 | K10: =IF(MOD(A10,3)=0,预算输入!$C$24/4,0) -> 15000 | L10: =IF(OR(A10=8,A10=11),预算输入!$C$25/2,IF(OR(A10=16,A10=22),预算输入!$C$25,0)) -> 0 | M10: =C10*用量测算!$B$14+D10*用量测算!$B$15+E10*用量测算!$B$16 -> 0 | N10: =IF(A10=1,预算输入!$C$23*0.6,IF(A10=7,预算输入!$C$23*0.4,0)) -> 0 | O10: =SUM(F10:N10)-R10+IF(A10=1,SUM(预算输入!$C$29:$C$31),0) -> 111996 | P10: =SUM($O$8:O10) -> 335988 | Q10: =SUM(F10:J10)+M10 -> 96996 | R10: =MIN(S9,H10+M10) -> 0 | S10: =S9-R10 -> 0 | T10: =H10+M10-R10 -> 936
A11: =4 -> 4 | B11: =DATE(2026,10+A11,1) -> 46419 | C11: =0 -> 0 | D11: =0 -> 0 | E11: =0 -> 0 | F11: =预算输入!$C$9*预算输入!$C$10*(1+预算输入!$C$11) -> 75000 | G11: =预算输入!$C$9*预算输入!$C$12*预算输入!$C$13 -> 17500 | H11: =用量测算!$B$17 -> 936 | I11: =(预算输入!B39+预算输入!C39)*预算输入!D39+预算输入!E39*预算输入!$C$21 -> 560 | J11: =预算输入!$C$22 -> 3000 | K11: =IF(MOD(A11,3)=0,预算输入!$C$24/4,0) -> 0 | L11: =IF(OR(A11=8,A11=11),预算输入!$C$25/2,IF(OR(A11=16,A11=22),预算输入!$C$25,0)) -> 0 | M11: =C11*用量测算!$B$14+D11*用量测算!$B$15+E11*用量测算!$B$16 -> 0 | N11: =IF(A11=1,预算输入!$C$23*0.6,IF(A11=7,预算输入!$C$23*0.4,0)) -> 0 | O11: =SUM(F11:N11)-R11+IF(A11=1,SUM(预算输入!$C$29:$C$31),0) -> 96996 | P11: =SUM($O$8:O11) -> 432984 | Q11: =SUM(F11:J11)+M11 -> 96996 | R11: =MIN(S10,H11+M11) -> 0 | S11: =S10-R11 -> 0 | T11: =H11+M11-R11 -> 936
A12: =5 -> 5 | B12: =DATE(2026,10+A12,1) -> 46447 | C12: =0 -> 0 | D12: =0 -> 0 | E12: =0 -> 0 | F12: =预算输入!$C$9*预算输入!$C$10*(1+预算输入!$C$11) -> 75000 | G12: =预算输入!$C$9*预算输入!$C$12*预算输入!$C$13 -> 17500 | H12: =用量测算!$B$17 -> 936 | I12: =(预算输入!B39+预算输入!C39)*预算输入!D39+预算输入!E39*预算输入!$C$21 -> 560 | J12: =预算输入!$C$22 -> 3000 | K12: =IF(MOD(A12,3)=0,预算输入!$C$24/4,0) -> 0 | L12: =IF(OR(A12=8,A12=11),预算输入!$C$25/2,IF(OR(A12=16,A12=22),预算输入!$C$25,0)) -> 0 | M12: =C12*用量测算!$B$14+D12*用量测算!$B$15+E12*用量测算!$B$16 -> 0 | N12: =IF(A12=1,预算输入!$C$23*0.6,IF(A12=7,预算输入!$C$23*0.4,0)) -> 0 | O12: =SUM(F12:N12)-R12+IF(A12=1,SUM(预算输入!$C$29:$C$31),0) -> 96996 | P12: =SUM($O$8:O12) -> 529980 | Q12: =SUM(F12:J12)+M12 -> 96996 | R12: =MIN(S11,H12+M12) -> 0 | S12: =S11-R12 -> 0 | T12: =H12+M12-R12 -> 936
A13: =6 -> 6 | B13: =DATE(2026,10+A13,1) -> 46478 | C13: =0 -> 0 | D13: =0 -> 0 | E13: =0 -> 0 | F13: =预算输入!$C$9*预算输入!$C$10*(1+预算输入!$C$11) -> 75000 | G13: =预算输入!$C$9*预算输入!$C$12*预算输入!$C$13 -> 17500 | H13: =用量测算!$B$17 -> 936 | I13: =(预算输入!B39+预算输入!C39)*预算输入!D39+预算输入!E39*预算输入!$C$21 -> 560 | J13: =预算输入!$C$22 -> 3000 | K13: =IF(MOD(A13,3)=0,预算输入!$C$24/4,0) -> 15000 | L13: =IF(OR(A13=8,A13=11),预算输入!$C$25/2,IF(OR(A13=16,A13=22),预算输入!$C$25,0)) -> 0 | M13: =C13*用量测算!$B$14+D13*用量测算!$B$15+E13*用量测算!$B$16 -> 0 | N13: =IF(A13=1,预算输入!$C$23*0.6,IF(A13=7,预算输入!$C$23*0.4,0)) -> 0 | O13: =SUM(F13:N13)-R13+IF(A13=1,SUM(预算输入!$C$29:$C$31),0) -> 111996 | P13: =SUM($O$8:O13) -> 641976 | Q13: =SUM(F13:J13)+M13 -> 96996 | R13: =MIN(S12,H13+M13) -> 0 | S13: =S12-R13 -> 0 | T13: =H13+M13-R13 -> 936
A14: =7 -> 7 | B14: =DATE(2026,10+A14,1) -> 46508 | C14: =预算输入!B45*预算输入!$C$20*预算输入!$C$33 -> 30 | D14: =预算输入!C45*预算输入!$C$20*预算输入!$C$33 -> 3 | E14: =预算输入!D45*预算输入!$C$20*预算输入!$C$33 -> 10 | F14: =预算输入!$C$9*预算输入!$C$10*(1+预算输入!$C$11) -> 75000 | G14: =预算输入!$C$9*预算输入!$C$12*预算输入!$C$13 -> 17500 | H14: =用量测算!$B$17 -> 936 | I14: =(预算输入!B40+预算输入!C40)*预算输入!D40+预算输入!E40*预算输入!$C$21 -> 1140 | J14: =预算输入!$C$22 -> 3000 | K14: =IF(MOD(A14,3)=0,预算输入!$C$24/4,0) -> 0 | L14: =IF(OR(A14=8,A14=11),预算输入!$C$25/2,IF(OR(A14=16,A14=22),预算输入!$C$25,0)) -> 0 | M14: =C14*用量测算!$B$14+D14*用量测算!$B$15+E14*用量测算!$B$16 -> 536.93395 | N14: =IF(A14=1,预算输入!$C$23*0.6,IF(A14=7,预算输入!$C$23*0.4,0)) -> 20000 | O14: =SUM(F14:N14)-R14+IF(A14=1,SUM(预算输入!$C$29:$C$31),0) -> 118112.93 | P14: =SUM($O$8:O14) -> 760088.93 | Q14: =SUM(F14:J14)+M14 -> 98112.934 | R14: =MIN(S13,H14+M14) -> 0 | S14: =S13-R14 -> 0 | T14: =H14+M14-R14 -> 1472.934
A15: =8 -> 8 | B15: =DATE(2026,10+A15,1) -> 46539 | C15: =预算输入!B45*预算输入!$C$20*预算输入!$C$33 -> 30 | D15: =预算输入!C45*预算输入!$C$20*预算输入!$C$33 -> 3 | E15: =预算输入!D45*预算输入!$C$20*预算输入!$C$33 -> 10 | F15: =预算输入!$C$9*预算输入!$C$10*(1+预算输入!$C$11) -> 75000 | G15: =预算输入!$C$9*预算输入!$C$12*预算输入!$C$13 -> 17500 | H15: =用量测算!$B$17 -> 936 | I15: =(预算输入!B40+预算输入!C40)*预算输入!D40+预算输入!E40*预算输入!$C$21 -> 1140 | J15: =预算输入!$C$22 -> 3000 | K15: =IF(MOD(A15,3)=0,预算输入!$C$24/4,0) -> 0 | L15: =IF(OR(A15=8,A15=11),预算输入!$C$25/2,IF(OR(A15=16,A15=22),预算输入!$C$25,0)) -> 10000 | M15: =C15*用量测算!$B$14+D15*用量测算!$B$15+E15*用量测算!$B$16 -> 536.93395 | N15: =IF(A15=1,预算输入!$C$23*0.6,IF(A15=7,预算输入!$C$23*0.4,0)) -> 0 | O15: =SUM(F15:N15)-R15+IF(A15=1,SUM(预算输入!$C$29:$C$31),0) -> 108112.93 | P15: =SUM($O$8:O15) -> 868201.87 | Q15: =SUM(F15:J15)+M15 -> 98112.934 | R15: =MIN(S14,H15+M15) -> 0 | S15: =S14-R15 -> 0 | T15: =H15+M15-R15 -> 1472.934
A16: =9 -> 9 | B16: =DATE(2026,10+A16,1) -> 46569 | C16: =预算输入!B45*预算输入!$C$20*预算输入!$C$33 -> 30 | D16: =预算输入!C45*预算输入!$C$20*预算输入!$C$33 -> 3 | E16: =预算输入!D45*预算输入!$C$20*预算输入!$C$33 -> 10 | F16: =预算输入!$C$9*预算输入!$C$10*(1+预算输入!$C$11) -> 75000 | G16: =预算输入!$C$9*预算输入!$C$12*预算输入!$C$13 -> 17500 | H16: =用量测算!$B$17 -> 936 | I16: =(预算输入!B40+预算输入!C40)*预算输入!D40+预算输入!E40*预算输入!$C$21 -> 1140 | J16: =预算输入!$C$22 -> 3000 | K16: =IF(MOD(A16,3)=0,预算输入!$C$24/4,0) -> 15000 | L16: =IF(OR(A16=8,A16=11),预算输入!$C$25/2,IF(OR(A16=16,A16=22),预算输入!$C$25,0)) -> 0 | M16: =C16*用量测算!$B$14+D16*用量测算!$B$15+E16*用量测算!$B$16 -> 536.93395 | N16: =IF(A16=1,预算输入!$C$23*0.6,IF(A16=7,预算输入!$C$23*0.4,0)) -> 0 | O16: =SUM(F16:N16)-R16+IF(A16=1,SUM(预算输入!$C$29:$C$31),0) -> 113112.93 | P16: =SUM($O$8:O16) -> 981314.8 | Q16: =SUM(F16:J16)+M16 -> 98112.934 | R16: =MIN(S15,H16+M16) -> 0 | S16: =S15-R16 -> 0 | T16: =H16+M16-R16 -> 1472.934
A17: =10 -> 10 | B17: =DATE(2026,10+A17,1) -> 46600 | C17: =预算输入!B46*预算输入!$C$20*预算输入!$C$33 -> 60 | D17: =预算输入!C46*预算输入!$C$20*预算输入!$C$33 -> 6 | E17: =预算输入!D46*预算输入!$C$20*预算输入!$C$33 -> 20 | F17: =预算输入!$C$9*预算输入!$C$10*(1+预算输入!$C$11) -> 75000 | G17: =预算输入!$C$9*预算输入!$C$12*预算输入!$C$13 -> 17500 | H17: =用量测算!$B$17 -> 936 | I17: =(预算输入!B40+预算输入!C40)*预算输入!D40+预算输入!E40*预算输入!$C$21 -> 1140 | J17: =预算输入!$C$22 -> 3000 | K17: =IF(MOD(A17,3)=0,预算输入!$C$24/4,0) -> 0 | L17: =IF(OR(A17=8,A17=11),预算输入!$C$25/2,IF(OR(A17=16,A17=22),预算输入!$C$25,0)) -> 0 | M17: =C17*用量测算!$B$14+D17*用量测算!$B$15+E17*用量测算!$B$16 -> 1073.8679 | N17: =IF(A17=1,预算输入!$C$23*0.6,IF(A17=7,预算输入!$C$23*0.4,0)) -> 0 | O17: =SUM(F17:N17)-R17+IF(A17=1,SUM(预算输入!$C$29:$C$31),0) -> 98649.868 | P17: =SUM($O$8:O17) -> 1079964.7 | Q17: =SUM(F17:J17)+M17 -> 98649.868 | R17: =MIN(S16,H17+M17) -> 0 | S17: =S16-R17 -> 0 | T17: =H17+M17-R17 -> 2009.8679
A18: =11 -> 11 | B18: =DATE(2026,10+A18,1) -> 46631 | C18: =预算输入!B46*预算输入!$C$20*预算输入!$C$33 -> 60 | D18: =预算输入!C46*预算输入!$C$20*预算输入!$C$33 -> 6 | E18: =预算输入!D46*预算输入!$C$20*预算输入!$C$33 -> 20 | F18: =预算输入!$C$9*预算输入!$C$10*(1+预算输入!$C$11) -> 75000 | G18: =预算输入!$C$9*预算输入!$C$12*预算输入!$C$13 -> 17500 | H18: =用量测算!$B$17 -> 936 | I18: =(预算输入!B40+预算输入!C40)*预算输入!D40+预算输入!E40*预算输入!$C$21 -> 1140 | J18: =预算输入!$C$22 -> 3000 | K18: =IF(MOD(A18,3)=0,预算输入!$C$24/4,0) -> 0 | L18: =IF(OR(A18=8,A18=11),预算输入!$C$25/2,IF(OR(A18=16,A18=22),预算输入!$C$25,0)) -> 10000 | M18: =C18*用量测算!$B$14+D18*用量测算!$B$15+E18*用量测算!$B$16 -> 1073.8679 | N18: =IF(A18=1,预算输入!$C$23*0.6,IF(A18=7,预算输入!$C$23*0.4,0)) -> 0 | O18: =SUM(F18:N18)-R18+IF(A18=1,SUM(预算输入!$C$29:$C$31),0) -> 108649.87 | P18: =SUM($O$8:O18) -> 1188614.5 | Q18: =SUM(F18:J18)+M18 -> 98649.868 | R18: =MIN(S17,H18+M18) -> 0 | S18: =S17-R18 -> 0 | T18: =H18+M18-R18 -> 2009.8679
A19: =12 -> 12 | B19: =DATE(2026,10+A19,1) -> 46661 | C19: =预算输入!B46*预算输入!$C$20*预算输入!$C$33 -> 60 | D19: =预算输入!C46*预算输入!$C$20*预算输入!$C$33 -> 6 | E19: =预算输入!D46*预算输入!$C$20*预算输入!$C$33 -> 20 | F19: =预算输入!$C$9*预算输入!$C$10*(1+预算输入!$C$11) -> 75000 | G19: =预算输入!$C$9*预算输入!$C$12*预算输入!$C$13 -> 17500 | H19: =用量测算!$B$17 -> 936 | I19: =(预算输入!B40+预算输入!C40)*预算输入!D40+预算输入!E40*预算输入!$C$21 -> 1140 | J19: =预算输入!$C$22 -> 3000 | K19: =IF(MOD(A19,3)=0,预算输入!$C$24/4,0) -> 15000 | L19: =IF(OR(A19=8,A19=11),预算输入!$C$25/2,IF(OR(A19=16,A19=22),预算输入!$C$25,0)) -> 0 | M19: =C19*用量测算!$B$14+D19*用量测算!$B$15+E19*用量测算!$B$16 -> 1073.8679 | N19: =IF(A19=1,预算输入!$C$23*0.6,IF(A19=7,预算输入!$C$23*0.4,0)) -> 0 | O19: =SUM(F19:N19)-R19+IF(A19=1,SUM(预算输入!$C$29:$C$31),0) -> 113649.87 | P19: =SUM($O$8:O19) -> 1302264.4 | Q19: =SUM(F19:J19)+M19 -> 98649.868 | R19: =MIN(S18,H19+M19) -> 0 | S19: =S18-R19 -> 0 | T19: =H19+M19-R19 -> 2009.8679
A20: =13 -> 13 | B20: =DATE(2026,10+A20,1) -> 46692 | C20: =预算输入!B47*预算输入!$C$20*预算输入!$C$33 -> 120 | D20: =预算输入!C47*预算输入!$C$20*预算输入!$C$33 -> 12 | E20: =预算输入!D47*预算输入!$C$20*预算输入!$C$33 -> 50 | F20: =预算输入!$C$9*预算输入!$C$10*(1+预算输入!$C$11) -> 75000 | G20: =预算输入!$C$9*预算输入!$C$12*预算输入!$C$13 -> 17500 | H20: =用量测算!$B$17 -> 936 | I20: =(预算输入!B41+预算输入!C41)*预算输入!D41+预算输入!E41*预算输入!$C$21 -> 1990 | J20: =预算输入!$C$22 -> 3000 | K20: =IF(MOD(A20,3)=0,预算输入!$C$24/4,0) -> 0 | L20: =IF(OR(A20=8,A20=11),预算输入!$C$25/2,IF(OR(A20=16,A20=22),预算输入!$C$25,0)) -> 0 | M20: =C20*用量测算!$B$14+D20*用量测算!$B$15+E20*用量测算!$B$16 -> 2522.1358 | N20: =IF(A20=1,预算输入!$C$23*0.6,IF(A20=7,预算输入!$C$23*0.4,0)) -> 0 | O20: =SUM(F20:N20)-R20+IF(A20=1,SUM(预算输入!$C$29:$C$31),0) -> 100948.14 | P20: =SUM($O$8:O20) -> 1403212.5 | Q20: =SUM(F20:J20)+M20 -> 100948.14 | R20: =MIN(S19,H20+M20) -> 0 | S20: =S19-R20 -> 0 | T20: =H20+M20-R20 -> 3458.1358
A21: =14 -> 14 | B21: =DATE(2026,10+A21,1) -> 46722 | C21: =预算输入!B47*预算输入!$C$20*预算输入!$C$33 -> 120 | D21: =预算输入!C47*预算输入!$C$20*预算输入!$C$33 -> 12 | E21: =预算输入!D47*预算输入!$C$20*预算输入!$C$33 -> 50 | F21: =预算输入!$C$9*预算输入!$C$10*(1+预算输入!$C$11) -> 75000 | G21: =预算输入!$C$9*预算输入!$C$12*预算输入!$C$13 -> 17500 | H21: =用量测算!$B$17 -> 936 | I21: =(预算输入!B41+预算输入!C41)*预算输入!D41+预算输入!E41*预算输入!$C$21 -> 1990 | J21: =预算输入!$C$22 -> 3000 | K21: =IF(MOD(A21,3)=0,预算输入!$C$24/4,0) -> 0 | L21: =IF(OR(A21=8,A21=11),预算输入!$C$25/2,IF(OR(A21=16,A21=22),预算输入!$C$25,0)) -> 0 | M21: =C21*用量测算!$B$14+D21*用量测算!$B$15+E21*用量测算!$B$16 -> 2522.1358 | N21: =IF(A21=1,预算输入!$C$23*0.6,IF(A21=7,预算输入!$C$23*0.4,0)) -> 0 | O21: =SUM(F21:N21)-R21+IF(A21=1,SUM(预算输入!$C$29:$C$31),0) -> 100948.14 | P21: =SUM($O$8:O21) -> 1504160.7 | Q21: =SUM(F21:J21)+M21 -> 100948.14 | R21: =MIN(S20,H21+M21) -> 0 | S21: =S20-R21 -> 0 | T21: =H21+M21-R21 -> 3458.1358
A22: =15 -> 15 | B22: =DATE(2026,10+A22,1) -> 46753 | C22: =预算输入!B47*预算输入!$C$20*预算输入!$C$33 -> 120 | D22: =预算输入!C47*预算输入!$C$20*预算输入!$C$33 -> 12 | E22: =预算输入!D47*预算输入!$C$20*预算输入!$C$33 -> 50 | F22: =预算输入!$C$9*预算输入!$C$10*(1+预算输入!$C$11) -> 75000 | G22: =预算输入!$C$9*预算输入!$C$12*预算输入!$C$13 -> 17500 | H22: =用量测算!$B$17 -> 936 | I22: =(预算输入!B41+预算输入!C41)*预算输入!D41+预算输入!E41*预算输入!$C$21 -> 1990 | J22: =预算输入!$C$22 -> 3000 | K22: =IF(MOD(A22,3)=0,预算输入!$C$24/4,0) -> 15000 | L22: =IF(OR(A22=8,A22=11),预算输入!$C$25/2,IF(OR(A22=16,A22=22),预算输入!$C$25,0)) -> 0 | M22: =C22*用量测算!$B$14+D22*用量测算!$B$15+E22*用量测算!$B$16 -> 2522.1358 | N22: =IF(A22=1,预算输入!$C$23*0.6,IF(A22=7,预算输入!$C$23*0.4,0)) -> 0 | O22: =SUM(F22:N22)-R22+IF(A22=1,SUM(预算输入!$C$29:$C$31),0) -> 115948.14 | P22: =SUM($O$8:O22) -> 1620108.8 | Q22: =SUM(F22:J22)+M22 -> 100948.14 | R22: =MIN(S21,H22+M22) -> 0 | S22: =S21-R22 -> 0 | T22: =H22+M22-R22 -> 3458.1358
A23: =16 -> 16 | B23: =DATE(2026,10+A23,1) -> 46784 | C23: =预算输入!B47*预算输入!$C$20*预算输入!$C$33 -> 120 | D23: =预算输入!C47*预算输入!$C$20*预算输入!$C$33 -> 12 | E23: =预算输入!D47*预算输入!$C$20*预算输入!$C$33 -> 50 | F23: =预算输入!$C$9*预算输入!$C$10*(1+预算输入!$C$11) -> 75000 | G23: =预算输入!$C$9*预算输入!$C$12*预算输入!$C$13 -> 17500 | H23: =用量测算!$B$17 -> 936 | I23: =(预算输入!B41+预算输入!C41)*预算输入!D41+预算输入!E41*预算输入!$C$21 -> 1990 | J23: =预算输入!$C$22 -> 3000 | K23: =IF(MOD(A23,3)=0,预算输入!$C$24/4,0) -> 0 | L23: =IF(OR(A23=8,A23=11),预算输入!$C$25/2,IF(OR(A23=16,A23=22),预算输入!$C$25,0)) -> 20000 | M23: =C23*用量测算!$B$14+D23*用量测算!$B$15+E23*用量测算!$B$16 -> 2522.1358 | N23: =IF(A23=1,预算输入!$C$23*0.6,IF(A23=7,预算输入!$C$23*0.4,0)) -> 0 | O23: =SUM(F23:N23)-R23+IF(A23=1,SUM(预算输入!$C$29:$C$31),0) -> 120948.14 | P23: =SUM($O$8:O23) -> 1741056.9 | Q23: =SUM(F23:J23)+M23 -> 100948.14 | R23: =MIN(S22,H23+M23) -> 0 | S23: =S22-R23 -> 0 | T23: =H23+M23-R23 -> 3458.1358
A24: =17 -> 17 | B24: =DATE(2026,10+A24,1) -> 46813 | C24: =预算输入!B47*预算输入!$C$20*预算输入!$C$33 -> 120 | D24: =预算输入!C47*预算输入!$C$20*预算输入!$C$33 -> 12 | E24: =预算输入!D47*预算输入!$C$20*预算输入!$C$33 -> 50 | F24: =预算输入!$C$9*预算输入!$C$10*(1+预算输入!$C$11) -> 75000 | G24: =预算输入!$C$9*预算输入!$C$12*预算输入!$C$13 -> 17500 | H24: =用量测算!$B$17 -> 936 | I24: =(预算输入!B41+预算输入!C41)*预算输入!D41+预算输入!E41*预算输入!$C$21 -> 1990 | J24: =预算输入!$C$22 -> 3000 | K24: =IF(MOD(A24,3)=0,预算输入!$C$24/4,0) -> 0 | L24: =IF(OR(A24=8,A24=11),预算输入!$C$25/2,IF(OR(A24=16,A24=22),预算输入!$C$25,0)) -> 0 | M24: =C24*用量测算!$B$14+D24*用量测算!$B$15+E24*用量测算!$B$16 -> 2522.1358 | N24: =IF(A24=1,预算输入!$C$23*0.6,IF(A24=7,预算输入!$C$23*0.4,0)) -> 0 | O24: =SUM(F24:N24)-R24+IF(A24=1,SUM(预算输入!$C$29:$C$31),0) -> 100948.14 | P24: =SUM($O$8:O24) -> 1842005.1 | Q24: =SUM(F24:J24)+M24 -> 100948.14 | R24: =MIN(S23,H24+M24) -> 0 | S24: =S23-R24 -> 0 | T24: =H24+M24-R24 -> 3458.1358
A25: =18 -> 18 | B25: =DATE(2026,10+A25,1) -> 46844 | C25: =预算输入!B47*预算输入!$C$20*预算输入!$C$33 -> 120 | D25: =预算输入!C47*预算输入!$C$20*预算输入!$C$33 -> 12 | E25: =预算输入!D47*预算输入!$C$20*预算输入!$C$33 -> 50 | F25: =预算输入!$C$9*预算输入!$C$10*(1+预算输入!$C$11) -> 75000 | G25: =预算输入!$C$9*预算输入!$C$12*预算输入!$C$13 -> 17500 | H25: =用量测算!$B$17 -> 936 | I25: =(预算输入!B41+预算输入!C41)*预算输入!D41+预算输入!E41*预算输入!$C$21 -> 1990 | J25: =预算输入!$C$22 -> 3000 | K25: =IF(MOD(A25,3)=0,预算输入!$C$24/4,0) -> 15000 | L25: =IF(OR(A25=8,A25=11),预算输入!$C$25/2,IF(OR(A25=16,A25=22),预算输入!$C$25,0)) -> 0 | M25: =C25*用量测算!$B$14+D25*用量测算!$B$15+E25*用量测算!$B$16 -> 2522.1358 | N25: =IF(A25=1,预算输入!$C$23*0.6,IF(A25=7,预算输入!$C$23*0.4,0)) -> 0 | O25: =SUM(F25:N25)-R25+IF(A25=1,SUM(预算输入!$C$29:$C$31),0) -> 115948.14 | P25: =SUM($O$8:O25) -> 1957953.2 | Q25: =SUM(F25:J25)+M25 -> 100948.14 | R25: =MIN(S24,H25+M25) -> 0 | S25: =S24-R25 -> 0 | T25: =H25+M25-R25 -> 3458.1358
A26: =19 -> 19 | B26: =DATE(2026,10+A26,1) -> 46874 | C26: =预算输入!B48*预算输入!$C$20*预算输入!$C$33 -> 240 | D26: =预算输入!C48*预算输入!$C$20*预算输入!$C$33 -> 24 | E26: =预算输入!D48*预算输入!$C$20*预算输入!$C$33 -> 100 | F26: =预算输入!$C$9*预算输入!$C$10*(1+预算输入!$C$11) -> 75000 | G26: =预算输入!$C$9*预算输入!$C$12*预算输入!$C$13 -> 17500 | H26: =用量测算!$B$17 -> 936 | I26: =(预算输入!B41+预算输入!C41)*预算输入!D41+预算输入!E41*预算输入!$C$21 -> 1990 | J26: =预算输入!$C$22 -> 3000 | K26: =IF(MOD(A26,3)=0,预算输入!$C$24/4,0) -> 0 | L26: =IF(OR(A26=8,A26=11),预算输入!$C$25/2,IF(OR(A26=16,A26=22),预算输入!$C$25,0)) -> 0 | M26: =C26*用量测算!$B$14+D26*用量测算!$B$15+E26*用量测算!$B$16 -> 5044.2716 | N26: =IF(A26=1,预算输入!$C$23*0.6,IF(A26=7,预算输入!$C$23*0.4,0)) -> 0 | O26: =SUM(F26:N26)-R26+IF(A26=1,SUM(预算输入!$C$29:$C$31),0) -> 103470.27 | P26: =SUM($O$8:O26) -> 2061423.5 | Q26: =SUM(F26:J26)+M26 -> 103470.27 | R26: =MIN(S25,H26+M26) -> 0 | S26: =S25-R26 -> 0 | T26: =H26+M26-R26 -> 5980.2716
A27: =20 -> 20 | B27: =DATE(2026,10+A27,1) -> 46905 | C27: =预算输入!B48*预算输入!$C$20*预算输入!$C$33 -> 240 | D27: =预算输入!C48*预算输入!$C$20*预算输入!$C$33 -> 24 | E27: =预算输入!D48*预算输入!$C$20*预算输入!$C$33 -> 100 | F27: =预算输入!$C$9*预算输入!$C$10*(1+预算输入!$C$11) -> 75000 | G27: =预算输入!$C$9*预算输入!$C$12*预算输入!$C$13 -> 17500 | H27: =用量测算!$B$17 -> 936 | I27: =(预算输入!B41+预算输入!C41)*预算输入!D41+预算输入!E41*预算输入!$C$21 -> 1990 | J27: =预算输入!$C$22 -> 3000 | K27: =IF(MOD(A27,3)=0,预算输入!$C$24/4,0) -> 0 | L27: =IF(OR(A27=8,A27=11),预算输入!$C$25/2,IF(OR(A27=16,A27=22),预算输入!$C$25,0)) -> 0 | M27: =C27*用量测算!$B$14+D27*用量测算!$B$15+E27*用量测算!$B$16 -> 5044.2716 | N27: =IF(A27=1,预算输入!$C$23*0.6,IF(A27=7,预算输入!$C$23*0.4,0)) -> 0 | O27: =SUM(F27:N27)-R27+IF(A27=1,SUM(预算输入!$C$29:$C$31),0) -> 103470.27 | P27: =SUM($O$8:O27) -> 2164893.8 | Q27: =SUM(F27:J27)+M27 -> 103470.27 | R27: =MIN(S26,H27+M27) -> 0 | S27: =S26-R27 -> 0 | T27: =H27+M27-R27 -> 5980.2716
A28: =21 -> 21 | B28: =DATE(2026,10+A28,1) -> 46935 | C28: =预算输入!B48*预算输入!$C$20*预算输入!$C$33 -> 240 | D28: =预算输入!C48*预算输入!$C$20*预算输入!$C$33 -> 24 | E28: =预算输入!D48*预算输入!$C$20*预算输入!$C$33 -> 100 | F28: =预算输入!$C$9*预算输入!$C$10*(1+预算输入!$C$11) -> 75000 | G28: =预算输入!$C$9*预算输入!$C$12*预算输入!$C$13 -> 17500 | H28: =用量测算!$B$17 -> 936 | I28: =(预算输入!B41+预算输入!C41)*预算输入!D41+预算输入!E41*预算输入!$C$21 -> 1990 | J28: =预算输入!$C$22 -> 3000 | K28: =IF(MOD(A28,3)=0,预算输入!$C$24/4,0) -> 15000 | L28: =IF(OR(A28=8,A28=11),预算输入!$C$25/2,IF(OR(A28=16,A28=22),预算输入!$C$25,0)) -> 0 | M28: =C28*用量测算!$B$14+D28*用量测算!$B$15+E28*用量测算!$B$16 -> 5044.2716 | N28: =IF(A28=1,预算输入!$C$23*0.6,IF(A28=7,预算输入!$C$23*0.4,0)) -> 0 | O28: =SUM(F28:N28)-R28+IF(A28=1,SUM(预算输入!$C$29:$C$31),0) -> 118470.27 | P28: =SUM($O$8:O28) -> 2283364 | Q28: =SUM(F28:J28)+M28 -> 103470.27 | R28: =MIN(S27,H28+M28) -> 0 | S28: =S27-R28 -> 0 | T28: =H28+M28-R28 -> 5980.2716
A29: =22 -> 22 | B29: =DATE(2026,10+A29,1) -> 46966 | C29: =预算输入!B48*预算输入!$C$20*预算输入!$C$33 -> 240 | D29: =预算输入!C48*预算输入!$C$20*预算输入!$C$33 -> 24 | E29: =预算输入!D48*预算输入!$C$20*预算输入!$C$33 -> 100 | F29: =预算输入!$C$9*预算输入!$C$10*(1+预算输入!$C$11) -> 75000 | G29: =预算输入!$C$9*预算输入!$C$12*预算输入!$C$13 -> 17500 | H29: =用量测算!$B$17 -> 936 | I29: =(预算输入!B41+预算输入!C41)*预算输入!D41+预算输入!E41*预算输入!$C$21 -> 1990 | J29: =预算输入!$C$22 -> 3000 | K29: =IF(MOD(A29,3)=0,预算输入!$C$24/4,0) -> 0 | L29: =IF(OR(A29=8,A29=11),预算输入!$C$25/2,IF(OR(A29=16,A29=22),预算输入!$C$25,0)) -> 20000 | M29: =C29*用量测算!$B$14+D29*用量测算!$B$15+E29*用量测算!$B$16 -> 5044.2716 | N29: =IF(A29=1,预算输入!$C$23*0.6,IF(A29=7,预算输入!$C$23*0.4,0)) -> 0 | O29: =SUM(F29:N29)-R29+IF(A29=1,SUM(预算输入!$C$29:$C$31),0) -> 123470.27 | P29: =SUM($O$8:O29) -> 2406834.3 | Q29: =SUM(F29:J29)+M29 -> 103470.27 | R29: =MIN(S28,H29+M29) -> 0 | S29: =S28-R29 -> 0 | T29: =H29+M29-R29 -> 5980.2716
A30: =23 -> 23 | B30: =DATE(2026,10+A30,1) -> 46997 | C30: =预算输入!B48*预算输入!$C$20*预算输入!$C$33 -> 240 | D30: =预算输入!C48*预算输入!$C$20*预算输入!$C$33 -> 24 | E30: =预算输入!D48*预算输入!$C$20*预算输入!$C$33 -> 100 | F30: =预算输入!$C$9*预算输入!$C$10*(1+预算输入!$C$11) -> 75000 | G30: =预算输入!$C$9*预算输入!$C$12*预算输入!$C$13 -> 17500 | H30: =用量测算!$B$17 -> 936 | I30: =(预算输入!B41+预算输入!C41)*预算输入!D41+预算输入!E41*预算输入!$C$21 -> 1990 | J30: =预算输入!$C$22 -> 3000 | K30: =IF(MOD(A30,3)=0,预算输入!$C$24/4,0) -> 0 | L30: =IF(OR(A30=8,A30=11),预算输入!$C$25/2,IF(OR(A30=16,A30=22),预算输入!$C$25,0)) -> 0 | M30: =C30*用量测算!$B$14+D30*用量测算!$B$15+E30*用量测算!$B$16 -> 5044.2716 | N30: =IF(A30=1,预算输入!$C$23*0.6,IF(A30=7,预算输入!$C$23*0.4,0)) -> 0 | O30: =SUM(F30:N30)-R30+IF(A30=1,SUM(预算输入!$C$29:$C$31),0) -> 103470.27 | P30: =SUM($O$8:O30) -> 2510304.6 | Q30: =SUM(F30:J30)+M30 -> 103470.27 | R30: =MIN(S29,H30+M30) -> 0 | S30: =S29-R30 -> 0 | T30: =H30+M30-R30 -> 5980.2716
A31: =24 -> 24 | B31: =DATE(2026,10+A31,1) -> 47027 | C31: =预算输入!B48*预算输入!$C$20*预算输入!$C$33 -> 240 | D31: =预算输入!C48*预算输入!$C$20*预算输入!$C$33 -> 24 | E31: =预算输入!D48*预算输入!$C$20*预算输入!$C$33 -> 100 | F31: =预算输入!$C$9*预算输入!$C$10*(1+预算输入!$C$11) -> 75000 | G31: =预算输入!$C$9*预算输入!$C$12*预算输入!$C$13 -> 17500 | H31: =用量测算!$B$17 -> 936 | I31: =(预算输入!B41+预算输入!C41)*预算输入!D41+预算输入!E41*预算输入!$C$21 -> 1990 | J31: =预算输入!$C$22 -> 3000 | K31: =IF(MOD(A31,3)=0,预算输入!$C$24/4,0) -> 15000 | L31: =IF(OR(A31=8,A31=11),预算输入!$C$25/2,IF(OR(A31=16,A31=22),预算输入!$C$25,0)) -> 0 | M31: =C31*用量测算!$B$14+D31*用量测算!$B$15+E31*用量测算!$B$16 -> 5044.2716 | N31: =IF(A31=1,预算输入!$C$23*0.6,IF(A31=7,预算输入!$C$23*0.4,0)) -> 0 | O31: =SUM(F31:N31)-R31+IF(A31=1,SUM(预算输入!$C$29:$C$31),0) -> 118470.27 | P31: =SUM($O$8:O31) -> 2628774.9 | Q31: =SUM(F31:J31)+M31 -> 103470.27 | R31: =MIN(S30,H31+M31) -> 0 | S31: =S30-R31 -> 0 | T31: =H31+M31-R31 -> 5980.2716

Sheet 用量测算
A1: 研发订阅与产品API分开计算
A4: 指标 | B4: 值 | C4: 单位 | D4: 依据
A5: 短任务累计输入 | B5: 76845 | C5: Token | D5: U1：10任务、30响应
A6: 短任务累计输出 | B6: 5738 | C6: Token | D6: 含有回执的输出；覆盖不完整
A7: 有回执任务数 | B7: 10 | C7: 任务 | D7: 非完整课堂或长Agent样本
A8: 有回执响应数 | B8: 30 | C8: 响应 | D8: 不推断未知失败请求免费
A9: Pro峰时未缓存输入价 | B9: 9 | C9: 元/百万Token | D9: D1，2026-10-10
A10: Pro峰时输出价 | B10: 27 | C10: 元/百万Token | D10: D1，2026-10-10
A11: 短任务重定价 | B11: =(B5*B9+B6*B10)/1000000/B7 -> 0.0846531 | C11: 元/任务 | D11: 样本Token×当前官网价
A12: 学生短任务频次 | B12: 40 | C12: 任务/人月 | D12: 频次假设
A13: 教师短任务频次 | B13: 240 | C13: 任务/人月 | D13: 频次假设
A14: 学生月模型成本 | B14: =B11*B12 -> 3.386124 | C14: 元/人月 | D14: 短任务×假设频次
A15: 教师月模型成本 | B15: =B11*B13 -> 20.316744 | C15: 元/人月 | D15: 短任务×假设频次
A16: 专业月模型成本 | B16: =预算输入!C18*预算输入!C19*(预算输入!C16*B9+预算输入!C17*B10)/1000000 -> 37.44 | C16: 元/人月 | D16: 任务×调用×输入/输出单价，未实测
A17: 团队研发API月成本 | B17: =预算输入!C9*预算输入!C14*预算输入!C15*(预算输入!C16*B9+预算输入!C17*B10)/1000000 -> 936 | C17: 元/月 | D17: 5人测试，不包含Pro订阅
A20: 基准专业情景：20任务/月×8调用/任务×每调用2万输入、2千输出，按Pro峰时无缓存价得到37.44元/月。高投入情景100任务×32调用为748.80元/月。两者是任务强度假设；既有短任务不能证明长任务成本。缓存、空闲折扣不预先抵减；图片、检索等新增收费另录入。

Sheet 定价与利润
A1: 拟定套餐：收入、模型成本与贡献利润
A3: 套餐暂未开放购买；贡献利润用于覆盖研发与运营，不能等同净利润。积分与Token折算尚待公布。
A5: 成本元/积分假设 | B5: 0.02
A6: 额度使用比例 | B6: 1
A7: 其他可变费用率 | B7: 0.1
A8: 目标贡献率假设 | B8: 0.5
A10: 套餐 | B10: 收入元 | C10: 积分额度 | D10: 模型成本元 | E10: 其他可变费元 | F10: 贡献利润元 | G10: 贡献率 | H10: 目标成本上限
A11: 标准月度 | B11: 99 | C11: 2000 | D11: =C11*$B$5*$B$6 -> 40 | E11: =B11*$B$7 -> 9.9 | F11: =B11-D11-E11 -> 49.1 | G11: =F11/B11 -> 0.4959596 | H11: =(B11*(1-$B$7-$B$8))/(C11*$B$6) -> 0.0198
A12: 进阶月度 | B12: 199 | C12: 4500 | D12: =C12*$B$5*$B$6 -> 90 | E12: =B12*$B$7 -> 19.9 | F12: =B12-D12-E12 -> 89.1 | G12: =F12/B12 -> 0.44773869 | H12: =(B12*(1-$B$7-$B$8))/(C12*$B$6) -> 0.017688889
A13: 专业月度 | B13: 999 | C13: 25000 | D13: =C13*$B$5*$B$6 -> 500 | E13: =B13*$B$7 -> 99.9 | F13: =B13-D13-E13 -> 399.1 | G13: =F13/B13 -> 0.3994995 | H13: =(B13*(1-$B$7-$B$8))/(C13*$B$6) -> 0.015984
A14: 加量30天 | B14: 50 | C14: 1000 | D14: =C14*$B$5*$B$6 -> 20 | E14: =B14*$B$7 -> 5 | F14: =B14-D14-E14 -> 25 | G14: =F14/B14 -> 0.5 | H14: =(B14*(1-$B$7-$B$8))/(C14*$B$6) -> 0.02
A17: 例：99元收入－40元模型成本－9.90元其他可变费＝49.10元贡献利润。0.02元/积分与10%费用均为测算假设，未与真实扣分映射；把B5改为0.04可查看高成本结果。逐模型费率、账单与任务结果明确后再决定售价和额度。月额度当期有效、不结转；BYOK、组织服务和未来应用订阅独立核算。

Sheet 来源与口径
A1: 官方核价与事实边界 · 2026-10-10
A4: ID | B4: 来源 | C4: 采用内容 | D4: 公开出处 | E4: 核对日 | F4: 性质
A5: O1 | B5: OpenAI Pro | C5: 500 USD / 席 / 月；月付，不保证50倍额度 | D5: https://learn.chatgpt.com/docs/pricing | E5: 2026-10-10 | F5: 官方价格
A6: O2 | B6: Pro套餐与用量限制 | C6: 100 / 200 / 500 USD；额外使用可能需加购 | D6: https://help.openai.com/en/articles/9793128-about-chatgpt-pro-tiers | E6: 2026-10-10 | F6: 官方说明
A7: D1 | B7: DeepSeek Pro峰时 | C7: 未命中输入9、输出27元 / 百万Token | D7: https://api-docs.deepseek.com/zh-cn/quick_start/pricing/ | E7: 2026-10-10 | F7: 官方价格
A8: D2 | B8: DeepSeek Flash峰时 | C8: 未命中输入2、输出8元 / 百万Token | D8: https://api-docs.deepseek.com/zh-cn/quick_start/pricing/ | E8: 2026-10-10 | F8: 备选价格；非质量等效承诺
A9: C1 | B9: 腾讯云内地轻量实例 | C9: 2核4GB 80元/月；4核8GB 230元/月 | D9: https://cloud.tencent.com/document/product/1207/119345 | E9: 2026-10-10 | F9: 刊例价；下单复核地域与配置
A10: W1 | B10: 国家统计局2025年工资 | C10: 私营软件信息业年均128166元；非私营248752元 | D10: https://www.stats.gov.cn/sj/zxfb/202605/t20260515_1963707.html | E10: 2026-10-10 | F10: 数量级参照；非本团队报价
A11: U1 | B11: 历史短任务回执 | C11: 10任务30响应；输入76845、输出5738 Token | D11: Blocky历史公开汇总样本，2026-10-02 | E11: 2026-10-10 | F11: 实测样本；失败及缓存覆盖不完整
A12: A1 | B12: 预算假设 | C12: 工资、附加成本、汇率、调用轮数、试用规模及其他费用可调整 | D12: 本规划输入；不代表合同、工资账本或实际用户 | E12: 2026-10-10 | F12: 假设
A14: 原900万元来自更大后期用户规模和工具使用成本参照，不是本团队当前账单。新模型按5人团队和近期任务采购；历史10任务Token仅支持短任务估算。工资、客户合同、供应商合作费和真实长任务成本尚未确认。软件规划仍涵盖教育、专业、OPC和企业；预算期和能力开放按实际关口调整。
