Workbook

Sheet Summary
A1: Blocky Studio｜24个月持续发展资金规划｜人民币
A2: 建设目标：个人开源、教育组织后台、多端、Agent App与社区；未报价参数均是规划假设。
B4: 精简推进 | C4: 基准建设 | D4: 高用量压力
A5: 期末平台云算力活跃人头 | B5: =Cohorts!Y6 -> 464 | C5: =Cohorts!Y20 -> 1160 | D5: =Cohorts!Y34 -> 2320
A6: 用户Token采购（24月） | B6: =SUM(Costs!B11:Y11) -> 913809.77 | C6: =SUM(Costs!B36:Y36) -> 3046032.6 | D6: =SUM(Costs!B61:Y61) -> 15230163
A7: 研发工具与内部算力 | B7: =SUM(Costs!B5:Y5) -> 95348.811 | C7: =SUM(Costs!B30:Y30) -> 173361.47 | D7: =SUM(Costs!B55:Y55) -> 329386.8
A8: 等效人力综合现金 | B8: =SUM(Costs!B4:Y4) -> 1056000 | C8: =SUM(Costs!B29:Y29) -> 1800000 | D8: =SUM(Costs!B54:Y54) -> 2736000
A9: 其他常规与专项运营 | B9: =SUM(Costs!B17:Y17)-B7-B8 -> 474750 | C9: =SUM(Costs!B42:Y42)-C7-C8 -> 633000 | D9: =SUM(Costs!B67:Y67)-D7-D8 -> 949500
A10: 设备现金 | B10: =SUM(Costs!B14:Y14) -> 60000 | C10: =SUM(Costs!B39:Y39) -> 80000 | D10: =SUM(Costs!B64:Y64) -> 120000
A11: 24个月现金支付总额 | B11: =SUM('Cash Flow'!B15:Y15) -> 2599908.6 | C11: =SUM('Cash Flow'!B48:Y48) -> 5732394 | D11: =SUM('Cash Flow'!B81:Y81) -> 19365050
A12: 规划收款（默认不抵减） | B12: =SUM(Revenue!B5:Y5) -> 0 | C12: =SUM(Revenue!B17:Y17) -> 0 | D12: =SUM(Revenue!B29:Y29) -> 0
A13: 确认自有现金（未录入） | B13: =Assumptions!$B$4 -> 0 | C13: =Assumptions!$B$4 -> 0 | D13: =Assumptions!$B$4 -> 0
A14: 峰值现金缺口 | B14: =MAX(0,-MIN('Cash Flow'!B17:Y17)) -> 2599908.6 | C14: =MAX(0,-MIN('Cash Flow'!B50:Y50)) -> 5732394 | D14: =MAX(0,-MIN('Cash Flow'!B83:Y83)) -> 19365050
A15: 常规支出风险预留 | B15: =SUM(Costs!B17:Y17)*Assumptions!B$24 -> 162609.88 | C15: =SUM(Costs!B42:Y42)*Assumptions!C$24 -> 260636.15 | D15: =SUM(Costs!B67:Y67)*Assumptions!D$24 -> 602233.02
A16: 未使用厂商合作现金预留 | B16: =MAX(0,Assumptions!B$23-SUM(Costs!B12:Y12)-'Cash Flow'!Y21-'Cash Flow'!Y22) -> 100000 | C16: =MAX(0,Assumptions!C$23-SUM(Costs!B37:Y37)-'Cash Flow'!Y54-'Cash Flow'!Y55) -> 300000 | D16: =MAX(0,Assumptions!D$23-SUM(Costs!B62:Y62)-'Cash Flow'!Y87-'Cash Flow'!Y88) -> 800000
A17: 正常运营现金储备 | B17: =Assumptions!B$25*(Costs!Y18+Costs!Y11*(1-Assumptions!$B$5)) -> 824586.72 | C17: =Assumptions!C$25*(Costs!Y43+Costs!Y36*(1-Assumptions!$B$5)) -> 2371396.9 | D17: =Assumptions!D$25*(Costs!Y68+Costs!Y61*(1-Assumptions!$B$5)) -> 10671751
A18: 最低追加资金需求 | B18: =SUM(B14:B17) -> 3687105.2 | C18: =SUM(C14:C17) -> 8664427.1 | D18: =SUM(D14:D17) -> 31439033
A19: 建议资金规划目标（取整） | B19: =ROUNDUP(B18/Assumptions!$B$12,0)*Assumptions!$B$12 -> 4000000 | C19: =ROUNDUP(C18/Assumptions!$B$12,0)*Assumptions!$B$12 -> 9000000 | D19: =ROUNDUP(D18/Assumptions!$B$12,0)*Assumptions!$B$12 -> 31500000
A20: 假设足额补资的期末现金 | B20: ='Cash Flow'!Y20 -> 1400091.4 | C20: ='Cash Flow'!Y53 -> 3267606 | D20: ='Cash Flow'!Y86 -> 12134950
A21: 期末单月用户Token成本 | B21: =Costs!Y11 -> 203028.2 | C21: =Costs!Y36 -> 676760.68 | D21: =Costs!Y61 -> 3383803.4
A22: 峰值缺口月份 | B22: =TEXT(INDEX('Cash Flow'!B2:Y2,1,MATCH(MIN('Cash Flow'!B17:Y17),'Cash Flow'!B17:Y17,0)),"yyyy-mm") -> 2028-10 | C22: =TEXT(INDEX('Cash Flow'!B35:Y35,1,MATCH(MIN('Cash Flow'!B50:Y50),'Cash Flow'!B50:Y50,0)),"yyyy-mm") -> 2028-10 | D22: =TEXT(INDEX('Cash Flow'!B68:Y68,1,MATCH(MIN('Cash Flow'!B83:Y83),'Cash Flow'!B83:Y83,0)),"yyyy-mm") -> 2028-10
A24: 默认成本回收率0：只表示未确认收入不用于压低资金，不能解释为实际商业收入为零。
A26: 厂商费用0表示未录入；现金预留是风险预算，获得报价后更新费、预付和保证金。
A28: 精简与高用量同时改变人力、人数和成本，是资源情景；新增用量须有额度与回款支持。

Sheet Assumptions
A1: 人民币；蓝色为可调输入，全部未证实金额与规模是规划假设
A2: 规划月数 | B2: 24
A3: 起始月份（假设） | B3: 46327
A4: 已确认自有现金（未录入为0） | B4: 0
A5: 算力成本回收比例（非套餐价） | B5: 0
A6: 收款延迟月数 | B6: 0
A7: 非退还合作费（报价未录入） | B7: 0
A8: 可抵扣算力预付（报价未录入） | B8: 0
A9: 可退保证金（报价未录入） | B9: 0
A10: 厂商款支付月份 | B10: 6
A11: 设备折旧月数 | B11: 36
A12: 资金目标取整步长（元） | B12: 500000
A14: 费用与人数均是条件预算；厂商条款、实际自有资金及算力售价未确认。0表示未录入；真实场景在产品准备关口后，未确认收入不抵减资金。
B16: 精简推进 | C16: 基准建设 | D16: 高用量压力
A17: 前6月等效人力 | B17: 2 | C17: 3 | D17: 4
A18: 后18月等效人力 | B18: 3 | C18: 4 | D18: 5
A19: 综合人月成本（元） | B19: 16000 | C19: 20000 | D19: 24000
A20: 平台云用户规模倍率 | B20: 0.4 | C20: 1 | D20: 2
A21: 人均算力成本倍率 | B21: 0.75 | C21: 1 | D21: 2.5
A22: 其他建设成本倍率 | B22: 0.75 | C22: 1 | D22: 1.5
A23: 厂商合作现金预留（元） | B23: 100000 | C23: 300000 | D23: 800000
A24: 常规支出风险预留比例 | B24: 0.1 | C24: 0.1 | D24: 0.15
A25: 期末正常运营储备月数 | B25: 3 | C25: 3 | D25: 3
A29: 学生短任务参考月成本 | B29: =Usage!B19 -> 3.386124
A30: 教师短任务参考月成本 | B30: =Usage!B20 -> 20.316744
A31: 专业云创作者参考月成本 | B31: =Usage!B21 -> 1347.02
A32: 研发等效人力月度Agent预算 | B32: =Usage!B22 -> 1926.2386
A34: 基础设施前6月/月 | B34: 3000
A35: 基础设施第7至12月/月 | B35: 6000
A36: 基础设施后12月/月 | B36: 9000
A37: 教学共创前3月/月 | B37: 0
A38: 教学共创第4至12月/月 | B38: 6000
A39: 教学共创后12月/月 | B39: 8000
A40: 社区前3月/月 | B40: 0
A41: 社区第4至12月/月 | B41: 3000
A42: 社区后12月/月 | B42: 6000
A43: 一般运营/月 | B43: 3000
A46: 月序 | B46: 学生云活跃人数 | C46: 教师云活跃人数 | D46: 个人云活跃人数 | F46: 专项外部交付月份 | G46: 专项支出
A47: 1 | B47: 0 | C47: 0 | D47: 0 | F47: 6 | G47: 30000
A48: 2 | B48: 0 | C48: 0 | D48: 0 | F48: 12 | G48: 40000
A49: 3 | B49: 0 | C49: 0 | D49: 0 | F49: 18 | G49: 40000
A50: 4 | B50: 0 | C50: 0 | D50: 0 | F50: 24 | G50: 40000
A51: 5 | B51: 0 | C51: 0 | D51: 0
A52: 6 | B52: 0 | C52: 0 | D52: 0
A53: 7 | B53: 0 | C53: 0 | D53: 0 | F53: 设备采购月份 | G53: 设备现金
A54: 8 | B54: 0 | C54: 0 | D54: 0 | F54: 1 | G54: 50000
A55: 9 | B55: 0 | C55: 0 | D55: 0 | F55: 7 | G55: 30000
A56: 10 | B56: 0 | C56: 0 | D56: 0
A57: 11 | B57: 0 | C57: 0 | D57: 0
A58: 12 | B58: 0 | C58: 0 | D58: 0
A59: 13 | B59: 0 | C59: 0 | D59: 0
A60: 14 | B60: 0 | C60: 0 | D60: 0
A61: 15 | B61: 0 | C61: 0 | D61: 0
A62: 16 | B62: 0 | C62: 0 | D62: 0
A63: 17 | B63: 0 | C63: 0 | D63: 0
A64: 18 | B64: 0 | C64: 0 | D64: 0
A65: 19 | B65: 300 | C65: 40 | D65: 250
A66: 20 | B66: 300 | C66: 40 | D66: 250
A67: 21 | B67: 300 | C67: 40 | D67: 250
... A70: 24 | B70: 600 | C70: 60 | D70: 500

Sheet Usage
A1: Token成本：项目短任务样本与专业开发者公开统计分开使用
A3: 有回执的任务数 | B3: 10
A4: 实际响应数 | B4: 30
A5: 美元兑人民币参考中间价 | B5: 6.7351
A6: 样本输入Token总量 | B6: 76845
A7: 样本输出Token总量 | B7: 5738
A8: Pro高峰未命中输入价（元/百万） | B8: 9
A9: Pro高峰输出价（元/百万） | B9: 27
A10: 学生每月活动次数（假设） | B10: 4
A11: 学生每活动任务尝试数（假设） | B11: 10
A12: 教师每月准备次数（假设） | B12: 12
A13: 教师每次任务尝试数（假设） | B13: 20
A14: 专业开发者典型月成本下限（美元） | B14: 150
... A18: 场景预算启用月序（条件假设） | B18: 19
A19: 学生人均月短任务参考成本 | B19: =B24*B10*B11 -> 3.386124
A20: 教师人均月短任务参考成本 | B20: =B24*B12*B13 -> 20.316744
A21: 专业云创作者人均月参考成本 | B21: =B15*B5 -> 1347.02
A22: 研发等效资源人均月Agent预算 | B22: =B17*B23*B5 -> 1926.2386
A23: 研发每月活跃天数（假设） | B23: 22
A24: 单任务按直供Pro峰价重定价（元） | B24: =(B6/B3*B8+B7/B3*B9)/1000000 -> 0.0846531
A25: 每任务平均输入Token | B25: =B6/B3 -> 7684.5
A26: 每任务平均输出Token | B26: =B7/B3 -> 573.8
A27: 专业月成本下限折人民币 | B27: =B14*B5 -> 1010.265
A28: 专业月成本上限折人民币 | B28: =B16*B5 -> 1683.775
A30: 样本仅涵盖10个有可读回执的短任务、30次响应；未取得缓存拆分。其他任务可能另有费用，不用成功样本估算其零消耗。
A31: 学生/教师频次为规划输入，短任务参考不代表真实课堂月成本或完整专业模板消耗；输入输出、上下文增长与重试须后续实测。
A32: 专业档单列Claude Code企业API使用统计150–250美元/月，中点为200；不套用于所有个人用户或小学生，不代表Blocky实测或厂商报价。
A33: 内部研发采用13美元/活跃日×22个活跃日的资源预算，活跃天数是工作负荷假设；公开典型月范围与活跃日均不能同时相加。
A34: DeepSeek价格来自当前中文API文档，缓存未知按全部未命中敏感性重定价；不能当成息壤实际支付账单。
A35: 汇率参考2026-09-30中国货币网6.7351，非支付成交汇率；美元统计先换算人民币再进入本模型。
A36: 前18个月为研发排期假设，场景预算第19月后且产品准备关口通过才启用；日期与人数均非上线承诺。关口延期时调整启用月与人数曲线。
A37: BYOK及本地用户不计平台采购人数。平台云算力专业档用户规模是条件容量，人头不等于下载、注册、订阅销量或既有客户。

Sheet Cohorts
A1: 精简推进
A2: 月份 | B2: =EDATE(Assumptions!$B$3,0) -> 46327 | C2: =EDATE(Assumptions!$B$3,1) -> 46357 | D2: =EDATE(Assumptions!$B$3,2) -> 46388 | E2: =EDATE(Assumptions!$B$3,3) -> 46419 | F2: =EDATE(Assumptions!$B$3,4) -> 46447 | G2: =EDATE(Assumptions!$B$3,5) -> 46478 | H2: =EDATE(Assumptions!$B$3,6) -> 46508 | I2: =EDATE(Assumptions!$B$3,7) -> 46539 | J2: =EDATE(Assumptions!$B$3,8) -> 46569 | K2: =EDATE(Assumptions!$B$3,9) -> 46600 | L2: =EDATE(Assumptions!$B$3,10) -> 46631 | M2: =EDATE(Assumptions!$B$3,11) -> 46661 | N2: =EDATE(Assumptions!$B$3,12) -> 46692 | O2: =EDATE(Assumptions!$B$3,13) -> 46722 | P2: =EDATE(Assumptions!$B$3,14) -> 46753 | Q2: =EDATE(Assumptions!$B$3,15) -> 46784 | R2: =EDATE(Assumptions!$B$3,16) -> 46813 | S2: =EDATE(Assumptions!$B$3,17) -> 46844 | T2: =EDATE(Assumptions!$B$3,18) -> 46874 | U2: =EDATE(Assumptions!$B$3,19) -> 46905 | V2: =EDATE(Assumptions!$B$3,20) -> 46935 | W2: =EDATE(Assumptions!$B$3,21) -> 46966 | X2: =EDATE(Assumptions!$B$3,22) -> 46997 | Y2: =EDATE(Assumptions!$B$3,23) -> 47027 | Z2: 24个月合计 / 期末
A3: 学生平台云算力条件容量 | B3: =IF(1>=Usage!$B$18,ROUND(Assumptions!B47*Assumptions!$B$20,0),0) -> 0 | C3: =IF(2>=Usage!$B$18,ROUND(Assumptions!B48*Assumptions!$B$20,0),0) -> 0 | D3: =IF(3>=Usage!$B$18,ROUND(Assumptions!B49*Assumptions!$B$20,0),0) -> 0 | E3: =IF(4>=Usage!$B$18,ROUND(Assumptions!B50*Assumptions!$B$20,0),0) -> 0 | F3: =IF(5>=Usage!$B$18,ROUND(Assumptions!B51*Assumptions!$B$20,0),0) -> 0 | G3: =IF(6>=Usage!$B$18,ROUND(Assumptions!B52*Assumptions!$B$20,0),0) -> 0 | H3: =IF(7>=Usage!$B$18,ROUND(Assumptions!B53*Assumptions!$B$20,0),0) -> 0 | I3: =IF(8>=Usage!$B$18,ROUND(Assumptions!B54*Assumptions!$B$20,0),0) -> 0 | J3: =IF(9>=Usage!$B$18,ROUND(Assumptions!B55*Assumptions!$B$20,0),0) -> 0 | K3: =IF(10>=Usage!$B$18,ROUND(Assumptions!B56*Assumptions!$B$20,0),0) -> 0 | L3: =IF(11>=Usage!$B$18,ROUND(Assumptions!B57*Assumptions!$B$20,0),0) -> 0 | M3: =IF(12>=Usage!$B$18,ROUND(Assumptions!B58*Assumptions!$B$20,0),0) -> 0 | N3: =IF(13>=Usage!$B$18,ROUND(Assumptions!B59*Assumptions!$B$20,0),0) -> 0 | O3: =IF(14>=Usage!$B$18,ROUND(Assumptions!B60*Assumptions!$B$20,0),0) -> 0 | P3: =IF(15>=Usage!$B$18,ROUND(Assumptions!B61*Assumptions!$B$20,0),0) -> 0 | Q3: =IF(16>=Usage!$B$18,ROUND(Assumptions!B62*Assumptions!$B$20,0),0) -> 0 | R3: =IF(17>=Usage!$B$18,ROUND(Assumptions!B63*Assumptions!$B$20,0),0) -> 0 | S3: =IF(18>=Usage!$B$18,ROUND(Assumptions!B64*Assumptions!$B$20,0),0) -> 0 | T3: =IF(19>=Usage!$B$18,ROUND(Assumptions!B65*Assumptions!$B$20,0),0) -> 120 | U3: =IF(20>=Usage!$B$18,ROUND(Assumptions!B66*Assumptions!$B$20,0),0) -> 120 | V3: =IF(21>=Usage!$B$18,ROUND(Assumptions!B67*Assumptions!$B$20,0),0) -> 120 | W3: =IF(22>=Usage!$B$18,ROUND(Assumptions!B68*Assumptions!$B$20,0),0) -> 240 | X3: =IF(23>=Usage!$B$18,ROUND(Assumptions!B69*Assumptions!$B$20,0),0) -> 240 | Y3: =IF(24>=Usage!$B$18,ROUND(Assumptions!B70*Assumptions!$B$20,0),0) -> 240 | Z3: =SUM(B3:Y3) -> 1080
A4: 教师平台云算力条件容量 | B4: =IF(1>=Usage!$B$18,ROUND(Assumptions!C47*Assumptions!$B$20,0),0) -> 0 | C4: =IF(2>=Usage!$B$18,ROUND(Assumptions!C48*Assumptions!$B$20,0),0) -> 0 | D4: =IF(3>=Usage!$B$18,ROUND(Assumptions!C49*Assumptions!$B$20,0),0) -> 0 | E4: =IF(4>=Usage!$B$18,ROUND(Assumptions!C50*Assumptions!$B$20,0),0) -> 0 | F4: =IF(5>=Usage!$B$18,ROUND(Assumptions!C51*Assumptions!$B$20,0),0) -> 0 | G4: =IF(6>=Usage!$B$18,ROUND(Assumptions!C52*Assumptions!$B$20,0),0) -> 0 | H4: =IF(7>=Usage!$B$18,ROUND(Assumptions!C53*Assumptions!$B$20,0),0) -> 0 | I4: =IF(8>=Usage!$B$18,ROUND(Assumptions!C54*Assumptions!$B$20,0),0) -> 0 | J4: =IF(9>=Usage!$B$18,ROUND(Assumptions!C55*Assumptions!$B$20,0),0) -> 0 | K4: =IF(10>=Usage!$B$18,ROUND(Assumptions!C56*Assumptions!$B$20,0),0) -> 0 | L4: =IF(11>=Usage!$B$18,ROUND(Assumptions!C57*Assumptions!$B$20,0),0) -> 0 | M4: =IF(12>=Usage!$B$18,ROUND(Assumptions!C58*Assumptions!$B$20,0),0) -> 0 | N4: =IF(13>=Usage!$B$18,ROUND(Assumptions!C59*Assumptions!$B$20,0),0) -> 0 | O4: =IF(14>=Usage!$B$18,ROUND(Assumptions!C60*Assumptions!$B$20,0),0) -> 0 | P4: =IF(15>=Usage!$B$18,ROUND(Assumptions!C61*Assumptions!$B$20,0),0) -> 0 | Q4: =IF(16>=Usage!$B$18,ROUND(Assumptions!C62*Assumptions!$B$20,0),0) -> 0 | R4: =IF(17>=Usage!$B$18,ROUND(Assumptions!C63*Assumptions!$B$20,0),0) -> 0 | S4: =IF(18>=Usage!$B$18,ROUND(Assumptions!C64*Assumptions!$B$20,0),0) -> 0 | T4: =IF(19>=Usage!$B$18,ROUND(Assumptions!C65*Assumptions!$B$20,0),0) -> 16 | U4: =IF(20>=Usage!$B$18,ROUND(Assumptions!C66*Assumptions!$B$20,0),0) -> 16 | V4: =IF(21>=Usage!$B$18,ROUND(Assumptions!C67*Assumptions!$B$20,0),0) -> 16 | W4: =IF(22>=Usage!$B$18,ROUND(Assumptions!C68*Assumptions!$B$20,0),0) -> 24 | X4: =IF(23>=Usage!$B$18,ROUND(Assumptions!C69*Assumptions!$B$20,0),0) -> 24 | Y4: =IF(24>=Usage!$B$18,ROUND(Assumptions!C70*Assumptions!$B$20,0),0) -> 24 | Z4: =SUM(B4:Y4) -> 120
A5: 专业创作者平台云算力条件容量 | B5: =IF(1>=Usage!$B$18,ROUND(Assumptions!D47*Assumptions!$B$20,0),0) -> 0 | C5: =IF(2>=Usage!$B$18,ROUND(Assumptions!D48*Assumptions!$B$20,0),0) -> 0 | D5: =IF(3>=Usage!$B$18,ROUND(Assumptions!D49*Assumptions!$B$20,0),0) -> 0 | E5: =IF(4>=Usage!$B$18,ROUND(Assumptions!D50*Assumptions!$B$20,0),0) -> 0 | F5: =IF(5>=Usage!$B$18,ROUND(Assumptions!D51*Assumptions!$B$20,0),0) -> 0 | G5: =IF(6>=Usage!$B$18,ROUND(Assumptions!D52*Assumptions!$B$20,0),0) -> 0 | H5: =IF(7>=Usage!$B$18,ROUND(Assumptions!D53*Assumptions!$B$20,0),0) -> 0 | I5: =IF(8>=Usage!$B$18,ROUND(Assumptions!D54*Assumptions!$B$20,0),0) -> 0 | J5: =IF(9>=Usage!$B$18,ROUND(Assumptions!D55*Assumptions!$B$20,0),0) -> 0 | K5: =IF(10>=Usage!$B$18,ROUND(Assumptions!D56*Assumptions!$B$20,0),0) -> 0 | L5: =IF(11>=Usage!$B$18,ROUND(Assumptions!D57*Assumptions!$B$20,0),0) -> 0 | M5: =IF(12>=Usage!$B$18,ROUND(Assumptions!D58*Assumptions!$B$20,0),0) -> 0 | N5: =IF(13>=Usage!$B$18,ROUND(Assumptions!D59*Assumptions!$B$20,0),0) -> 0 | O5: =IF(14>=Usage!$B$18,ROUND(Assumptions!D60*Assumptions!$B$20,0),0) -> 0 | P5: =IF(15>=Usage!$B$18,ROUND(Assumptions!D61*Assumptions!$B$20,0),0) -> 0 | Q5: =IF(16>=Usage!$B$18,ROUND(Assumptions!D62*Assumptions!$B$20,0),0) -> 0 | R5: =IF(17>=Usage!$B$18,ROUND(Assumptions!D63*Assumptions!$B$20,0),0) -> 0 | S5: =IF(18>=Usage!$B$18,ROUND(Assumptions!D64*Assumptions!$B$20,0),0) -> 0 | T5: =IF(19>=Usage!$B$18,ROUND(Assumptions!D65*Assumptions!$B$20,0),0) -> 100 | U5: =IF(20>=Usage!$B$18,ROUND(Assumptions!D66*Assumptions!$B$20,0),0) -> 100 | V5: =IF(21>=Usage!$B$18,ROUND(Assumptions!D67*Assumptions!$B$20,0),0) -> 100 | W5: =IF(22>=Usage!$B$18,ROUND(Assumptions!D68*Assumptions!$B$20,0),0) -> 200 | X5: =IF(23>=Usage!$B$18,ROUND(Assumptions!D69*Assumptions!$B$20,0),0) -> 200 | Y5: =IF(24>=Usage!$B$18,ROUND(Assumptions!D70*Assumptions!$B$20,0),0) -> 200 | Z5: =SUM(B5:Y5) -> 900
A6: 合计云算力人头（非下载数） | B6: =SUM(B3:B5) -> 0 | C6: =SUM(C3:C5) -> 0 | D6: =SUM(D3:D5) -> 0 | E6: =SUM(E3:E5) -> 0 | F6: =SUM(F3:F5) -> 0 | G6: =SUM(G3:G5) -> 0 | H6: =SUM(H3:H5) -> 0 | I6: =SUM(I3:I5) -> 0 | ... Y6: =SUM(Y3:Y5) -> 464 | Z6: =Y6 -> 464
A7: 学生月度算力采购 | B7: =B3*Assumptions!$B$29*Assumptions!$B$21 -> 0 | C7: =C3*Assumptions!$B$29*Assumptions!$B$21 -> 0 | D7: =D3*Assumptions!$B$29*Assumptions!$B$21 -> 0 | E7: =E3*Assumptions!$B$29*Assumptions!$B$21 -> 0 | F7: =F3*Assumptions!$B$29*Assumptions!$B$21 -> 0 | G7: =G3*Assumptions!$B$29*Assumptions!$B$21 -> 0 | H7: =H3*Assumptions!$B$29*Assumptions!$B$21 -> 0 | I7: =I3*Assumptions!$B$29*Assumptions!$B$21 -> 0 | ... Y7: =Y3*Assumptions!$B$29*Assumptions!$B$21 -> 609.50232 | Z7: =SUM(B7:Y7) -> 2742.7604
A8: 教师月度算力采购 | B8: =B4*Assumptions!$B$30*Assumptions!$B$21 -> 0 | C8: =C4*Assumptions!$B$30*Assumptions!$B$21 -> 0 | D8: =D4*Assumptions!$B$30*Assumptions!$B$21 -> 0 | E8: =E4*Assumptions!$B$30*Assumptions!$B$21 -> 0 | F8: =F4*Assumptions!$B$30*Assumptions!$B$21 -> 0 | G8: =G4*Assumptions!$B$30*Assumptions!$B$21 -> 0 | H8: =H4*Assumptions!$B$30*Assumptions!$B$21 -> 0 | I8: =I4*Assumptions!$B$30*Assumptions!$B$21 -> 0 | ... Y8: =Y4*Assumptions!$B$30*Assumptions!$B$21 -> 365.70139 | Z8: =SUM(B8:Y8) -> 1828.507
A9: 个人月度算力采购 | B9: =B5*Assumptions!$B$31*Assumptions!$B$21 -> 0 | C9: =C5*Assumptions!$B$31*Assumptions!$B$21 -> 0 | D9: =D5*Assumptions!$B$31*Assumptions!$B$21 -> 0 | E9: =E5*Assumptions!$B$31*Assumptions!$B$21 -> 0 | F9: =F5*Assumptions!$B$31*Assumptions!$B$21 -> 0 | G9: =G5*Assumptions!$B$31*Assumptions!$B$21 -> 0 | H9: =H5*Assumptions!$B$31*Assumptions!$B$21 -> 0 | I9: =I5*Assumptions!$B$31*Assumptions!$B$21 -> 0 | ... Y9: =Y5*Assumptions!$B$31*Assumptions!$B$21 -> 202053 | Z9: =SUM(B9:Y9) -> 909238.5
A10: 外部用户Token成本合计 | B10: =SUM(B7:B9) -> 0 | C10: =SUM(C7:C9) -> 0 | D10: =SUM(D7:D9) -> 0 | E10: =SUM(E7:E9) -> 0 | F10: =SUM(F7:F9) -> 0 | G10: =SUM(G7:G9) -> 0 | H10: =SUM(H7:H9) -> 0 | I10: =SUM(I7:I9) -> 0 | ... Y10: =SUM(Y7:Y9) -> 203028.2 | Z10: =SUM(B10:Y10) -> 913809.77
A15: 基准建设
A16: 月份 | B16: =EDATE(Assumptions!$B$3,0) -> 46327 | C16: =EDATE(Assumptions!$B$3,1) -> 46357 | D16: =EDATE(Assumptions!$B$3,2) -> 46388 | E16: =EDATE(Assumptions!$B$3,3) -> 46419 | F16: =EDATE(Assumptions!$B$3,4) -> 46447 | G16: =EDATE(Assumptions!$B$3,5) -> 46478 | H16: =EDATE(Assumptions!$B$3,6) -> 46508 | I16: =EDATE(Assumptions!$B$3,7) -> 46539 | J16: =EDATE(Assumptions!$B$3,8) -> 46569 | K16: =EDATE(Assumptions!$B$3,9) -> 46600 | L16: =EDATE(Assumptions!$B$3,10) -> 46631 | M16: =EDATE(Assumptions!$B$3,11) -> 46661 | N16: =EDATE(Assumptions!$B$3,12) -> 46692 | O16: =EDATE(Assumptions!$B$3,13) -> 46722 | P16: =EDATE(Assumptions!$B$3,14) -> 46753 | Q16: =EDATE(Assumptions!$B$3,15) -> 46784 | R16: =EDATE(Assumptions!$B$3,16) -> 46813 | S16: =EDATE(Assumptions!$B$3,17) -> 46844 | T16: =EDATE(Assumptions!$B$3,18) -> 46874 | U16: =EDATE(Assumptions!$B$3,19) -> 46905 | V16: =EDATE(Assumptions!$B$3,20) -> 46935 | W16: =EDATE(Assumptions!$B$3,21) -> 46966 | X16: =EDATE(Assumptions!$B$3,22) -> 46997 | Y16: =EDATE(Assumptions!$B$3,23) -> 47027 | Z16: 24个月合计 / 期末
A17: 学生平台云算力条件容量 | B17: =IF(1>=Usage!$B$18,ROUND(Assumptions!B47*Assumptions!$C$20,0),0) -> 0 | C17: =IF(2>=Usage!$B$18,ROUND(Assumptions!B48*Assumptions!$C$20,0),0) -> 0 | D17: =IF(3>=Usage!$B$18,ROUND(Assumptions!B49*Assumptions!$C$20,0),0) -> 0 | E17: =IF(4>=Usage!$B$18,ROUND(Assumptions!B50*Assumptions!$C$20,0),0) -> 0 | F17: =IF(5>=Usage!$B$18,ROUND(Assumptions!B51*Assumptions!$C$20,0),0) -> 0 | G17: =IF(6>=Usage!$B$18,ROUND(Assumptions!B52*Assumptions!$C$20,0),0) -> 0 | H17: =IF(7>=Usage!$B$18,ROUND(Assumptions!B53*Assumptions!$C$20,0),0) -> 0 | I17: =IF(8>=Usage!$B$18,ROUND(Assumptions!B54*Assumptions!$C$20,0),0) -> 0 | J17: =IF(9>=Usage!$B$18,ROUND(Assumptions!B55*Assumptions!$C$20,0),0) -> 0 | K17: =IF(10>=Usage!$B$18,ROUND(Assumptions!B56*Assumptions!$C$20,0),0) -> 0 | L17: =IF(11>=Usage!$B$18,ROUND(Assumptions!B57*Assumptions!$C$20,0),0) -> 0 | M17: =IF(12>=Usage!$B$18,ROUND(Assumptions!B58*Assumptions!$C$20,0),0) -> 0 | N17: =IF(13>=Usage!$B$18,ROUND(Assumptions!B59*Assumptions!$C$20,0),0) -> 0 | O17: =IF(14>=Usage!$B$18,ROUND(Assumptions!B60*Assumptions!$C$20,0),0) -> 0 | P17: =IF(15>=Usage!$B$18,ROUND(Assumptions!B61*Assumptions!$C$20,0),0) -> 0 | Q17: =IF(16>=Usage!$B$18,ROUND(Assumptions!B62*Assumptions!$C$20,0),0) -> 0 | R17: =IF(17>=Usage!$B$18,ROUND(Assumptions!B63*Assumptions!$C$20,0),0) -> 0 | S17: =IF(18>=Usage!$B$18,ROUND(Assumptions!B64*Assumptions!$C$20,0),0) -> 0 | T17: =IF(19>=Usage!$B$18,ROUND(Assumptions!B65*Assumptions!$C$20,0),0) -> 300 | U17: =IF(20>=Usage!$B$18,ROUND(Assumptions!B66*Assumptions!$C$20,0),0) -> 300 | V17: =IF(21>=Usage!$B$18,ROUND(Assumptions!B67*Assumptions!$C$20,0),0) -> 300 | W17: =IF(22>=Usage!$B$18,ROUND(Assumptions!B68*Assumptions!$C$20,0),0) -> 600 | X17: =IF(23>=Usage!$B$18,ROUND(Assumptions!B69*Assumptions!$C$20,0),0) -> 600 | Y17: =IF(24>=Usage!$B$18,ROUND(Assumptions!B70*Assumptions!$C$20,0),0) -> 600 | Z17: =SUM(B17:Y17) -> 2700
A18: 教师平台云算力条件容量 | B18: =IF(1>=Usage!$B$18,ROUND(Assumptions!C47*Assumptions!$C$20,0),0) -> 0 | C18: =IF(2>=Usage!$B$18,ROUND(Assumptions!C48*Assumptions!$C$20,0),0) -> 0 | D18: =IF(3>=Usage!$B$18,ROUND(Assumptions!C49*Assumptions!$C$20,0),0) -> 0 | E18: =IF(4>=Usage!$B$18,ROUND(Assumptions!C50*Assumptions!$C$20,0),0) -> 0 | F18: =IF(5>=Usage!$B$18,ROUND(Assumptions!C51*Assumptions!$C$20,0),0) -> 0 | G18: =IF(6>=Usage!$B$18,ROUND(Assumptions!C52*Assumptions!$C$20,0),0) -> 0 | H18: =IF(7>=Usage!$B$18,ROUND(Assumptions!C53*Assumptions!$C$20,0),0) -> 0 | I18: =IF(8>=Usage!$B$18,ROUND(Assumptions!C54*Assumptions!$C$20,0),0) -> 0 | J18: =IF(9>=Usage!$B$18,ROUND(Assumptions!C55*Assumptions!$C$20,0),0) -> 0 | K18: =IF(10>=Usage!$B$18,ROUND(Assumptions!C56*Assumptions!$C$20,0),0) -> 0 | L18: =IF(11>=Usage!$B$18,ROUND(Assumptions!C57*Assumptions!$C$20,0),0) -> 0 | M18: =IF(12>=Usage!$B$18,ROUND(Assumptions!C58*Assumptions!$C$20,0),0) -> 0 | N18: =IF(13>=Usage!$B$18,ROUND(Assumptions!C59*Assumptions!$C$20,0),0) -> 0 | O18: =IF(14>=Usage!$B$18,ROUND(Assumptions!C60*Assumptions!$C$20,0),0) -> 0 | P18: =IF(15>=Usage!$B$18,ROUND(Assumptions!C61*Assumptions!$C$20,0),0) -> 0 | Q18: =IF(16>=Usage!$B$18,ROUND(Assumptions!C62*Assumptions!$C$20,0),0) -> 0 | R18: =IF(17>=Usage!$B$18,ROUND(Assumptions!C63*Assumptions!$C$20,0),0) -> 0 | S18: =IF(18>=Usage!$B$18,ROUND(Assumptions!C64*Assumptions!$C$20,0),0) -> 0 | T18: =IF(19>=Usage!$B$18,ROUND(Assumptions!C65*Assumptions!$C$20,0),0) -> 40 | U18: =IF(20>=Usage!$B$18,ROUND(Assumptions!C66*Assumptions!$C$20,0),0) -> 40 | V18: =IF(21>=Usage!$B$18,ROUND(Assumptions!C67*Assumptions!$C$20,0),0) -> 40 | W18: =IF(22>=Usage!$B$18,ROUND(Assumptions!C68*Assumptions!$C$20,0),0) -> 60 | X18: =IF(23>=Usage!$B$18,ROUND(Assumptions!C69*Assumptions!$C$20,0),0) -> 60 | Y18: =IF(24>=Usage!$B$18,ROUND(Assumptions!C70*Assumptions!$C$20,0),0) -> 60 | Z18: =SUM(B18:Y18) -> 300
A19: 专业创作者平台云算力条件容量 | B19: =IF(1>=Usage!$B$18,ROUND(Assumptions!D47*Assumptions!$C$20,0),0) -> 0 | C19: =IF(2>=Usage!$B$18,ROUND(Assumptions!D48*Assumptions!$C$20,0),0) -> 0 | D19: =IF(3>=Usage!$B$18,ROUND(Assumptions!D49*Assumptions!$C$20,0),0) -> 0 | E19: =IF(4>=Usage!$B$18,ROUND(Assumptions!D50*Assumptions!$C$20,0),0) -> 0 | F19: =IF(5>=Usage!$B$18,ROUND(Assumptions!D51*Assumptions!$C$20,0),0) -> 0 | G19: =IF(6>=Usage!$B$18,ROUND(Assumptions!D52*Assumptions!$C$20,0),0) -> 0 | H19: =IF(7>=Usage!$B$18,ROUND(Assumptions!D53*Assumptions!$C$20,0),0) -> 0 | I19: =IF(8>=Usage!$B$18,ROUND(Assumptions!D54*Assumptions!$C$20,0),0) -> 0 | J19: =IF(9>=Usage!$B$18,ROUND(Assumptions!D55*Assumptions!$C$20,0),0) -> 0 | K19: =IF(10>=Usage!$B$18,ROUND(Assumptions!D56*Assumptions!$C$20,0),0) -> 0 | L19: =IF(11>=Usage!$B$18,ROUND(Assumptions!D57*Assumptions!$C$20,0),0) -> 0 | M19: =IF(12>=Usage!$B$18,ROUND(Assumptions!D58*Assumptions!$C$20,0),0) -> 0 | N19: =IF(13>=Usage!$B$18,ROUND(Assumptions!D59*Assumptions!$C$20,0),0) -> 0 | O19: =IF(14>=Usage!$B$18,ROUND(Assumptions!D60*Assumptions!$C$20,0),0) -> 0 | P19: =IF(15>=Usage!$B$18,ROUND(Assumptions!D61*Assumptions!$C$20,0),0) -> 0 | Q19: =IF(16>=Usage!$B$18,ROUND(Assumptions!D62*Assumptions!$C$20,0),0) -> 0 | R19: =IF(17>=Usage!$B$18,ROUND(Assumptions!D63*Assumptions!$C$20,0),0) -> 0 | S19: =IF(18>=Usage!$B$18,ROUND(Assumptions!D64*Assumptions!$C$20,0),0) -> 0 | T19: =IF(19>=Usage!$B$18,ROUND(Assumptions!D65*Assumptions!$C$20,0),0) -> 250 | U19: =IF(20>=Usage!$B$18,ROUND(Assumptions!D66*Assumptions!$C$20,0),0) -> 250 | V19: =IF(21>=Usage!$B$18,ROUND(Assumptions!D67*Assumptions!$C$20,0),0) -> 250 | W19: =IF(22>=Usage!$B$18,ROUND(Assumptions!D68*Assumptions!$C$20,0),0) -> 500 | X19: =IF(23>=Usage!$B$18,ROUND(Assumptions!D69*Assumptions!$C$20,0),0) -> 500 | Y19: =IF(24>=Usage!$B$18,ROUND(Assumptions!D70*Assumptions!$C$20,0),0) -> 500 | Z19: =SUM(B19:Y19) -> 2250
A20: 合计云算力人头（非下载数） | B20: =SUM(B17:B19) -> 0 | C20: =SUM(C17:C19) -> 0 | D20: =SUM(D17:D19) -> 0 | E20: =SUM(E17:E19) -> 0 | F20: =SUM(F17:F19) -> 0 | G20: =SUM(G17:G19) -> 0 | H20: =SUM(H17:H19) -> 0 | I20: =SUM(I17:I19) -> 0 | ... Y20: =SUM(Y17:Y19) -> 1160 | Z20: =Y20 -> 1160
A21: 学生月度算力采购 | B21: =B17*Assumptions!$B$29*Assumptions!$C$21 -> 0 | C21: =C17*Assumptions!$B$29*Assumptions!$C$21 -> 0 | D21: =D17*Assumptions!$B$29*Assumptions!$C$21 -> 0 | E21: =E17*Assumptions!$B$29*Assumptions!$C$21 -> 0 | F21: =F17*Assumptions!$B$29*Assumptions!$C$21 -> 0 | G21: =G17*Assumptions!$B$29*Assumptions!$C$21 -> 0 | H21: =H17*Assumptions!$B$29*Assumptions!$C$21 -> 0 | I21: =I17*Assumptions!$B$29*Assumptions!$C$21 -> 0 | ... Y21: =Y17*Assumptions!$B$29*Assumptions!$C$21 -> 2031.6744 | Z21: =SUM(B21:Y21) -> 9142.5348
A22: 教师月度算力采购 | B22: =B18*Assumptions!$B$30*Assumptions!$C$21 -> 0 | C22: =C18*Assumptions!$B$30*Assumptions!$C$21 -> 0 | D22: =D18*Assumptions!$B$30*Assumptions!$C$21 -> 0 | E22: =E18*Assumptions!$B$30*Assumptions!$C$21 -> 0 | F22: =F18*Assumptions!$B$30*Assumptions!$C$21 -> 0 | G22: =G18*Assumptions!$B$30*Assumptions!$C$21 -> 0 | H22: =H18*Assumptions!$B$30*Assumptions!$C$21 -> 0 | I22: =I18*Assumptions!$B$30*Assumptions!$C$21 -> 0 | ... Y22: =Y18*Assumptions!$B$30*Assumptions!$C$21 -> 1219.0046 | Z22: =SUM(B22:Y22) -> 6095.0232
A23: 个人月度算力采购 | B23: =B19*Assumptions!$B$31*Assumptions!$C$21 -> 0 | C23: =C19*Assumptions!$B$31*Assumptions!$C$21 -> 0 | D23: =D19*Assumptions!$B$31*Assumptions!$C$21 -> 0 | E23: =E19*Assumptions!$B$31*Assumptions!$C$21 -> 0 | F23: =F19*Assumptions!$B$31*Assumptions!$C$21 -> 0 | G23: =G19*Assumptions!$B$31*Assumptions!$C$21 -> 0 | H23: =H19*Assumptions!$B$31*Assumptions!$C$21 -> 0 | I23: =I19*Assumptions!$B$31*Assumptions!$C$21 -> 0 | ... Y23: =Y19*Assumptions!$B$31*Assumptions!$C$21 -> 673510 | Z23: =SUM(B23:Y23) -> 3030795
A24: 外部用户Token成本合计 | B24: =SUM(B21:B23) -> 0 | C24: =SUM(C21:C23) -> 0 | D24: =SUM(D21:D23) -> 0 | E24: =SUM(E21:E23) -> 0 | F24: =SUM(F21:F23) -> 0 | G24: =SUM(G21:G23) -> 0 | H24: =SUM(H21:H23) -> 0 | I24: =SUM(I21:I23) -> 0 | ... Y24: =SUM(Y21:Y23) -> 676760.68 | Z24: =SUM(B24:Y24) -> 3046032.6
A29: 高用量压力
A30: 月份 | B30: =EDATE(Assumptions!$B$3,0) -> 46327 | C30: =EDATE(Assumptions!$B$3,1) -> 46357 | D30: =EDATE(Assumptions!$B$3,2) -> 46388 | E30: =EDATE(Assumptions!$B$3,3) -> 46419 | F30: =EDATE(Assumptions!$B$3,4) -> 46447 | G30: =EDATE(Assumptions!$B$3,5) -> 46478 | H30: =EDATE(Assumptions!$B$3,6) -> 46508 | I30: =EDATE(Assumptions!$B$3,7) -> 46539 | J30: =EDATE(Assumptions!$B$3,8) -> 46569 | K30: =EDATE(Assumptions!$B$3,9) -> 46600 | L30: =EDATE(Assumptions!$B$3,10) -> 46631 | M30: =EDATE(Assumptions!$B$3,11) -> 46661 | N30: =EDATE(Assumptions!$B$3,12) -> 46692 | O30: =EDATE(Assumptions!$B$3,13) -> 46722 | P30: =EDATE(Assumptions!$B$3,14) -> 46753 | Q30: =EDATE(Assumptions!$B$3,15) -> 46784 | R30: =EDATE(Assumptions!$B$3,16) -> 46813 | S30: =EDATE(Assumptions!$B$3,17) -> 46844 | T30: =EDATE(Assumptions!$B$3,18) -> 46874 | U30: =EDATE(Assumptions!$B$3,19) -> 46905 | V30: =EDATE(Assumptions!$B$3,20) -> 46935 | W30: =EDATE(Assumptions!$B$3,21) -> 46966 | X30: =EDATE(Assumptions!$B$3,22) -> 46997 | Y30: =EDATE(Assumptions!$B$3,23) -> 47027 | Z30: 24个月合计 / 期末
A31: 学生平台云算力条件容量 | B31: =IF(1>=Usage!$B$18,ROUND(Assumptions!B47*Assumptions!$D$20,0),0) -> 0 | C31: =IF(2>=Usage!$B$18,ROUND(Assumptions!B48*Assumptions!$D$20,0),0) -> 0 | D31: =IF(3>=Usage!$B$18,ROUND(Assumptions!B49*Assumptions!$D$20,0),0) -> 0 | E31: =IF(4>=Usage!$B$18,ROUND(Assumptions!B50*Assumptions!$D$20,0),0) -> 0 | F31: =IF(5>=Usage!$B$18,ROUND(Assumptions!B51*Assumptions!$D$20,0),0) -> 0 | G31: =IF(6>=Usage!$B$18,ROUND(Assumptions!B52*Assumptions!$D$20,0),0) -> 0 | H31: =IF(7>=Usage!$B$18,ROUND(Assumptions!B53*Assumptions!$D$20,0),0) -> 0 | I31: =IF(8>=Usage!$B$18,ROUND(Assumptions!B54*Assumptions!$D$20,0),0) -> 0 | J31: =IF(9>=Usage!$B$18,ROUND(Assumptions!B55*Assumptions!$D$20,0),0) -> 0 | K31: =IF(10>=Usage!$B$18,ROUND(Assumptions!B56*Assumptions!$D$20,0),0) -> 0 | L31: =IF(11>=Usage!$B$18,ROUND(Assumptions!B57*Assumptions!$D$20,0),0) -> 0 | M31: =IF(12>=Usage!$B$18,ROUND(Assumptions!B58*Assumptions!$D$20,0),0) -> 0 | N31: =IF(13>=Usage!$B$18,ROUND(Assumptions!B59*Assumptions!$D$20,0),0) -> 0 | O31: =IF(14>=Usage!$B$18,ROUND(Assumptions!B60*Assumptions!$D$20,0),0) -> 0 | P31: =IF(15>=Usage!$B$18,ROUND(Assumptions!B61*Assumptions!$D$20,0),0) -> 0 | Q31: =IF(16>=Usage!$B$18,ROUND(Assumptions!B62*Assumptions!$D$20,0),0) -> 0 | R31: =IF(17>=Usage!$B$18,ROUND(Assumptions!B63*Assumptions!$D$20,0),0) -> 0 | S31: =IF(18>=Usage!$B$18,ROUND(Assumptions!B64*Assumptions!$D$20,0),0) -> 0 | T31: =IF(19>=Usage!$B$18,ROUND(Assumptions!B65*Assumptions!$D$20,0),0) -> 600 | U31: =IF(20>=Usage!$B$18,ROUND(Assumptions!B66*Assumptions!$D$20,0),0) -> 600 | V31: =IF(21>=Usage!$B$18,ROUND(Assumptions!B67*Assumptions!$D$20,0),0) -> 600 | W31: =IF(22>=Usage!$B$18,ROUND(Assumptions!B68*Assumptions!$D$20,0),0) -> 1200 | X31: =IF(23>=Usage!$B$18,ROUND(Assumptions!B69*Assumptions!$D$20,0),0) -> 1200 | Y31: =IF(24>=Usage!$B$18,ROUND(Assumptions!B70*Assumptions!$D$20,0),0) -> 1200 | Z31: =SUM(B31:Y31) -> 5400
A32: 教师平台云算力条件容量 | B32: =IF(1>=Usage!$B$18,ROUND(Assumptions!C47*Assumptions!$D$20,0),0) -> 0 | C32: =IF(2>=Usage!$B$18,ROUND(Assumptions!C48*Assumptions!$D$20,0),0) -> 0 | D32: =IF(3>=Usage!$B$18,ROUND(Assumptions!C49*Assumptions!$D$20,0),0) -> 0 | E32: =IF(4>=Usage!$B$18,ROUND(Assumptions!C50*Assumptions!$D$20,0),0) -> 0 | F32: =IF(5>=Usage!$B$18,ROUND(Assumptions!C51*Assumptions!$D$20,0),0) -> 0 | G32: =IF(6>=Usage!$B$18,ROUND(Assumptions!C52*Assumptions!$D$20,0),0) -> 0 | H32: =IF(7>=Usage!$B$18,ROUND(Assumptions!C53*Assumptions!$D$20,0),0) -> 0 | I32: =IF(8>=Usage!$B$18,ROUND(Assumptions!C54*Assumptions!$D$20,0),0) -> 0 | J32: =IF(9>=Usage!$B$18,ROUND(Assumptions!C55*Assumptions!$D$20,0),0) -> 0 | K32: =IF(10>=Usage!$B$18,ROUND(Assumptions!C56*Assumptions!$D$20,0),0) -> 0 | L32: =IF(11>=Usage!$B$18,ROUND(Assumptions!C57*Assumptions!$D$20,0),0) -> 0 | M32: =IF(12>=Usage!$B$18,ROUND(Assumptions!C58*Assumptions!$D$20,0),0) -> 0 | N32: =IF(13>=Usage!$B$18,ROUND(Assumptions!C59*Assumptions!$D$20,0),0) -> 0 | O32: =IF(14>=Usage!$B$18,ROUND(Assumptions!C60*Assumptions!$D$20,0),0) -> 0 | P32: =IF(15>=Usage!$B$18,ROUND(Assumptions!C61*Assumptions!$D$20,0),0) -> 0 | Q32: =IF(16>=Usage!$B$18,ROUND(Assumptions!C62*Assumptions!$D$20,0),0) -> 0 | R32: =IF(17>=Usage!$B$18,ROUND(Assumptions!C63*Assumptions!$D$20,0),0) -> 0 | S32: =IF(18>=Usage!$B$18,ROUND(Assumptions!C64*Assumptions!$D$20,0),0) -> 0 | T32: =IF(19>=Usage!$B$18,ROUND(Assumptions!C65*Assumptions!$D$20,0),0) -> 80 | U32: =IF(20>=Usage!$B$18,ROUND(Assumptions!C66*Assumptions!$D$20,0),0) -> 80 | V32: =IF(21>=Usage!$B$18,ROUND(Assumptions!C67*Assumptions!$D$20,0),0) -> 80 | W32: =IF(22>=Usage!$B$18,ROUND(Assumptions!C68*Assumptions!$D$20,0),0) -> 120 | X32: =IF(23>=Usage!$B$18,ROUND(Assumptions!C69*Assumptions!$D$20,0),0) -> 120 | Y32: =IF(24>=Usage!$B$18,ROUND(Assumptions!C70*Assumptions!$D$20,0),0) -> 120 | Z32: =SUM(B32:Y32) -> 600
A33: 专业创作者平台云算力条件容量 | B33: =IF(1>=Usage!$B$18,ROUND(Assumptions!D47*Assumptions!$D$20,0),0) -> 0 | C33: =IF(2>=Usage!$B$18,ROUND(Assumptions!D48*Assumptions!$D$20,0),0) -> 0 | D33: =IF(3>=Usage!$B$18,ROUND(Assumptions!D49*Assumptions!$D$20,0),0) -> 0 | E33: =IF(4>=Usage!$B$18,ROUND(Assumptions!D50*Assumptions!$D$20,0),0) -> 0 | F33: =IF(5>=Usage!$B$18,ROUND(Assumptions!D51*Assumptions!$D$20,0),0) -> 0 | G33: =IF(6>=Usage!$B$18,ROUND(Assumptions!D52*Assumptions!$D$20,0),0) -> 0 | H33: =IF(7>=Usage!$B$18,ROUND(Assumptions!D53*Assumptions!$D$20,0),0) -> 0 | I33: =IF(8>=Usage!$B$18,ROUND(Assumptions!D54*Assumptions!$D$20,0),0) -> 0 | J33: =IF(9>=Usage!$B$18,ROUND(Assumptions!D55*Assumptions!$D$20,0),0) -> 0 | K33: =IF(10>=Usage!$B$18,ROUND(Assumptions!D56*Assumptions!$D$20,0),0) -> 0 | L33: =IF(11>=Usage!$B$18,ROUND(Assumptions!D57*Assumptions!$D$20,0),0) -> 0 | M33: =IF(12>=Usage!$B$18,ROUND(Assumptions!D58*Assumptions!$D$20,0),0) -> 0 | N33: =IF(13>=Usage!$B$18,ROUND(Assumptions!D59*Assumptions!$D$20,0),0) -> 0 | O33: =IF(14>=Usage!$B$18,ROUND(Assumptions!D60*Assumptions!$D$20,0),0) -> 0 | P33: =IF(15>=Usage!$B$18,ROUND(Assumptions!D61*Assumptions!$D$20,0),0) -> 0 | Q33: =IF(16>=Usage!$B$18,ROUND(Assumptions!D62*Assumptions!$D$20,0),0) -> 0 | R33: =IF(17>=Usage!$B$18,ROUND(Assumptions!D63*Assumptions!$D$20,0),0) -> 0 | S33: =IF(18>=Usage!$B$18,ROUND(Assumptions!D64*Assumptions!$D$20,0),0) -> 0 | T33: =IF(19>=Usage!$B$18,ROUND(Assumptions!D65*Assumptions!$D$20,0),0) -> 500 | U33: =IF(20>=Usage!$B$18,ROUND(Assumptions!D66*Assumptions!$D$20,0),0) -> 500 | V33: =IF(21>=Usage!$B$18,ROUND(Assumptions!D67*Assumptions!$D$20,0),0) -> 500 | W33: =IF(22>=Usage!$B$18,ROUND(Assumptions!D68*Assumptions!$D$20,0),0) -> 1000 | X33: =IF(23>=Usage!$B$18,ROUND(Assumptions!D69*Assumptions!$D$20,0),0) -> 1000 | Y33: =IF(24>=Usage!$B$18,ROUND(Assumptions!D70*Assumptions!$D$20,0),0) -> 1000 | Z33: =SUM(B33:Y33) -> 4500
A34: 合计云算力人头（非下载数） | B34: =SUM(B31:B33) -> 0 | C34: =SUM(C31:C33) -> 0 | D34: =SUM(D31:D33) -> 0 | E34: =SUM(E31:E33) -> 0 | F34: =SUM(F31:F33) -> 0 | G34: =SUM(G31:G33) -> 0 | H34: =SUM(H31:H33) -> 0 | I34: =SUM(I31:I33) -> 0 | ... Y34: =SUM(Y31:Y33) -> 2320 | Z34: =Y34 -> 2320
A35: 学生月度算力采购 | B35: =B31*Assumptions!$B$29*Assumptions!$D$21 -> 0 | C35: =C31*Assumptions!$B$29*Assumptions!$D$21 -> 0 | D35: =D31*Assumptions!$B$29*Assumptions!$D$21 -> 0 | E35: =E31*Assumptions!$B$29*Assumptions!$D$21 -> 0 | F35: =F31*Assumptions!$B$29*Assumptions!$D$21 -> 0 | G35: =G31*Assumptions!$B$29*Assumptions!$D$21 -> 0 | H35: =H31*Assumptions!$B$29*Assumptions!$D$21 -> 0 | I35: =I31*Assumptions!$B$29*Assumptions!$D$21 -> 0 | ... Y35: =Y31*Assumptions!$B$29*Assumptions!$D$21 -> 10158.372 | Z35: =SUM(B35:Y35) -> 45712.674
A36: 教师月度算力采购 | B36: =B32*Assumptions!$B$30*Assumptions!$D$21 -> 0 | C36: =C32*Assumptions!$B$30*Assumptions!$D$21 -> 0 | D36: =D32*Assumptions!$B$30*Assumptions!$D$21 -> 0 | E36: =E32*Assumptions!$B$30*Assumptions!$D$21 -> 0 | F36: =F32*Assumptions!$B$30*Assumptions!$D$21 -> 0 | G36: =G32*Assumptions!$B$30*Assumptions!$D$21 -> 0 | H36: =H32*Assumptions!$B$30*Assumptions!$D$21 -> 0 | I36: =I32*Assumptions!$B$30*Assumptions!$D$21 -> 0 | ... Y36: =Y32*Assumptions!$B$30*Assumptions!$D$21 -> 6095.0232 | Z36: =SUM(B36:Y36) -> 30475.116
A37: 个人月度算力采购 | B37: =B33*Assumptions!$B$31*Assumptions!$D$21 -> 0 | C37: =C33*Assumptions!$B$31*Assumptions!$D$21 -> 0 | D37: =D33*Assumptions!$B$31*Assumptions!$D$21 -> 0 | E37: =E33*Assumptions!$B$31*Assumptions!$D$21 -> 0 | F37: =F33*Assumptions!$B$31*Assumptions!$D$21 -> 0 | G37: =G33*Assumptions!$B$31*Assumptions!$D$21 -> 0 | H37: =H33*Assumptions!$B$31*Assumptions!$D$21 -> 0 | I37: =I33*Assumptions!$B$31*Assumptions!$D$21 -> 0 | ... Y37: =Y33*Assumptions!$B$31*Assumptions!$D$21 -> 3367550 | Z37: =SUM(B37:Y37) -> 15153975
A38: 外部用户Token成本合计 | B38: =SUM(B35:B37) -> 0 | C38: =SUM(C35:C37) -> 0 | D38: =SUM(D35:D37) -> 0 | E38: =SUM(E35:E37) -> 0 | F38: =SUM(F35:F37) -> 0 | G38: =SUM(G35:G37) -> 0 | H38: =SUM(H35:H37) -> 0 | I38: =SUM(I35:I37) -> 0 | ... Y38: =SUM(Y35:Y37) -> 3383803.4 | Z38: =SUM(B38:Y38) -> 15230163

Sheet Costs
A1: 精简推进
A2: 月份 | B2: =EDATE(Assumptions!$B$3,0) -> 46327 | C2: =EDATE(Assumptions!$B$3,1) -> 46357 | D2: =EDATE(Assumptions!$B$3,2) -> 46388 | E2: =EDATE(Assumptions!$B$3,3) -> 46419 | F2: =EDATE(Assumptions!$B$3,4) -> 46447 | G2: =EDATE(Assumptions!$B$3,5) -> 46478 | H2: =EDATE(Assumptions!$B$3,6) -> 46508 | I2: =EDATE(Assumptions!$B$3,7) -> 46539 | J2: =EDATE(Assumptions!$B$3,8) -> 46569 | K2: =EDATE(Assumptions!$B$3,9) -> 46600 | L2: =EDATE(Assumptions!$B$3,10) -> 46631 | M2: =EDATE(Assumptions!$B$3,11) -> 46661 | N2: =EDATE(Assumptions!$B$3,12) -> 46692 | O2: =EDATE(Assumptions!$B$3,13) -> 46722 | P2: =EDATE(Assumptions!$B$3,14) -> 46753 | Q2: =EDATE(Assumptions!$B$3,15) -> 46784 | R2: =EDATE(Assumptions!$B$3,16) -> 46813 | S2: =EDATE(Assumptions!$B$3,17) -> 46844 | T2: =EDATE(Assumptions!$B$3,18) -> 46874 | U2: =EDATE(Assumptions!$B$3,19) -> 46905 | V2: =EDATE(Assumptions!$B$3,20) -> 46935 | W2: =EDATE(Assumptions!$B$3,21) -> 46966 | X2: =EDATE(Assumptions!$B$3,22) -> 46997 | Y2: =EDATE(Assumptions!$B$3,23) -> 47027 | Z2: 24个月合计 / 期末
A3: 等效资源人力 | B3: =IF(1<=6,Assumptions!$B$17,Assumptions!$B$18) -> 2 | C3: =IF(2<=6,Assumptions!$B$17,Assumptions!$B$18) -> 2 | D3: =IF(3<=6,Assumptions!$B$17,Assumptions!$B$18) -> 2 | E3: =IF(4<=6,Assumptions!$B$17,Assumptions!$B$18) -> 2 | F3: =IF(5<=6,Assumptions!$B$17,Assumptions!$B$18) -> 2 | G3: =IF(6<=6,Assumptions!$B$17,Assumptions!$B$18) -> 2 | H3: =IF(7<=6,Assumptions!$B$17,Assumptions!$B$18) -> 3 | I3: =IF(8<=6,Assumptions!$B$17,Assumptions!$B$18) -> 3 | J3: =IF(9<=6,Assumptions!$B$17,Assumptions!$B$18) -> 3 | K3: =IF(10<=6,Assumptions!$B$17,Assumptions!$B$18) -> 3 | L3: =IF(11<=6,Assumptions!$B$17,Assumptions!$B$18) -> 3 | M3: =IF(12<=6,Assumptions!$B$17,Assumptions!$B$18) -> 3 | N3: =IF(13<=6,Assumptions!$B$17,Assumptions!$B$18) -> 3 | O3: =IF(14<=6,Assumptions!$B$17,Assumptions!$B$18) -> 3 | P3: =IF(15<=6,Assumptions!$B$17,Assumptions!$B$18) -> 3 | Q3: =IF(16<=6,Assumptions!$B$17,Assumptions!$B$18) -> 3 | R3: =IF(17<=6,Assumptions!$B$17,Assumptions!$B$18) -> 3 | S3: =IF(18<=6,Assumptions!$B$17,Assumptions!$B$18) -> 3 | T3: =IF(19<=6,Assumptions!$B$17,Assumptions!$B$18) -> 3 | U3: =IF(20<=6,Assumptions!$B$17,Assumptions!$B$18) -> 3 | V3: =IF(21<=6,Assumptions!$B$17,Assumptions!$B$18) -> 3 | W3: =IF(22<=6,Assumptions!$B$17,Assumptions!$B$18) -> 3 | X3: =IF(23<=6,Assumptions!$B$17,Assumptions!$B$18) -> 3 | Y3: =IF(24<=6,Assumptions!$B$17,Assumptions!$B$18) -> 3 | Z3: =SUM(B3:Y3) -> 66
A4: 综合人力现金 | B4: =B3*Assumptions!$B$19 -> 32000 | C4: =C3*Assumptions!$B$19 -> 32000 | D4: =D3*Assumptions!$B$19 -> 32000 | E4: =E3*Assumptions!$B$19 -> 32000 | F4: =F3*Assumptions!$B$19 -> 32000 | G4: =G3*Assumptions!$B$19 -> 32000 | H4: =H3*Assumptions!$B$19 -> 48000 | I4: =I3*Assumptions!$B$19 -> 48000 | ... Y4: =Y3*Assumptions!$B$19 -> 48000 | Z4: =SUM(B4:Y4) -> 1056000
A5: 内部研发Agent预算 | B5: =B3*Assumptions!$B$32*Assumptions!$B$22 -> 2889.3579 | C5: =C3*Assumptions!$B$32*Assumptions!$B$22 -> 2889.3579 | D5: =D3*Assumptions!$B$32*Assumptions!$B$22 -> 2889.3579 | E5: =E3*Assumptions!$B$32*Assumptions!$B$22 -> 2889.3579 | F5: =F3*Assumptions!$B$32*Assumptions!$B$22 -> 2889.3579 | G5: =G3*Assumptions!$B$32*Assumptions!$B$22 -> 2889.3579 | H5: =H3*Assumptions!$B$32*Assumptions!$B$22 -> 4334.0369 | I5: =I3*Assumptions!$B$32*Assumptions!$B$22 -> 4334.0369 | ... Y5: =Y3*Assumptions!$B$32*Assumptions!$B$22 -> 4334.0369 | Z5: =SUM(B5:Y5) -> 95348.811
A6: 云基础设施 | B6: =IF(1<=6,Assumptions!$B$34,IF(1<=12,Assumptions!$B$35,Assumptions!$B$36))*Assumptions!$B$22 -> 2250 | C6: =IF(2<=6,Assumptions!$B$34,IF(2<=12,Assumptions!$B$35,Assumptions!$B$36))*Assumptions!$B$22 -> 2250 | D6: =IF(3<=6,Assumptions!$B$34,IF(3<=12,Assumptions!$B$35,Assumptions!$B$36))*Assumptions!$B$22 -> 2250 | E6: =IF(4<=6,Assumptions!$B$34,IF(4<=12,Assumptions!$B$35,Assumptions!$B$36))*Assumptions!$B$22 -> 2250 | F6: =IF(5<=6,Assumptions!$B$34,IF(5<=12,Assumptions!$B$35,Assumptions!$B$36))*Assumptions!$B$22 -> 2250 | G6: =IF(6<=6,Assumptions!$B$34,IF(6<=12,Assumptions!$B$35,Assumptions!$B$36))*Assumptions!$B$22 -> 2250 | H6: =IF(7<=6,Assumptions!$B$34,IF(7<=12,Assumptions!$B$35,Assumptions!$B$36))*Assumptions!$B$22 -> 4500 | I6: =IF(8<=6,Assumptions!$B$34,IF(8<=12,Assumptions!$B$35,Assumptions!$B$36))*Assumptions!$B$22 -> 4500 | J6: =IF(9<=6,Assumptions!$B$34,IF(9<=12,Assumptions!$B$35,Assumptions!$B$36))*Assumptions!$B$22 -> 4500 | K6: =IF(10<=6,Assumptions!$B$34,IF(10<=12,Assumptions!$B$35,Assumptions!$B$36))*Assumptions!$B$22 -> 4500 | L6: =IF(11<=6,Assumptions!$B$34,IF(11<=12,Assumptions!$B$35,Assumptions!$B$36))*Assumptions!$B$22 -> 4500 | M6: =IF(12<=6,Assumptions!$B$34,IF(12<=12,Assumptions!$B$35,Assumptions!$B$36))*Assumptions!$B$22 -> 4500 | N6: =IF(13<=6,Assumptions!$B$34,IF(13<=12,Assumptions!$B$35,Assumptions!$B$36))*Assumptions!$B$22 -> 6750 | O6: =IF(14<=6,Assumptions!$B$34,IF(14<=12,Assumptions!$B$35,Assumptions!$B$36))*Assumptions!$B$22 -> 6750 | P6: =IF(15<=6,Assumptions!$B$34,IF(15<=12,Assumptions!$B$35,Assumptions!$B$36))*Assumptions!$B$22 -> 6750 | Q6: =IF(16<=6,Assumptions!$B$34,IF(16<=12,Assumptions!$B$35,Assumptions!$B$36))*Assumptions!$B$22 -> 6750 | R6: =IF(17<=6,Assumptions!$B$34,IF(17<=12,Assumptions!$B$35,Assumptions!$B$36))*Assumptions!$B$22 -> 6750 | S6: =IF(18<=6,Assumptions!$B$34,IF(18<=12,Assumptions!$B$35,Assumptions!$B$36))*Assumptions!$B$22 -> 6750 | T6: =IF(19<=6,Assumptions!$B$34,IF(19<=12,Assumptions!$B$35,Assumptions!$B$36))*Assumptions!$B$22 -> 6750 | U6: =IF(20<=6,Assumptions!$B$34,IF(20<=12,Assumptions!$B$35,Assumptions!$B$36))*Assumptions!$B$22 -> 6750 | V6: =IF(21<=6,Assumptions!$B$34,IF(21<=12,Assumptions!$B$35,Assumptions!$B$36))*Assumptions!$B$22 -> 6750 | W6: =IF(22<=6,Assumptions!$B$34,IF(22<=12,Assumptions!$B$35,Assumptions!$B$36))*Assumptions!$B$22 -> 6750 | X6: =IF(23<=6,Assumptions!$B$34,IF(23<=12,Assumptions!$B$35,Assumptions!$B$36))*Assumptions!$B$22 -> 6750 | Y6: =IF(24<=6,Assumptions!$B$34,IF(24<=12,Assumptions!$B$35,Assumptions!$B$36))*Assumptions!$B$22 -> 6750 | Z6: =SUM(B6:Y6) -> 121500
A7: 教学共创与试用 | B7: =IF(1<=3,Assumptions!$B$37,IF(1<=12,Assumptions!$B$38,Assumptions!$B$39))*Assumptions!$B$22 -> 0 | C7: =IF(2<=3,Assumptions!$B$37,IF(2<=12,Assumptions!$B$38,Assumptions!$B$39))*Assumptions!$B$22 -> 0 | D7: =IF(3<=3,Assumptions!$B$37,IF(3<=12,Assumptions!$B$38,Assumptions!$B$39))*Assumptions!$B$22 -> 0 | E7: =IF(4<=3,Assumptions!$B$37,IF(4<=12,Assumptions!$B$38,Assumptions!$B$39))*Assumptions!$B$22 -> 4500 | F7: =IF(5<=3,Assumptions!$B$37,IF(5<=12,Assumptions!$B$38,Assumptions!$B$39))*Assumptions!$B$22 -> 4500 | G7: =IF(6<=3,Assumptions!$B$37,IF(6<=12,Assumptions!$B$38,Assumptions!$B$39))*Assumptions!$B$22 -> 4500 | H7: =IF(7<=3,Assumptions!$B$37,IF(7<=12,Assumptions!$B$38,Assumptions!$B$39))*Assumptions!$B$22 -> 4500 | I7: =IF(8<=3,Assumptions!$B$37,IF(8<=12,Assumptions!$B$38,Assumptions!$B$39))*Assumptions!$B$22 -> 4500 | J7: =IF(9<=3,Assumptions!$B$37,IF(9<=12,Assumptions!$B$38,Assumptions!$B$39))*Assumptions!$B$22 -> 4500 | K7: =IF(10<=3,Assumptions!$B$37,IF(10<=12,Assumptions!$B$38,Assumptions!$B$39))*Assumptions!$B$22 -> 4500 | L7: =IF(11<=3,Assumptions!$B$37,IF(11<=12,Assumptions!$B$38,Assumptions!$B$39))*Assumptions!$B$22 -> 4500 | M7: =IF(12<=3,Assumptions!$B$37,IF(12<=12,Assumptions!$B$38,Assumptions!$B$39))*Assumptions!$B$22 -> 4500 | N7: =IF(13<=3,Assumptions!$B$37,IF(13<=12,Assumptions!$B$38,Assumptions!$B$39))*Assumptions!$B$22 -> 6000 | O7: =IF(14<=3,Assumptions!$B$37,IF(14<=12,Assumptions!$B$38,Assumptions!$B$39))*Assumptions!$B$22 -> 6000 | P7: =IF(15<=3,Assumptions!$B$37,IF(15<=12,Assumptions!$B$38,Assumptions!$B$39))*Assumptions!$B$22 -> 6000 | Q7: =IF(16<=3,Assumptions!$B$37,IF(16<=12,Assumptions!$B$38,Assumptions!$B$39))*Assumptions!$B$22 -> 6000 | R7: =IF(17<=3,Assumptions!$B$37,IF(17<=12,Assumptions!$B$38,Assumptions!$B$39))*Assumptions!$B$22 -> 6000 | S7: =IF(18<=3,Assumptions!$B$37,IF(18<=12,Assumptions!$B$38,Assumptions!$B$39))*Assumptions!$B$22 -> 6000 | T7: =IF(19<=3,Assumptions!$B$37,IF(19<=12,Assumptions!$B$38,Assumptions!$B$39))*Assumptions!$B$22 -> 6000 | U7: =IF(20<=3,Assumptions!$B$37,IF(20<=12,Assumptions!$B$38,Assumptions!$B$39))*Assumptions!$B$22 -> 6000 | V7: =IF(21<=3,Assumptions!$B$37,IF(21<=12,Assumptions!$B$38,Assumptions!$B$39))*Assumptions!$B$22 -> 6000 | W7: =IF(22<=3,Assumptions!$B$37,IF(22<=12,Assumptions!$B$38,Assumptions!$B$39))*Assumptions!$B$22 -> 6000 | X7: =IF(23<=3,Assumptions!$B$37,IF(23<=12,Assumptions!$B$38,Assumptions!$B$39))*Assumptions!$B$22 -> 6000 | Y7: =IF(24<=3,Assumptions!$B$37,IF(24<=12,Assumptions!$B$38,Assumptions!$B$39))*Assumptions!$B$22 -> 6000 | Z7: =SUM(B7:Y7) -> 112500
A8: 社区活动与材料 | B8: =IF(1<=3,Assumptions!$B$40,IF(1<=12,Assumptions!$B$41,Assumptions!$B$42))*Assumptions!$B$22 -> 0 | C8: =IF(2<=3,Assumptions!$B$40,IF(2<=12,Assumptions!$B$41,Assumptions!$B$42))*Assumptions!$B$22 -> 0 | D8: =IF(3<=3,Assumptions!$B$40,IF(3<=12,Assumptions!$B$41,Assumptions!$B$42))*Assumptions!$B$22 -> 0 | E8: =IF(4<=3,Assumptions!$B$40,IF(4<=12,Assumptions!$B$41,Assumptions!$B$42))*Assumptions!$B$22 -> 2250 | F8: =IF(5<=3,Assumptions!$B$40,IF(5<=12,Assumptions!$B$41,Assumptions!$B$42))*Assumptions!$B$22 -> 2250 | G8: =IF(6<=3,Assumptions!$B$40,IF(6<=12,Assumptions!$B$41,Assumptions!$B$42))*Assumptions!$B$22 -> 2250 | H8: =IF(7<=3,Assumptions!$B$40,IF(7<=12,Assumptions!$B$41,Assumptions!$B$42))*Assumptions!$B$22 -> 2250 | I8: =IF(8<=3,Assumptions!$B$40,IF(8<=12,Assumptions!$B$41,Assumptions!$B$42))*Assumptions!$B$22 -> 2250 | J8: =IF(9<=3,Assumptions!$B$40,IF(9<=12,Assumptions!$B$41,Assumptions!$B$42))*Assumptions!$B$22 -> 2250 | K8: =IF(10<=3,Assumptions!$B$40,IF(10<=12,Assumptions!$B$41,Assumptions!$B$42))*Assumptions!$B$22 -> 2250 | L8: =IF(11<=3,Assumptions!$B$40,IF(11<=12,Assumptions!$B$41,Assumptions!$B$42))*Assumptions!$B$22 -> 2250 | M8: =IF(12<=3,Assumptions!$B$40,IF(12<=12,Assumptions!$B$41,Assumptions!$B$42))*Assumptions!$B$22 -> 2250 | N8: =IF(13<=3,Assumptions!$B$40,IF(13<=12,Assumptions!$B$41,Assumptions!$B$42))*Assumptions!$B$22 -> 4500 | O8: =IF(14<=3,Assumptions!$B$40,IF(14<=12,Assumptions!$B$41,Assumptions!$B$42))*Assumptions!$B$22 -> 4500 | P8: =IF(15<=3,Assumptions!$B$40,IF(15<=12,Assumptions!$B$41,Assumptions!$B$42))*Assumptions!$B$22 -> 4500 | Q8: =IF(16<=3,Assumptions!$B$40,IF(16<=12,Assumptions!$B$41,Assumptions!$B$42))*Assumptions!$B$22 -> 4500 | R8: =IF(17<=3,Assumptions!$B$40,IF(17<=12,Assumptions!$B$41,Assumptions!$B$42))*Assumptions!$B$22 -> 4500 | S8: =IF(18<=3,Assumptions!$B$40,IF(18<=12,Assumptions!$B$41,Assumptions!$B$42))*Assumptions!$B$22 -> 4500 | T8: =IF(19<=3,Assumptions!$B$40,IF(19<=12,Assumptions!$B$41,Assumptions!$B$42))*Assumptions!$B$22 -> 4500 | U8: =IF(20<=3,Assumptions!$B$40,IF(20<=12,Assumptions!$B$41,Assumptions!$B$42))*Assumptions!$B$22 -> 4500 | V8: =IF(21<=3,Assumptions!$B$40,IF(21<=12,Assumptions!$B$41,Assumptions!$B$42))*Assumptions!$B$22 -> 4500 | W8: =IF(22<=3,Assumptions!$B$40,IF(22<=12,Assumptions!$B$41,Assumptions!$B$42))*Assumptions!$B$22 -> 4500 | X8: =IF(23<=3,Assumptions!$B$40,IF(23<=12,Assumptions!$B$41,Assumptions!$B$42))*Assumptions!$B$22 -> 4500 | Y8: =IF(24<=3,Assumptions!$B$40,IF(24<=12,Assumptions!$B$41,Assumptions!$B$42))*Assumptions!$B$22 -> 4500 | Z8: =SUM(B8:Y8) -> 74250
A9: 一般运营与合规预算 | B9: =Assumptions!$B$43*Assumptions!$B$22 -> 2250 | C9: =Assumptions!$B$43*Assumptions!$B$22 -> 2250 | D9: =Assumptions!$B$43*Assumptions!$B$22 -> 2250 | E9: =Assumptions!$B$43*Assumptions!$B$22 -> 2250 | F9: =Assumptions!$B$43*Assumptions!$B$22 -> 2250 | G9: =Assumptions!$B$43*Assumptions!$B$22 -> 2250 | H9: =Assumptions!$B$43*Assumptions!$B$22 -> 2250 | I9: =Assumptions!$B$43*Assumptions!$B$22 -> 2250 | ... Y9: =Assumptions!$B$43*Assumptions!$B$22 -> 2250 | Z9: =SUM(B9:Y9) -> 54000
A10: 专项外部交付 | B10: =SUMIF(Assumptions!$F$47:$F$50,1,Assumptions!$G$47:$G$50)*Assumptions!$B$22 -> 0 | C10: =SUMIF(Assumptions!$F$47:$F$50,2,Assumptions!$G$47:$G$50)*Assumptions!$B$22 -> 0 | D10: =SUMIF(Assumptions!$F$47:$F$50,3,Assumptions!$G$47:$G$50)*Assumptions!$B$22 -> 0 | E10: =SUMIF(Assumptions!$F$47:$F$50,4,Assumptions!$G$47:$G$50)*Assumptions!$B$22 -> 0 | F10: =SUMIF(Assumptions!$F$47:$F$50,5,Assumptions!$G$47:$G$50)*Assumptions!$B$22 -> 0 | G10: =SUMIF(Assumptions!$F$47:$F$50,6,Assumptions!$G$47:$G$50)*Assumptions!$B$22 -> 22500 | H10: =SUMIF(Assumptions!$F$47:$F$50,7,Assumptions!$G$47:$G$50)*Assumptions!$B$22 -> 0 | I10: =SUMIF(Assumptions!$F$47:$F$50,8,Assumptions!$G$47:$G$50)*Assumptions!$B$22 -> 0 | J10: =SUMIF(Assumptions!$F$47:$F$50,9,Assumptions!$G$47:$G$50)*Assumptions!$B$22 -> 0 | K10: =SUMIF(Assumptions!$F$47:$F$50,10,Assumptions!$G$47:$G$50)*Assumptions!$B$22 -> 0 | L10: =SUMIF(Assumptions!$F$47:$F$50,11,Assumptions!$G$47:$G$50)*Assumptions!$B$22 -> 0 | M10: =SUMIF(Assumptions!$F$47:$F$50,12,Assumptions!$G$47:$G$50)*Assumptions!$B$22 -> 30000 | N10: =SUMIF(Assumptions!$F$47:$F$50,13,Assumptions!$G$47:$G$50)*Assumptions!$B$22 -> 0 | O10: =SUMIF(Assumptions!$F$47:$F$50,14,Assumptions!$G$47:$G$50)*Assumptions!$B$22 -> 0 | P10: =SUMIF(Assumptions!$F$47:$F$50,15,Assumptions!$G$47:$G$50)*Assumptions!$B$22 -> 0 | Q10: =SUMIF(Assumptions!$F$47:$F$50,16,Assumptions!$G$47:$G$50)*Assumptions!$B$22 -> 0 | R10: =SUMIF(Assumptions!$F$47:$F$50,17,Assumptions!$G$47:$G$50)*Assumptions!$B$22 -> 0 | S10: =SUMIF(Assumptions!$F$47:$F$50,18,Assumptions!$G$47:$G$50)*Assumptions!$B$22 -> 30000 | T10: =SUMIF(Assumptions!$F$47:$F$50,19,Assumptions!$G$47:$G$50)*Assumptions!$B$22 -> 0 | U10: =SUMIF(Assumptions!$F$47:$F$50,20,Assumptions!$G$47:$G$50)*Assumptions!$B$22 -> 0 | V10: =SUMIF(Assumptions!$F$47:$F$50,21,Assumptions!$G$47:$G$50)*Assumptions!$B$22 -> 0 | W10: =SUMIF(Assumptions!$F$47:$F$50,22,Assumptions!$G$47:$G$50)*Assumptions!$B$22 -> 0 | X10: =SUMIF(Assumptions!$F$47:$F$50,23,Assumptions!$G$47:$G$50)*Assumptions!$B$22 -> 0 | Y10: =SUMIF(Assumptions!$F$47:$F$50,24,Assumptions!$G$47:$G$50)*Assumptions!$B$22 -> 30000 | Z10: =SUM(B10:Y10) -> 112500
A11: 条件用户算力成本 | B11: =Cohorts!B10 -> 0 | C11: =Cohorts!C10 -> 0 | D11: =Cohorts!D10 -> 0 | E11: =Cohorts!E10 -> 0 | F11: =Cohorts!F10 -> 0 | G11: =Cohorts!G10 -> 0 | H11: =Cohorts!H10 -> 0 | I11: =Cohorts!I10 -> 0 | ... Y11: =Cohorts!Y10 -> 203028.2 | Z11: =SUM(B11:Y11) -> 913809.77
A12: 实际非退还合作费（未录入） | B12: =IF(1=Assumptions!$B$10,Assumptions!$B$7,0) -> 0 | C12: =IF(2=Assumptions!$B$10,Assumptions!$B$7,0) -> 0 | D12: =IF(3=Assumptions!$B$10,Assumptions!$B$7,0) -> 0 | E12: =IF(4=Assumptions!$B$10,Assumptions!$B$7,0) -> 0 | F12: =IF(5=Assumptions!$B$10,Assumptions!$B$7,0) -> 0 | G12: =IF(6=Assumptions!$B$10,Assumptions!$B$7,0) -> 0 | H12: =IF(7=Assumptions!$B$10,Assumptions!$B$7,0) -> 0 | I12: =IF(8=Assumptions!$B$10,Assumptions!$B$7,0) -> 0 | J12: =IF(9=Assumptions!$B$10,Assumptions!$B$7,0) -> 0 | K12: =IF(10=Assumptions!$B$10,Assumptions!$B$7,0) -> 0 | L12: =IF(11=Assumptions!$B$10,Assumptions!$B$7,0) -> 0 | M12: =IF(12=Assumptions!$B$10,Assumptions!$B$7,0) -> 0 | N12: =IF(13=Assumptions!$B$10,Assumptions!$B$7,0) -> 0 | O12: =IF(14=Assumptions!$B$10,Assumptions!$B$7,0) -> 0 | P12: =IF(15=Assumptions!$B$10,Assumptions!$B$7,0) -> 0 | Q12: =IF(16=Assumptions!$B$10,Assumptions!$B$7,0) -> 0 | R12: =IF(17=Assumptions!$B$10,Assumptions!$B$7,0) -> 0 | S12: =IF(18=Assumptions!$B$10,Assumptions!$B$7,0) -> 0 | T12: =IF(19=Assumptions!$B$10,Assumptions!$B$7,0) -> 0 | U12: =IF(20=Assumptions!$B$10,Assumptions!$B$7,0) -> 0 | V12: =IF(21=Assumptions!$B$10,Assumptions!$B$7,0) -> 0 | W12: =IF(22=Assumptions!$B$10,Assumptions!$B$7,0) -> 0 | X12: =IF(23=Assumptions!$B$10,Assumptions!$B$7,0) -> 0 | Y12: =IF(24=Assumptions!$B$10,Assumptions!$B$7,0) -> 0 | Z12: =SUM(B12:Y12) -> 0
A13: 费用现金合计（不含设备） | B13: =SUM(B4:B12) -> 39389.358 | C13: =SUM(C4:C12) -> 39389.358 | D13: =SUM(D4:D12) -> 39389.358 | E13: =SUM(E4:E12) -> 46139.358 | F13: =SUM(F4:F12) -> 46139.358 | G13: =SUM(G4:G12) -> 68639.358 | H13: =SUM(H4:H12) -> 65834.037 | I13: =SUM(I4:I12) -> 65834.037 | ... Y13: =SUM(Y4:Y12) -> 304862.24 | Z13: =SUM(B13:Y13) -> 2539908.6
A14: 设备购置现金 | B14: =SUMIF(Assumptions!$F$54:$F$55,1,Assumptions!$G$54:$G$55)*Assumptions!$B$22 -> 37500 | C14: =SUMIF(Assumptions!$F$54:$F$55,2,Assumptions!$G$54:$G$55)*Assumptions!$B$22 -> 0 | D14: =SUMIF(Assumptions!$F$54:$F$55,3,Assumptions!$G$54:$G$55)*Assumptions!$B$22 -> 0 | E14: =SUMIF(Assumptions!$F$54:$F$55,4,Assumptions!$G$54:$G$55)*Assumptions!$B$22 -> 0 | F14: =SUMIF(Assumptions!$F$54:$F$55,5,Assumptions!$G$54:$G$55)*Assumptions!$B$22 -> 0 | G14: =SUMIF(Assumptions!$F$54:$F$55,6,Assumptions!$G$54:$G$55)*Assumptions!$B$22 -> 0 | H14: =SUMIF(Assumptions!$F$54:$F$55,7,Assumptions!$G$54:$G$55)*Assumptions!$B$22 -> 22500 | I14: =SUMIF(Assumptions!$F$54:$F$55,8,Assumptions!$G$54:$G$55)*Assumptions!$B$22 -> 0 | J14: =SUMIF(Assumptions!$F$54:$F$55,9,Assumptions!$G$54:$G$55)*Assumptions!$B$22 -> 0 | K14: =SUMIF(Assumptions!$F$54:$F$55,10,Assumptions!$G$54:$G$55)*Assumptions!$B$22 -> 0 | L14: =SUMIF(Assumptions!$F$54:$F$55,11,Assumptions!$G$54:$G$55)*Assumptions!$B$22 -> 0 | M14: =SUMIF(Assumptions!$F$54:$F$55,12,Assumptions!$G$54:$G$55)*Assumptions!$B$22 -> 0 | N14: =SUMIF(Assumptions!$F$54:$F$55,13,Assumptions!$G$54:$G$55)*Assumptions!$B$22 -> 0 | O14: =SUMIF(Assumptions!$F$54:$F$55,14,Assumptions!$G$54:$G$55)*Assumptions!$B$22 -> 0 | P14: =SUMIF(Assumptions!$F$54:$F$55,15,Assumptions!$G$54:$G$55)*Assumptions!$B$22 -> 0 | Q14: =SUMIF(Assumptions!$F$54:$F$55,16,Assumptions!$G$54:$G$55)*Assumptions!$B$22 -> 0 | R14: =SUMIF(Assumptions!$F$54:$F$55,17,Assumptions!$G$54:$G$55)*Assumptions!$B$22 -> 0 | S14: =SUMIF(Assumptions!$F$54:$F$55,18,Assumptions!$G$54:$G$55)*Assumptions!$B$22 -> 0 | T14: =SUMIF(Assumptions!$F$54:$F$55,19,Assumptions!$G$54:$G$55)*Assumptions!$B$22 -> 0 | U14: =SUMIF(Assumptions!$F$54:$F$55,20,Assumptions!$G$54:$G$55)*Assumptions!$B$22 -> 0 | V14: =SUMIF(Assumptions!$F$54:$F$55,21,Assumptions!$G$54:$G$55)*Assumptions!$B$22 -> 0 | W14: =SUMIF(Assumptions!$F$54:$F$55,22,Assumptions!$G$54:$G$55)*Assumptions!$B$22 -> 0 | X14: =SUMIF(Assumptions!$F$54:$F$55,23,Assumptions!$G$54:$G$55)*Assumptions!$B$22 -> 0 | Y14: =SUMIF(Assumptions!$F$54:$F$55,24,Assumptions!$G$54:$G$55)*Assumptions!$B$22 -> 0 | Z14: =SUM(B14:Y14) -> 60000
A15: 当月设备折旧 | B15: =SUMPRODUCT((1-Assumptions!$F$54:$F$55+1>0)*(1-Assumptions!$F$54:$F$55+1<=Assumptions!$B$11)*Assumptions!$G$54:$G$55)*Assumptions!$B$22/Assumptions!$B$11 -> 1041.6667 | C15: =SUMPRODUCT((2-Assumptions!$F$54:$F$55+1>0)*(2-Assumptions!$F$54:$F$55+1<=Assumptions!$B$11)*Assumptions!$G$54:$G$55)*Assumptions!$B$22/Assumptions!$B$11 -> 1041.6667 | D15: =SUMPRODUCT((3-Assumptions!$F$54:$F$55+1>0)*(3-Assumptions!$F$54:$F$55+1<=Assumptions!$B$11)*Assumptions!$G$54:$G$55)*Assumptions!$B$22/Assumptions!$B$11 -> 1041.6667 | E15: =SUMPRODUCT((4-Assumptions!$F$54:$F$55+1>0)*(4-Assumptions!$F$54:$F$55+1<=Assumptions!$B$11)*Assumptions!$G$54:$G$55)*Assumptions!$B$22/Assumptions!$B$11 -> 1041.6667 | F15: =SUMPRODUCT((5-Assumptions!$F$54:$F$55+1>0)*(5-Assumptions!$F$54:$F$55+1<=Assumptions!$B$11)*Assumptions!$G$54:$G$55)*Assumptions!$B$22/Assumptions!$B$11 -> 1041.6667 | G15: =SUMPRODUCT((6-Assumptions!$F$54:$F$55+1>0)*(6-Assumptions!$F$54:$F$55+1<=Assumptions!$B$11)*Assumptions!$G$54:$G$55)*Assumptions!$B$22/Assumptions!$B$11 -> 1041.6667 | H15: =SUMPRODUCT((7-Assumptions!$F$54:$F$55+1>0)*(7-Assumptions!$F$54:$F$55+1<=Assumptions!$B$11)*Assumptions!$G$54:$G$55)*Assumptions!$B$22/Assumptions!$B$11 -> 1666.6667 | I15: =SUMPRODUCT((8-Assumptions!$F$54:$F$55+1>0)*(8-Assumptions!$F$54:$F$55+1<=Assumptions!$B$11)*Assumptions!$G$54:$G$55)*Assumptions!$B$22/Assumptions!$B$11 -> 1666.6667 | J15: =SUMPRODUCT((9-Assumptions!$F$54:$F$55+1>0)*(9-Assumptions!$F$54:$F$55+1<=Assumptions!$B$11)*Assumptions!$G$54:$G$55)*Assumptions!$B$22/Assumptions!$B$11 -> 1666.6667 | K15: =SUMPRODUCT((10-Assumptions!$F$54:$F$55+1>0)*(10-Assumptions!$F$54:$F$55+1<=Assumptions!$B$11)*Assumptions!$G$54:$G$55)*Assumptions!$B$22/Assumptions!$B$11 -> 1666.6667 | L15: =SUMPRODUCT((11-Assumptions!$F$54:$F$55+1>0)*(11-Assumptions!$F$54:$F$55+1<=Assumptions!$B$11)*Assumptions!$G$54:$G$55)*Assumptions!$B$22/Assumptions!$B$11 -> 1666.6667 | M15: =SUMPRODUCT((12-Assumptions!$F$54:$F$55+1>0)*(12-Assumptions!$F$54:$F$55+1<=Assumptions!$B$11)*Assumptions!$G$54:$G$55)*Assumptions!$B$22/Assumptions!$B$11 -> 1666.6667 | N15: =SUMPRODUCT((13-Assumptions!$F$54:$F$55+1>0)*(13-Assumptions!$F$54:$F$55+1<=Assumptions!$B$11)*Assumptions!$G$54:$G$55)*Assumptions!$B$22/Assumptions!$B$11 -> 1666.6667 | O15: =SUMPRODUCT((14-Assumptions!$F$54:$F$55+1>0)*(14-Assumptions!$F$54:$F$55+1<=Assumptions!$B$11)*Assumptions!$G$54:$G$55)*Assumptions!$B$22/Assumptions!$B$11 -> 1666.6667 | P15: =SUMPRODUCT((15-Assumptions!$F$54:$F$55+1>0)*(15-Assumptions!$F$54:$F$55+1<=Assumptions!$B$11)*Assumptions!$G$54:$G$55)*Assumptions!$B$22/Assumptions!$B$11 -> 1666.6667 | Q15: =SUMPRODUCT((16-Assumptions!$F$54:$F$55+1>0)*(16-Assumptions!$F$54:$F$55+1<=Assumptions!$B$11)*Assumptions!$G$54:$G$55)*Assumptions!$B$22/Assumptions!$B$11 -> 1666.6667 | R15: =SUMPRODUCT((17-Assumptions!$F$54:$F$55+1>0)*(17-Assumptions!$F$54:$F$55+1<=Assumptions!$B$11)*Assumptions!$G$54:$G$55)*Assumptions!$B$22/Assumptions!$B$11 -> 1666.6667 | S15: =SUMPRODUCT((18-Assumptions!$F$54:$F$55+1>0)*(18-Assumptions!$F$54:$F$55+1<=Assumptions!$B$11)*Assumptions!$G$54:$G$55)*Assumptions!$B$22/Assumptions!$B$11 -> 1666.6667 | T15: =SUMPRODUCT((19-Assumptions!$F$54:$F$55+1>0)*(19-Assumptions!$F$54:$F$55+1<=Assumptions!$B$11)*Assumptions!$G$54:$G$55)*Assumptions!$B$22/Assumptions!$B$11 -> 1666.6667 | U15: =SUMPRODUCT((20-Assumptions!$F$54:$F$55+1>0)*(20-Assumptions!$F$54:$F$55+1<=Assumptions!$B$11)*Assumptions!$G$54:$G$55)*Assumptions!$B$22/Assumptions!$B$11 -> 1666.6667 | V15: =SUMPRODUCT((21-Assumptions!$F$54:$F$55+1>0)*(21-Assumptions!$F$54:$F$55+1<=Assumptions!$B$11)*Assumptions!$G$54:$G$55)*Assumptions!$B$22/Assumptions!$B$11 -> 1666.6667 | W15: =SUMPRODUCT((22-Assumptions!$F$54:$F$55+1>0)*(22-Assumptions!$F$54:$F$55+1<=Assumptions!$B$11)*Assumptions!$G$54:$G$55)*Assumptions!$B$22/Assumptions!$B$11 -> 1666.6667 | X15: =SUMPRODUCT((23-Assumptions!$F$54:$F$55+1>0)*(23-Assumptions!$F$54:$F$55+1<=Assumptions!$B$11)*Assumptions!$G$54:$G$55)*Assumptions!$B$22/Assumptions!$B$11 -> 1666.6667 | Y15: =SUMPRODUCT((24-Assumptions!$F$54:$F$55+1>0)*(24-Assumptions!$F$54:$F$55+1<=Assumptions!$B$11)*Assumptions!$G$54:$G$55)*Assumptions!$B$22/Assumptions!$B$11 -> 1666.6667 | Z15: =SUM(B15:Y15) -> 36250
A16: 损益费用合计 | B16: =B13+B15 -> 40431.025 | C16: =C13+C15 -> 40431.025 | D16: =D13+D15 -> 40431.025 | E16: =E13+E15 -> 47181.025 | F16: =F13+F15 -> 47181.025 | G16: =G13+G15 -> 69681.025 | H16: =H13+H15 -> 67500.704 | I16: =I13+I15 -> 67500.704 | ... Y16: =Y13+Y15 -> 306528.91 | Z16: =SUM(B16:Y16) -> 2576158.6
A17: 常规固定与专项支出 | B17: =SUM(B4:B10) -> 39389.358 | C17: =SUM(C4:C10) -> 39389.358 | D17: =SUM(D4:D10) -> 39389.358 | E17: =SUM(E4:E10) -> 46139.358 | F17: =SUM(F4:F10) -> 46139.358 | G17: =SUM(G4:G10) -> 68639.358 | H17: =SUM(H4:H10) -> 65834.037 | I17: =SUM(I4:I10) -> 65834.037 | ... Y17: =SUM(Y4:Y10) -> 101834.04 | Z17: =SUM(B17:Y17) -> 1626098.8
A18: 常规经常性支出 | B18: =SUM(B4:B9) -> 39389.358 | C18: =SUM(C4:C9) -> 39389.358 | D18: =SUM(D4:D9) -> 39389.358 | E18: =SUM(E4:E9) -> 46139.358 | F18: =SUM(F4:F9) -> 46139.358 | G18: =SUM(G4:G9) -> 46139.358 | H18: =SUM(H4:H9) -> 65834.037 | I18: =SUM(I4:I9) -> 65834.037 | ... Y18: =SUM(Y4:Y9) -> 71834.037 | Z18: =SUM(B18:Y18) -> 1513598.8
A26: 基准建设
A27: 月份 | B27: =EDATE(Assumptions!$B$3,0) -> 46327 | C27: =EDATE(Assumptions!$B$3,1) -> 46357 | D27: =EDATE(Assumptions!$B$3,2) -> 46388 | E27: =EDATE(Assumptions!$B$3,3) -> 46419 | F27: =EDATE(Assumptions!$B$3,4) -> 46447 | G27: =EDATE(Assumptions!$B$3,5) -> 46478 | H27: =EDATE(Assumptions!$B$3,6) -> 46508 | I27: =EDATE(Assumptions!$B$3,7) -> 46539 | J27: =EDATE(Assumptions!$B$3,8) -> 46569 | K27: =EDATE(Assumptions!$B$3,9) -> 46600 | L27: =EDATE(Assumptions!$B$3,10) -> 46631 | M27: =EDATE(Assumptions!$B$3,11) -> 46661 | N27: =EDATE(Assumptions!$B$3,12) -> 46692 | O27: =EDATE(Assumptions!$B$3,13) -> 46722 | P27: =EDATE(Assumptions!$B$3,14) -> 46753 | Q27: =EDATE(Assumptions!$B$3,15) -> 46784 | R27: =EDATE(Assumptions!$B$3,16) -> 46813 | S27: =EDATE(Assumptions!$B$3,17) -> 46844 | T27: =EDATE(Assumptions!$B$3,18) -> 46874 | U27: =EDATE(Assumptions!$B$3,19) -> 46905 | V27: =EDATE(Assumptions!$B$3,20) -> 46935 | W27: =EDATE(Assumptions!$B$3,21) -> 46966 | X27: =EDATE(Assumptions!$B$3,22) -> 46997 | Y27: =EDATE(Assumptions!$B$3,23) -> 47027 | Z27: 24个月合计 / 期末
A28: 等效资源人力 | B28: =IF(1<=6,Assumptions!$C$17,Assumptions!$C$18) -> 3 | C28: =IF(2<=6,Assumptions!$C$17,Assumptions!$C$18) -> 3 | D28: =IF(3<=6,Assumptions!$C$17,Assumptions!$C$18) -> 3 | E28: =IF(4<=6,Assumptions!$C$17,Assumptions!$C$18) -> 3 | F28: =IF(5<=6,Assumptions!$C$17,Assumptions!$C$18) -> 3 | G28: =IF(6<=6,Assumptions!$C$17,Assumptions!$C$18) -> 3 | H28: =IF(7<=6,Assumptions!$C$17,Assumptions!$C$18) -> 4 | I28: =IF(8<=6,Assumptions!$C$17,Assumptions!$C$18) -> 4 | J28: =IF(9<=6,Assumptions!$C$17,Assumptions!$C$18) -> 4 | K28: =IF(10<=6,Assumptions!$C$17,Assumptions!$C$18) -> 4 | L28: =IF(11<=6,Assumptions!$C$17,Assumptions!$C$18) -> 4 | M28: =IF(12<=6,Assumptions!$C$17,Assumptions!$C$18) -> 4 | N28: =IF(13<=6,Assumptions!$C$17,Assumptions!$C$18) -> 4 | O28: =IF(14<=6,Assumptions!$C$17,Assumptions!$C$18) -> 4 | P28: =IF(15<=6,Assumptions!$C$17,Assumptions!$C$18) -> 4 | Q28: =IF(16<=6,Assumptions!$C$17,Assumptions!$C$18) -> 4 | R28: =IF(17<=6,Assumptions!$C$17,Assumptions!$C$18) -> 4 | S28: =IF(18<=6,Assumptions!$C$17,Assumptions!$C$18) -> 4 | T28: =IF(19<=6,Assumptions!$C$17,Assumptions!$C$18) -> 4 | U28: =IF(20<=6,Assumptions!$C$17,Assumptions!$C$18) -> 4 | V28: =IF(21<=6,Assumptions!$C$17,Assumptions!$C$18) -> 4 | W28: =IF(22<=6,Assumptions!$C$17,Assumptions!$C$18) -> 4 | X28: =IF(23<=6,Assumptions!$C$17,Assumptions!$C$18) -> 4 | Y28: =IF(24<=6,Assumptions!$C$17,Assumptions!$C$18) -> 4 | Z28: =SUM(B28:Y28) -> 90
A29: 综合人力现金 | B29: =B28*Assumptions!$C$19 -> 60000 | C29: =C28*Assumptions!$C$19 -> 60000 | D29: =D28*Assumptions!$C$19 -> 60000 | E29: =E28*Assumptions!$C$19 -> 60000 | F29: =F28*Assumptions!$C$19 -> 60000 | G29: =G28*Assumptions!$C$19 -> 60000 | H29: =H28*Assumptions!$C$19 -> 80000 | I29: =I28*Assumptions!$C$19 -> 80000 | ... Y29: =Y28*Assumptions!$C$19 -> 80000 | Z29: =SUM(B29:Y29) -> 1800000
A30: 内部研发Agent预算 | B30: =B28*Assumptions!$B$32*Assumptions!$C$22 -> 5778.7158 | C30: =C28*Assumptions!$B$32*Assumptions!$C$22 -> 5778.7158 | D30: =D28*Assumptions!$B$32*Assumptions!$C$22 -> 5778.7158 | E30: =E28*Assumptions!$B$32*Assumptions!$C$22 -> 5778.7158 | F30: =F28*Assumptions!$B$32*Assumptions!$C$22 -> 5778.7158 | G30: =G28*Assumptions!$B$32*Assumptions!$C$22 -> 5778.7158 | H30: =H28*Assumptions!$B$32*Assumptions!$C$22 -> 7704.9544 | I30: =I28*Assumptions!$B$32*Assumptions!$C$22 -> 7704.9544 | ... Y30: =Y28*Assumptions!$B$32*Assumptions!$C$22 -> 7704.9544 | Z30: =SUM(B30:Y30) -> 173361.47
A31: 云基础设施 | B31: =IF(1<=6,Assumptions!$B$34,IF(1<=12,Assumptions!$B$35,Assumptions!$B$36))*Assumptions!$C$22 -> 3000 | C31: =IF(2<=6,Assumptions!$B$34,IF(2<=12,Assumptions!$B$35,Assumptions!$B$36))*Assumptions!$C$22 -> 3000 | D31: =IF(3<=6,Assumptions!$B$34,IF(3<=12,Assumptions!$B$35,Assumptions!$B$36))*Assumptions!$C$22 -> 3000 | E31: =IF(4<=6,Assumptions!$B$34,IF(4<=12,Assumptions!$B$35,Assumptions!$B$36))*Assumptions!$C$22 -> 3000 | F31: =IF(5<=6,Assumptions!$B$34,IF(5<=12,Assumptions!$B$35,Assumptions!$B$36))*Assumptions!$C$22 -> 3000 | G31: =IF(6<=6,Assumptions!$B$34,IF(6<=12,Assumptions!$B$35,Assumptions!$B$36))*Assumptions!$C$22 -> 3000 | H31: =IF(7<=6,Assumptions!$B$34,IF(7<=12,Assumptions!$B$35,Assumptions!$B$36))*Assumptions!$C$22 -> 6000 | I31: =IF(8<=6,Assumptions!$B$34,IF(8<=12,Assumptions!$B$35,Assumptions!$B$36))*Assumptions!$C$22 -> 6000 | J31: =IF(9<=6,Assumptions!$B$34,IF(9<=12,Assumptions!$B$35,Assumptions!$B$36))*Assumptions!$C$22 -> 6000 | K31: =IF(10<=6,Assumptions!$B$34,IF(10<=12,Assumptions!$B$35,Assumptions!$B$36))*Assumptions!$C$22 -> 6000 | L31: =IF(11<=6,Assumptions!$B$34,IF(11<=12,Assumptions!$B$35,Assumptions!$B$36))*Assumptions!$C$22 -> 6000 | M31: =IF(12<=6,Assumptions!$B$34,IF(12<=12,Assumptions!$B$35,Assumptions!$B$36))*Assumptions!$C$22 -> 6000 | N31: =IF(13<=6,Assumptions!$B$34,IF(13<=12,Assumptions!$B$35,Assumptions!$B$36))*Assumptions!$C$22 -> 9000 | O31: =IF(14<=6,Assumptions!$B$34,IF(14<=12,Assumptions!$B$35,Assumptions!$B$36))*Assumptions!$C$22 -> 9000 | P31: =IF(15<=6,Assumptions!$B$34,IF(15<=12,Assumptions!$B$35,Assumptions!$B$36))*Assumptions!$C$22 -> 9000 | Q31: =IF(16<=6,Assumptions!$B$34,IF(16<=12,Assumptions!$B$35,Assumptions!$B$36))*Assumptions!$C$22 -> 9000 | R31: =IF(17<=6,Assumptions!$B$34,IF(17<=12,Assumptions!$B$35,Assumptions!$B$36))*Assumptions!$C$22 -> 9000 | S31: =IF(18<=6,Assumptions!$B$34,IF(18<=12,Assumptions!$B$35,Assumptions!$B$36))*Assumptions!$C$22 -> 9000 | T31: =IF(19<=6,Assumptions!$B$34,IF(19<=12,Assumptions!$B$35,Assumptions!$B$36))*Assumptions!$C$22 -> 9000 | U31: =IF(20<=6,Assumptions!$B$34,IF(20<=12,Assumptions!$B$35,Assumptions!$B$36))*Assumptions!$C$22 -> 9000 | V31: =IF(21<=6,Assumptions!$B$34,IF(21<=12,Assumptions!$B$35,Assumptions!$B$36))*Assumptions!$C$22 -> 9000 | W31: =IF(22<=6,Assumptions!$B$34,IF(22<=12,Assumptions!$B$35,Assumptions!$B$36))*Assumptions!$C$22 -> 9000 | X31: =IF(23<=6,Assumptions!$B$34,IF(23<=12,Assumptions!$B$35,Assumptions!$B$36))*Assumptions!$C$22 -> 9000 | Y31: =IF(24<=6,Assumptions!$B$34,IF(24<=12,Assumptions!$B$35,Assumptions!$B$36))*Assumptions!$C$22 -> 9000 | Z31: =SUM(B31:Y31) -> 162000
A32: 教学共创与试用 | B32: =IF(1<=3,Assumptions!$B$37,IF(1<=12,Assumptions!$B$38,Assumptions!$B$39))*Assumptions!$C$22 -> 0 | C32: =IF(2<=3,Assumptions!$B$37,IF(2<=12,Assumptions!$B$38,Assumptions!$B$39))*Assumptions!$C$22 -> 0 | D32: =IF(3<=3,Assumptions!$B$37,IF(3<=12,Assumptions!$B$38,Assumptions!$B$39))*Assumptions!$C$22 -> 0 | E32: =IF(4<=3,Assumptions!$B$37,IF(4<=12,Assumptions!$B$38,Assumptions!$B$39))*Assumptions!$C$22 -> 6000 | F32: =IF(5<=3,Assumptions!$B$37,IF(5<=12,Assumptions!$B$38,Assumptions!$B$39))*Assumptions!$C$22 -> 6000 | G32: =IF(6<=3,Assumptions!$B$37,IF(6<=12,Assumptions!$B$38,Assumptions!$B$39))*Assumptions!$C$22 -> 6000 | H32: =IF(7<=3,Assumptions!$B$37,IF(7<=12,Assumptions!$B$38,Assumptions!$B$39))*Assumptions!$C$22 -> 6000 | I32: =IF(8<=3,Assumptions!$B$37,IF(8<=12,Assumptions!$B$38,Assumptions!$B$39))*Assumptions!$C$22 -> 6000 | J32: =IF(9<=3,Assumptions!$B$37,IF(9<=12,Assumptions!$B$38,Assumptions!$B$39))*Assumptions!$C$22 -> 6000 | K32: =IF(10<=3,Assumptions!$B$37,IF(10<=12,Assumptions!$B$38,Assumptions!$B$39))*Assumptions!$C$22 -> 6000 | L32: =IF(11<=3,Assumptions!$B$37,IF(11<=12,Assumptions!$B$38,Assumptions!$B$39))*Assumptions!$C$22 -> 6000 | M32: =IF(12<=3,Assumptions!$B$37,IF(12<=12,Assumptions!$B$38,Assumptions!$B$39))*Assumptions!$C$22 -> 6000 | N32: =IF(13<=3,Assumptions!$B$37,IF(13<=12,Assumptions!$B$38,Assumptions!$B$39))*Assumptions!$C$22 -> 8000 | O32: =IF(14<=3,Assumptions!$B$37,IF(14<=12,Assumptions!$B$38,Assumptions!$B$39))*Assumptions!$C$22 -> 8000 | P32: =IF(15<=3,Assumptions!$B$37,IF(15<=12,Assumptions!$B$38,Assumptions!$B$39))*Assumptions!$C$22 -> 8000 | Q32: =IF(16<=3,Assumptions!$B$37,IF(16<=12,Assumptions!$B$38,Assumptions!$B$39))*Assumptions!$C$22 -> 8000 | R32: =IF(17<=3,Assumptions!$B$37,IF(17<=12,Assumptions!$B$38,Assumptions!$B$39))*Assumptions!$C$22 -> 8000 | S32: =IF(18<=3,Assumptions!$B$37,IF(18<=12,Assumptions!$B$38,Assumptions!$B$39))*Assumptions!$C$22 -> 8000 | T32: =IF(19<=3,Assumptions!$B$37,IF(19<=12,Assumptions!$B$38,Assumptions!$B$39))*Assumptions!$C$22 -> 8000 | U32: =IF(20<=3,Assumptions!$B$37,IF(20<=12,Assumptions!$B$38,Assumptions!$B$39))*Assumptions!$C$22 -> 8000 | V32: =IF(21<=3,Assumptions!$B$37,IF(21<=12,Assumptions!$B$38,Assumptions!$B$39))*Assumptions!$C$22 -> 8000 | W32: =IF(22<=3,Assumptions!$B$37,IF(22<=12,Assumptions!$B$38,Assumptions!$B$39))*Assumptions!$C$22 -> 8000 | X32: =IF(23<=3,Assumptions!$B$37,IF(23<=12,Assumptions!$B$38,Assumptions!$B$39))*Assumptions!$C$22 -> 8000 | Y32: =IF(24<=3,Assumptions!$B$37,IF(24<=12,Assumptions!$B$38,Assumptions!$B$39))*Assumptions!$C$22 -> 8000 | Z32: =SUM(B32:Y32) -> 150000
A33: 社区活动与材料 | B33: =IF(1<=3,Assumptions!$B$40,IF(1<=12,Assumptions!$B$41,Assumptions!$B$42))*Assumptions!$C$22 -> 0 | C33: =IF(2<=3,Assumptions!$B$40,IF(2<=12,Assumptions!$B$41,Assumptions!$B$42))*Assumptions!$C$22 -> 0 | D33: =IF(3<=3,Assumptions!$B$40,IF(3<=12,Assumptions!$B$41,Assumptions!$B$42))*Assumptions!$C$22 -> 0 | E33: =IF(4<=3,Assumptions!$B$40,IF(4<=12,Assumptions!$B$41,Assumptions!$B$42))*Assumptions!$C$22 -> 3000 | F33: =IF(5<=3,Assumptions!$B$40,IF(5<=12,Assumptions!$B$41,Assumptions!$B$42))*Assumptions!$C$22 -> 3000 | G33: =IF(6<=3,Assumptions!$B$40,IF(6<=12,Assumptions!$B$41,Assumptions!$B$42))*Assumptions!$C$22 -> 3000 | H33: =IF(7<=3,Assumptions!$B$40,IF(7<=12,Assumptions!$B$41,Assumptions!$B$42))*Assumptions!$C$22 -> 3000 | I33: =IF(8<=3,Assumptions!$B$40,IF(8<=12,Assumptions!$B$41,Assumptions!$B$42))*Assumptions!$C$22 -> 3000 | J33: =IF(9<=3,Assumptions!$B$40,IF(9<=12,Assumptions!$B$41,Assumptions!$B$42))*Assumptions!$C$22 -> 3000 | K33: =IF(10<=3,Assumptions!$B$40,IF(10<=12,Assumptions!$B$41,Assumptions!$B$42))*Assumptions!$C$22 -> 3000 | L33: =IF(11<=3,Assumptions!$B$40,IF(11<=12,Assumptions!$B$41,Assumptions!$B$42))*Assumptions!$C$22 -> 3000 | M33: =IF(12<=3,Assumptions!$B$40,IF(12<=12,Assumptions!$B$41,Assumptions!$B$42))*Assumptions!$C$22 -> 3000 | N33: =IF(13<=3,Assumptions!$B$40,IF(13<=12,Assumptions!$B$41,Assumptions!$B$42))*Assumptions!$C$22 -> 6000 | O33: =IF(14<=3,Assumptions!$B$40,IF(14<=12,Assumptions!$B$41,Assumptions!$B$42))*Assumptions!$C$22 -> 6000 | P33: =IF(15<=3,Assumptions!$B$40,IF(15<=12,Assumptions!$B$41,Assumptions!$B$42))*Assumptions!$C$22 -> 6000 | Q33: =IF(16<=3,Assumptions!$B$40,IF(16<=12,Assumptions!$B$41,Assumptions!$B$42))*Assumptions!$C$22 -> 6000 | R33: =IF(17<=3,Assumptions!$B$40,IF(17<=12,Assumptions!$B$41,Assumptions!$B$42))*Assumptions!$C$22 -> 6000 | S33: =IF(18<=3,Assumptions!$B$40,IF(18<=12,Assumptions!$B$41,Assumptions!$B$42))*Assumptions!$C$22 -> 6000 | T33: =IF(19<=3,Assumptions!$B$40,IF(19<=12,Assumptions!$B$41,Assumptions!$B$42))*Assumptions!$C$22 -> 6000 | U33: =IF(20<=3,Assumptions!$B$40,IF(20<=12,Assumptions!$B$41,Assumptions!$B$42))*Assumptions!$C$22 -> 6000 | V33: =IF(21<=3,Assumptions!$B$40,IF(21<=12,Assumptions!$B$41,Assumptions!$B$42))*Assumptions!$C$22 -> 6000 | W33: =IF(22<=3,Assumptions!$B$40,IF(22<=12,Assumptions!$B$41,Assumptions!$B$42))*Assumptions!$C$22 -> 6000 | X33: =IF(23<=3,Assumptions!$B$40,IF(23<=12,Assumptions!$B$41,Assumptions!$B$42))*Assumptions!$C$22 -> 6000 | Y33: =IF(24<=3,Assumptions!$B$40,IF(24<=12,Assumptions!$B$41,Assumptions!$B$42))*Assumptions!$C$22 -> 6000 | Z33: =SUM(B33:Y33) -> 99000
A34: 一般运营与合规预算 | B34: =Assumptions!$B$43*Assumptions!$C$22 -> 3000 | C34: =Assumptions!$B$43*Assumptions!$C$22 -> 3000 | D34: =Assumptions!$B$43*Assumptions!$C$22 -> 3000 | E34: =Assumptions!$B$43*Assumptions!$C$22 -> 3000 | F34: =Assumptions!$B$43*Assumptions!$C$22 -> 3000 | G34: =Assumptions!$B$43*Assumptions!$C$22 -> 3000 | H34: =Assumptions!$B$43*Assumptions!$C$22 -> 3000 | I34: =Assumptions!$B$43*Assumptions!$C$22 -> 3000 | ... Y34: =Assumptions!$B$43*Assumptions!$C$22 -> 3000 | Z34: =SUM(B34:Y34) -> 72000
A35: 专项外部交付 | B35: =SUMIF(Assumptions!$F$47:$F$50,1,Assumptions!$G$47:$G$50)*Assumptions!$C$22 -> 0 | C35: =SUMIF(Assumptions!$F$47:$F$50,2,Assumptions!$G$47:$G$50)*Assumptions!$C$22 -> 0 | D35: =SUMIF(Assumptions!$F$47:$F$50,3,Assumptions!$G$47:$G$50)*Assumptions!$C$22 -> 0 | E35: =SUMIF(Assumptions!$F$47:$F$50,4,Assumptions!$G$47:$G$50)*Assumptions!$C$22 -> 0 | F35: =SUMIF(Assumptions!$F$47:$F$50,5,Assumptions!$G$47:$G$50)*Assumptions!$C$22 -> 0 | G35: =SUMIF(Assumptions!$F$47:$F$50,6,Assumptions!$G$47:$G$50)*Assumptions!$C$22 -> 30000 | H35: =SUMIF(Assumptions!$F$47:$F$50,7,Assumptions!$G$47:$G$50)*Assumptions!$C$22 -> 0 | I35: =SUMIF(Assumptions!$F$47:$F$50,8,Assumptions!$G$47:$G$50)*Assumptions!$C$22 -> 0 | J35: =SUMIF(Assumptions!$F$47:$F$50,9,Assumptions!$G$47:$G$50)*Assumptions!$C$22 -> 0 | K35: =SUMIF(Assumptions!$F$47:$F$50,10,Assumptions!$G$47:$G$50)*Assumptions!$C$22 -> 0 | L35: =SUMIF(Assumptions!$F$47:$F$50,11,Assumptions!$G$47:$G$50)*Assumptions!$C$22 -> 0 | M35: =SUMIF(Assumptions!$F$47:$F$50,12,Assumptions!$G$47:$G$50)*Assumptions!$C$22 -> 40000 | N35: =SUMIF(Assumptions!$F$47:$F$50,13,Assumptions!$G$47:$G$50)*Assumptions!$C$22 -> 0 | O35: =SUMIF(Assumptions!$F$47:$F$50,14,Assumptions!$G$47:$G$50)*Assumptions!$C$22 -> 0 | P35: =SUMIF(Assumptions!$F$47:$F$50,15,Assumptions!$G$47:$G$50)*Assumptions!$C$22 -> 0 | Q35: =SUMIF(Assumptions!$F$47:$F$50,16,Assumptions!$G$47:$G$50)*Assumptions!$C$22 -> 0 | R35: =SUMIF(Assumptions!$F$47:$F$50,17,Assumptions!$G$47:$G$50)*Assumptions!$C$22 -> 0 | S35: =SUMIF(Assumptions!$F$47:$F$50,18,Assumptions!$G$47:$G$50)*Assumptions!$C$22 -> 40000 | T35: =SUMIF(Assumptions!$F$47:$F$50,19,Assumptions!$G$47:$G$50)*Assumptions!$C$22 -> 0 | U35: =SUMIF(Assumptions!$F$47:$F$50,20,Assumptions!$G$47:$G$50)*Assumptions!$C$22 -> 0 | V35: =SUMIF(Assumptions!$F$47:$F$50,21,Assumptions!$G$47:$G$50)*Assumptions!$C$22 -> 0 | W35: =SUMIF(Assumptions!$F$47:$F$50,22,Assumptions!$G$47:$G$50)*Assumptions!$C$22 -> 0 | X35: =SUMIF(Assumptions!$F$47:$F$50,23,Assumptions!$G$47:$G$50)*Assumptions!$C$22 -> 0 | Y35: =SUMIF(Assumptions!$F$47:$F$50,24,Assumptions!$G$47:$G$50)*Assumptions!$C$22 -> 40000 | Z35: =SUM(B35:Y35) -> 150000
A36: 条件用户算力成本 | B36: =Cohorts!B24 -> 0 | C36: =Cohorts!C24 -> 0 | D36: =Cohorts!D24 -> 0 | E36: =Cohorts!E24 -> 0 | F36: =Cohorts!F24 -> 0 | G36: =Cohorts!G24 -> 0 | H36: =Cohorts!H24 -> 0 | I36: =Cohorts!I24 -> 0 | ... Y36: =Cohorts!Y24 -> 676760.68 | Z36: =SUM(B36:Y36) -> 3046032.6
A37: 实际非退还合作费（未录入） | B37: =IF(1=Assumptions!$B$10,Assumptions!$B$7,0) -> 0 | C37: =IF(2=Assumptions!$B$10,Assumptions!$B$7,0) -> 0 | D37: =IF(3=Assumptions!$B$10,Assumptions!$B$7,0) -> 0 | E37: =IF(4=Assumptions!$B$10,Assumptions!$B$7,0) -> 0 | F37: =IF(5=Assumptions!$B$10,Assumptions!$B$7,0) -> 0 | G37: =IF(6=Assumptions!$B$10,Assumptions!$B$7,0) -> 0 | H37: =IF(7=Assumptions!$B$10,Assumptions!$B$7,0) -> 0 | I37: =IF(8=Assumptions!$B$10,Assumptions!$B$7,0) -> 0 | J37: =IF(9=Assumptions!$B$10,Assumptions!$B$7,0) -> 0 | K37: =IF(10=Assumptions!$B$10,Assumptions!$B$7,0) -> 0 | L37: =IF(11=Assumptions!$B$10,Assumptions!$B$7,0) -> 0 | M37: =IF(12=Assumptions!$B$10,Assumptions!$B$7,0) -> 0 | N37: =IF(13=Assumptions!$B$10,Assumptions!$B$7,0) -> 0 | O37: =IF(14=Assumptions!$B$10,Assumptions!$B$7,0) -> 0 | P37: =IF(15=Assumptions!$B$10,Assumptions!$B$7,0) -> 0 | Q37: =IF(16=Assumptions!$B$10,Assumptions!$B$7,0) -> 0 | R37: =IF(17=Assumptions!$B$10,Assumptions!$B$7,0) -> 0 | S37: =IF(18=Assumptions!$B$10,Assumptions!$B$7,0) -> 0 | T37: =IF(19=Assumptions!$B$10,Assumptions!$B$7,0) -> 0 | U37: =IF(20=Assumptions!$B$10,Assumptions!$B$7,0) -> 0 | V37: =IF(21=Assumptions!$B$10,Assumptions!$B$7,0) -> 0 | W37: =IF(22=Assumptions!$B$10,Assumptions!$B$7,0) -> 0 | X37: =IF(23=Assumptions!$B$10,Assumptions!$B$7,0) -> 0 | Y37: =IF(24=Assumptions!$B$10,Assumptions!$B$7,0) -> 0 | Z37: =SUM(B37:Y37) -> 0
A38: 费用现金合计（不含设备） | B38: =SUM(B29:B37) -> 71778.716 | C38: =SUM(C29:C37) -> 71778.716 | D38: =SUM(D29:D37) -> 71778.716 | E38: =SUM(E29:E37) -> 80778.716 | F38: =SUM(F29:F37) -> 80778.716 | G38: =SUM(G29:G37) -> 110778.72 | H38: =SUM(H29:H37) -> 105704.95 | I38: =SUM(I29:I37) -> 105704.95 | ... Y38: =SUM(Y29:Y37) -> 830465.63 | Z38: =SUM(B38:Y38) -> 5652394
A39: 设备购置现金 | B39: =SUMIF(Assumptions!$F$54:$F$55,1,Assumptions!$G$54:$G$55)*Assumptions!$C$22 -> 50000 | C39: =SUMIF(Assumptions!$F$54:$F$55,2,Assumptions!$G$54:$G$55)*Assumptions!$C$22 -> 0 | D39: =SUMIF(Assumptions!$F$54:$F$55,3,Assumptions!$G$54:$G$55)*Assumptions!$C$22 -> 0 | E39: =SUMIF(Assumptions!$F$54:$F$55,4,Assumptions!$G$54:$G$55)*Assumptions!$C$22 -> 0 | F39: =SUMIF(Assumptions!$F$54:$F$55,5,Assumptions!$G$54:$G$55)*Assumptions!$C$22 -> 0 | G39: =SUMIF(Assumptions!$F$54:$F$55,6,Assumptions!$G$54:$G$55)*Assumptions!$C$22 -> 0 | H39: =SUMIF(Assumptions!$F$54:$F$55,7,Assumptions!$G$54:$G$55)*Assumptions!$C$22 -> 30000 | I39: =SUMIF(Assumptions!$F$54:$F$55,8,Assumptions!$G$54:$G$55)*Assumptions!$C$22 -> 0 | J39: =SUMIF(Assumptions!$F$54:$F$55,9,Assumptions!$G$54:$G$55)*Assumptions!$C$22 -> 0 | K39: =SUMIF(Assumptions!$F$54:$F$55,10,Assumptions!$G$54:$G$55)*Assumptions!$C$22 -> 0 | L39: =SUMIF(Assumptions!$F$54:$F$55,11,Assumptions!$G$54:$G$55)*Assumptions!$C$22 -> 0 | M39: =SUMIF(Assumptions!$F$54:$F$55,12,Assumptions!$G$54:$G$55)*Assumptions!$C$22 -> 0 | N39: =SUMIF(Assumptions!$F$54:$F$55,13,Assumptions!$G$54:$G$55)*Assumptions!$C$22 -> 0 | O39: =SUMIF(Assumptions!$F$54:$F$55,14,Assumptions!$G$54:$G$55)*Assumptions!$C$22 -> 0 | P39: =SUMIF(Assumptions!$F$54:$F$55,15,Assumptions!$G$54:$G$55)*Assumptions!$C$22 -> 0 | Q39: =SUMIF(Assumptions!$F$54:$F$55,16,Assumptions!$G$54:$G$55)*Assumptions!$C$22 -> 0 | R39: =SUMIF(Assumptions!$F$54:$F$55,17,Assumptions!$G$54:$G$55)*Assumptions!$C$22 -> 0 | S39: =SUMIF(Assumptions!$F$54:$F$55,18,Assumptions!$G$54:$G$55)*Assumptions!$C$22 -> 0 | T39: =SUMIF(Assumptions!$F$54:$F$55,19,Assumptions!$G$54:$G$55)*Assumptions!$C$22 -> 0 | U39: =SUMIF(Assumptions!$F$54:$F$55,20,Assumptions!$G$54:$G$55)*Assumptions!$C$22 -> 0 | V39: =SUMIF(Assumptions!$F$54:$F$55,21,Assumptions!$G$54:$G$55)*Assumptions!$C$22 -> 0 | W39: =SUMIF(Assumptions!$F$54:$F$55,22,Assumptions!$G$54:$G$55)*Assumptions!$C$22 -> 0 | X39: =SUMIF(Assumptions!$F$54:$F$55,23,Assumptions!$G$54:$G$55)*Assumptions!$C$22 -> 0 | Y39: =SUMIF(Assumptions!$F$54:$F$55,24,Assumptions!$G$54:$G$55)*Assumptions!$C$22 -> 0 | Z39: =SUM(B39:Y39) -> 80000
A40: 当月设备折旧 | B40: =SUMPRODUCT((1-Assumptions!$F$54:$F$55+1>0)*(1-Assumptions!$F$54:$F$55+1<=Assumptions!$B$11)*Assumptions!$G$54:$G$55)*Assumptions!$C$22/Assumptions!$B$11 -> 1388.8889 | C40: =SUMPRODUCT((2-Assumptions!$F$54:$F$55+1>0)*(2-Assumptions!$F$54:$F$55+1<=Assumptions!$B$11)*Assumptions!$G$54:$G$55)*Assumptions!$C$22/Assumptions!$B$11 -> 1388.8889 | D40: =SUMPRODUCT((3-Assumptions!$F$54:$F$55+1>0)*(3-Assumptions!$F$54:$F$55+1<=Assumptions!$B$11)*Assumptions!$G$54:$G$55)*Assumptions!$C$22/Assumptions!$B$11 -> 1388.8889 | E40: =SUMPRODUCT((4-Assumptions!$F$54:$F$55+1>0)*(4-Assumptions!$F$54:$F$55+1<=Assumptions!$B$11)*Assumptions!$G$54:$G$55)*Assumptions!$C$22/Assumptions!$B$11 -> 1388.8889 | F40: =SUMPRODUCT((5-Assumptions!$F$54:$F$55+1>0)*(5-Assumptions!$F$54:$F$55+1<=Assumptions!$B$11)*Assumptions!$G$54:$G$55)*Assumptions!$C$22/Assumptions!$B$11 -> 1388.8889 | G40: =SUMPRODUCT((6-Assumptions!$F$54:$F$55+1>0)*(6-Assumptions!$F$54:$F$55+1<=Assumptions!$B$11)*Assumptions!$G$54:$G$55)*Assumptions!$C$22/Assumptions!$B$11 -> 1388.8889 | H40: =SUMPRODUCT((7-Assumptions!$F$54:$F$55+1>0)*(7-Assumptions!$F$54:$F$55+1<=Assumptions!$B$11)*Assumptions!$G$54:$G$55)*Assumptions!$C$22/Assumptions!$B$11 -> 2222.2222 | I40: =SUMPRODUCT((8-Assumptions!$F$54:$F$55+1>0)*(8-Assumptions!$F$54:$F$55+1<=Assumptions!$B$11)*Assumptions!$G$54:$G$55)*Assumptions!$C$22/Assumptions!$B$11 -> 2222.2222 | J40: =SUMPRODUCT((9-Assumptions!$F$54:$F$55+1>0)*(9-Assumptions!$F$54:$F$55+1<=Assumptions!$B$11)*Assumptions!$G$54:$G$55)*Assumptions!$C$22/Assumptions!$B$11 -> 2222.2222 | K40: =SUMPRODUCT((10-Assumptions!$F$54:$F$55+1>0)*(10-Assumptions!$F$54:$F$55+1<=Assumptions!$B$11)*Assumptions!$G$54:$G$55)*Assumptions!$C$22/Assumptions!$B$11 -> 2222.2222 | L40: =SUMPRODUCT((11-Assumptions!$F$54:$F$55+1>0)*(11-Assumptions!$F$54:$F$55+1<=Assumptions!$B$11)*Assumptions!$G$54:$G$55)*Assumptions!$C$22/Assumptions!$B$11 -> 2222.2222 | M40: =SUMPRODUCT((12-Assumptions!$F$54:$F$55+1>0)*(12-Assumptions!$F$54:$F$55+1<=Assumptions!$B$11)*Assumptions!$G$54:$G$55)*Assumptions!$C$22/Assumptions!$B$11 -> 2222.2222 | N40: =SUMPRODUCT((13-Assumptions!$F$54:$F$55+1>0)*(13-Assumptions!$F$54:$F$55+1<=Assumptions!$B$11)*Assumptions!$G$54:$G$55)*Assumptions!$C$22/Assumptions!$B$11 -> 2222.2222 | O40: =SUMPRODUCT((14-Assumptions!$F$54:$F$55+1>0)*(14-Assumptions!$F$54:$F$55+1<=Assumptions!$B$11)*Assumptions!$G$54:$G$55)*Assumptions!$C$22/Assumptions!$B$11 -> 2222.2222 | P40: =SUMPRODUCT((15-Assumptions!$F$54:$F$55+1>0)*(15-Assumptions!$F$54:$F$55+1<=Assumptions!$B$11)*Assumptions!$G$54:$G$55)*Assumptions!$C$22/Assumptions!$B$11 -> 2222.2222 | Q40: =SUMPRODUCT((16-Assumptions!$F$54:$F$55+1>0)*(16-Assumptions!$F$54:$F$55+1<=Assumptions!$B$11)*Assumptions!$G$54:$G$55)*Assumptions!$C$22/Assumptions!$B$11 -> 2222.2222 | R40: =SUMPRODUCT((17-Assumptions!$F$54:$F$55+1>0)*(17-Assumptions!$F$54:$F$55+1<=Assumptions!$B$11)*Assumptions!$G$54:$G$55)*Assumptions!$C$22/Assumptions!$B$11 -> 2222.2222 | S40: =SUMPRODUCT((18-Assumptions!$F$54:$F$55+1>0)*(18-Assumptions!$F$54:$F$55+1<=Assumptions!$B$11)*Assumptions!$G$54:$G$55)*Assumptions!$C$22/Assumptions!$B$11 -> 2222.2222 | T40: =SUMPRODUCT((19-Assumptions!$F$54:$F$55+1>0)*(19-Assumptions!$F$54:$F$55+1<=Assumptions!$B$11)*Assumptions!$G$54:$G$55)*Assumptions!$C$22/Assumptions!$B$11 -> 2222.2222 | U40: =SUMPRODUCT((20-Assumptions!$F$54:$F$55+1>0)*(20-Assumptions!$F$54:$F$55+1<=Assumptions!$B$11)*Assumptions!$G$54:$G$55)*Assumptions!$C$22/Assumptions!$B$11 -> 2222.2222 | V40: =SUMPRODUCT((21-Assumptions!$F$54:$F$55+1>0)*(21-Assumptions!$F$54:$F$55+1<=Assumptions!$B$11)*Assumptions!$G$54:$G$55)*Assumptions!$C$22/Assumptions!$B$11 -> 2222.2222 | W40: =SUMPRODUCT((22-Assumptions!$F$54:$F$55+1>0)*(22-Assumptions!$F$54:$F$55+1<=Assumptions!$B$11)*Assumptions!$G$54:$G$55)*Assumptions!$C$22/Assumptions!$B$11 -> 2222.2222 | X40: =SUMPRODUCT((23-Assumptions!$F$54:$F$55+1>0)*(23-Assumptions!$F$54:$F$55+1<=Assumptions!$B$11)*Assumptions!$G$54:$G$55)*Assumptions!$C$22/Assumptions!$B$11 -> 2222.2222 | Y40: =SUMPRODUCT((24-Assumptions!$F$54:$F$55+1>0)*(24-Assumptions!$F$54:$F$55+1<=Assumptions!$B$11)*Assumptions!$G$54:$G$55)*Assumptions!$C$22/Assumptions!$B$11 -> 2222.2222 | Z40: =SUM(B40:Y40) -> 48333.333
A41: 损益费用合计 | B41: =B38+B40 -> 73167.605 | C41: =C38+C40 -> 73167.605 | D41: =D38+D40 -> 73167.605 | E41: =E38+E40 -> 82167.605 | F41: =F38+F40 -> 82167.605 | G41: =G38+G40 -> 112167.6 | H41: =H38+H40 -> 107927.18 | I41: =I38+I40 -> 107927.18 | ... Y41: =Y38+Y40 -> 832687.86 | Z41: =SUM(B41:Y41) -> 5700727.4
A42: 常规固定与专项支出 | B42: =SUM(B29:B35) -> 71778.716 | C42: =SUM(C29:C35) -> 71778.716 | D42: =SUM(D29:D35) -> 71778.716 | E42: =SUM(E29:E35) -> 80778.716 | F42: =SUM(F29:F35) -> 80778.716 | G42: =SUM(G29:G35) -> 110778.72 | H42: =SUM(H29:H35) -> 105704.95 | I42: =SUM(I29:I35) -> 105704.95 | ... Y42: =SUM(Y29:Y35) -> 153704.95 | Z42: =SUM(B42:Y42) -> 2606361.5
A43: 常规经常性支出 | B43: =SUM(B29:B34) -> 71778.716 | C43: =SUM(C29:C34) -> 71778.716 | D43: =SUM(D29:D34) -> 71778.716 | E43: =SUM(E29:E34) -> 80778.716 | F43: =SUM(F29:F34) -> 80778.716 | G43: =SUM(G29:G34) -> 80778.716 | H43: =SUM(H29:H34) -> 105704.95 | I43: =SUM(I29:I34) -> 105704.95 | ... Y43: =SUM(Y29:Y34) -> 113704.95 | Z43: =SUM(B43:Y43) -> 2456361.5
A51: 高用量压力
A52: 月份 | B52: =EDATE(Assumptions!$B$3,0) -> 46327 | C52: =EDATE(Assumptions!$B$3,1) -> 46357 | D52: =EDATE(Assumptions!$B$3,2) -> 46388 | E52: =EDATE(Assumptions!$B$3,3) -> 46419 | F52: =EDATE(Assumptions!$B$3,4) -> 46447 | G52: =EDATE(Assumptions!$B$3,5) -> 46478 | H52: =EDATE(Assumptions!$B$3,6) -> 46508 | I52: =EDATE(Assumptions!$B$3,7) -> 46539 | J52: =EDATE(Assumptions!$B$3,8) -> 46569 | K52: =EDATE(Assumptions!$B$3,9) -> 46600 | L52: =EDATE(Assumptions!$B$3,10) -> 46631 | M52: =EDATE(Assumptions!$B$3,11) -> 46661 | N52: =EDATE(Assumptions!$B$3,12) -> 46692 | O52: =EDATE(Assumptions!$B$3,13) -> 46722 | P52: =EDATE(Assumptions!$B$3,14) -> 46753 | Q52: =EDATE(Assumptions!$B$3,15) -> 46784 | R52: =EDATE(Assumptions!$B$3,16) -> 46813 | S52: =EDATE(Assumptions!$B$3,17) -> 46844 | T52: =EDATE(Assumptions!$B$3,18) -> 46874 | U52: =EDATE(Assumptions!$B$3,19) -> 46905 | V52: =EDATE(Assumptions!$B$3,20) -> 46935 | W52: =EDATE(Assumptions!$B$3,21) -> 46966 | X52: =EDATE(Assumptions!$B$3,22) -> 46997 | Y52: =EDATE(Assumptions!$B$3,23) -> 47027 | Z52: 24个月合计 / 期末
A53: 等效资源人力 | B53: =IF(1<=6,Assumptions!$D$17,Assumptions!$D$18) -> 4 | C53: =IF(2<=6,Assumptions!$D$17,Assumptions!$D$18) -> 4 | D53: =IF(3<=6,Assumptions!$D$17,Assumptions!$D$18) -> 4 | E53: =IF(4<=6,Assumptions!$D$17,Assumptions!$D$18) -> 4 | F53: =IF(5<=6,Assumptions!$D$17,Assumptions!$D$18) -> 4 | G53: =IF(6<=6,Assumptions!$D$17,Assumptions!$D$18) -> 4 | H53: =IF(7<=6,Assumptions!$D$17,Assumptions!$D$18) -> 5 | I53: =IF(8<=6,Assumptions!$D$17,Assumptions!$D$18) -> 5 | J53: =IF(9<=6,Assumptions!$D$17,Assumptions!$D$18) -> 5 | K53: =IF(10<=6,Assumptions!$D$17,Assumptions!$D$18) -> 5 | L53: =IF(11<=6,Assumptions!$D$17,Assumptions!$D$18) -> 5 | M53: =IF(12<=6,Assumptions!$D$17,Assumptions!$D$18) -> 5 | N53: =IF(13<=6,Assumptions!$D$17,Assumptions!$D$18) -> 5 | O53: =IF(14<=6,Assumptions!$D$17,Assumptions!$D$18) -> 5 | P53: =IF(15<=6,Assumptions!$D$17,Assumptions!$D$18) -> 5 | Q53: =IF(16<=6,Assumptions!$D$17,Assumptions!$D$18) -> 5 | R53: =IF(17<=6,Assumptions!$D$17,Assumptions!$D$18) -> 5 | S53: =IF(18<=6,Assumptions!$D$17,Assumptions!$D$18) -> 5 | T53: =IF(19<=6,Assumptions!$D$17,Assumptions!$D$18) -> 5 | U53: =IF(20<=6,Assumptions!$D$17,Assumptions!$D$18) -> 5 | V53: =IF(21<=6,Assumptions!$D$17,Assumptions!$D$18) -> 5 | W53: =IF(22<=6,Assumptions!$D$17,Assumptions!$D$18) -> 5 | X53: =IF(23<=6,Assumptions!$D$17,Assumptions!$D$18) -> 5 | Y53: =IF(24<=6,Assumptions!$D$17,Assumptions!$D$18) -> 5 | Z53: =SUM(B53:Y53) -> 114
A54: 综合人力现金 | B54: =B53*Assumptions!$D$19 -> 96000 | C54: =C53*Assumptions!$D$19 -> 96000 | D54: =D53*Assumptions!$D$19 -> 96000 | E54: =E53*Assumptions!$D$19 -> 96000 | F54: =F53*Assumptions!$D$19 -> 96000 | G54: =G53*Assumptions!$D$19 -> 96000 | H54: =H53*Assumptions!$D$19 -> 120000 | I54: =I53*Assumptions!$D$19 -> 120000 | ... Y54: =Y53*Assumptions!$D$19 -> 120000 | Z54: =SUM(B54:Y54) -> 2736000
A55: 内部研发Agent预算 | B55: =B53*Assumptions!$B$32*Assumptions!$D$22 -> 11557.432 | C55: =C53*Assumptions!$B$32*Assumptions!$D$22 -> 11557.432 | D55: =D53*Assumptions!$B$32*Assumptions!$D$22 -> 11557.432 | E55: =E53*Assumptions!$B$32*Assumptions!$D$22 -> 11557.432 | F55: =F53*Assumptions!$B$32*Assumptions!$D$22 -> 11557.432 | G55: =G53*Assumptions!$B$32*Assumptions!$D$22 -> 11557.432 | H55: =H53*Assumptions!$B$32*Assumptions!$D$22 -> 14446.79 | I55: =I53*Assumptions!$B$32*Assumptions!$D$22 -> 14446.79 | ... Y55: =Y53*Assumptions!$B$32*Assumptions!$D$22 -> 14446.79 | Z55: =SUM(B55:Y55) -> 329386.8
A56: 云基础设施 | B56: =IF(1<=6,Assumptions!$B$34,IF(1<=12,Assumptions!$B$35,Assumptions!$B$36))*Assumptions!$D$22 -> 4500 | C56: =IF(2<=6,Assumptions!$B$34,IF(2<=12,Assumptions!$B$35,Assumptions!$B$36))*Assumptions!$D$22 -> 4500 | D56: =IF(3<=6,Assumptions!$B$34,IF(3<=12,Assumptions!$B$35,Assumptions!$B$36))*Assumptions!$D$22 -> 4500 | E56: =IF(4<=6,Assumptions!$B$34,IF(4<=12,Assumptions!$B$35,Assumptions!$B$36))*Assumptions!$D$22 -> 4500 | F56: =IF(5<=6,Assumptions!$B$34,IF(5<=12,Assumptions!$B$35,Assumptions!$B$36))*Assumptions!$D$22 -> 4500 | G56: =IF(6<=6,Assumptions!$B$34,IF(6<=12,Assumptions!$B$35,Assumptions!$B$36))*Assumptions!$D$22 -> 4500 | H56: =IF(7<=6,Assumptions!$B$34,IF(7<=12,Assumptions!$B$35,Assumptions!$B$36))*Assumptions!$D$22 -> 9000 | I56: =IF(8<=6,Assumptions!$B$34,IF(8<=12,Assumptions!$B$35,Assumptions!$B$36))*Assumptions!$D$22 -> 9000 | J56: =IF(9<=6,Assumptions!$B$34,IF(9<=12,Assumptions!$B$35,Assumptions!$B$36))*Assumptions!$D$22 -> 9000 | K56: =IF(10<=6,Assumptions!$B$34,IF(10<=12,Assumptions!$B$35,Assumptions!$B$36))*Assumptions!$D$22 -> 9000 | L56: =IF(11<=6,Assumptions!$B$34,IF(11<=12,Assumptions!$B$35,Assumptions!$B$36))*Assumptions!$D$22 -> 9000 | M56: =IF(12<=6,Assumptions!$B$34,IF(12<=12,Assumptions!$B$35,Assumptions!$B$36))*Assumptions!$D$22 -> 9000 | N56: =IF(13<=6,Assumptions!$B$34,IF(13<=12,Assumptions!$B$35,Assumptions!$B$36))*Assumptions!$D$22 -> 13500 | O56: =IF(14<=6,Assumptions!$B$34,IF(14<=12,Assumptions!$B$35,Assumptions!$B$36))*Assumptions!$D$22 -> 13500 | P56: =IF(15<=6,Assumptions!$B$34,IF(15<=12,Assumptions!$B$35,Assumptions!$B$36))*Assumptions!$D$22 -> 13500 | Q56: =IF(16<=6,Assumptions!$B$34,IF(16<=12,Assumptions!$B$35,Assumptions!$B$36))*Assumptions!$D$22 -> 13500 | R56: =IF(17<=6,Assumptions!$B$34,IF(17<=12,Assumptions!$B$35,Assumptions!$B$36))*Assumptions!$D$22 -> 13500 | S56: =IF(18<=6,Assumptions!$B$34,IF(18<=12,Assumptions!$B$35,Assumptions!$B$36))*Assumptions!$D$22 -> 13500 | T56: =IF(19<=6,Assumptions!$B$34,IF(19<=12,Assumptions!$B$35,Assumptions!$B$36))*Assumptions!$D$22 -> 13500 | U56: =IF(20<=6,Assumptions!$B$34,IF(20<=12,Assumptions!$B$35,Assumptions!$B$36))*Assumptions!$D$22 -> 13500 | V56: =IF(21<=6,Assumptions!$B$34,IF(21<=12,Assumptions!$B$35,Assumptions!$B$36))*Assumptions!$D$22 -> 13500 | W56: =IF(22<=6,Assumptions!$B$34,IF(22<=12,Assumptions!$B$35,Assumptions!$B$36))*Assumptions!$D$22 -> 13500 | X56: =IF(23<=6,Assumptions!$B$34,IF(23<=12,Assumptions!$B$35,Assumptions!$B$36))*Assumptions!$D$22 -> 13500 | Y56: =IF(24<=6,Assumptions!$B$34,IF(24<=12,Assumptions!$B$35,Assumptions!$B$36))*Assumptions!$D$22 -> 13500 | Z56: =SUM(B56:Y56) -> 243000
A57: 教学共创与试用 | B57: =IF(1<=3,Assumptions!$B$37,IF(1<=12,Assumptions!$B$38,Assumptions!$B$39))*Assumptions!$D$22 -> 0 | C57: =IF(2<=3,Assumptions!$B$37,IF(2<=12,Assumptions!$B$38,Assumptions!$B$39))*Assumptions!$D$22 -> 0 | D57: =IF(3<=3,Assumptions!$B$37,IF(3<=12,Assumptions!$B$38,Assumptions!$B$39))*Assumptions!$D$22 -> 0 | E57: =IF(4<=3,Assumptions!$B$37,IF(4<=12,Assumptions!$B$38,Assumptions!$B$39))*Assumptions!$D$22 -> 9000 | F57: =IF(5<=3,Assumptions!$B$37,IF(5<=12,Assumptions!$B$38,Assumptions!$B$39))*Assumptions!$D$22 -> 9000 | G57: =IF(6<=3,Assumptions!$B$37,IF(6<=12,Assumptions!$B$38,Assumptions!$B$39))*Assumptions!$D$22 -> 9000 | H57: =IF(7<=3,Assumptions!$B$37,IF(7<=12,Assumptions!$B$38,Assumptions!$B$39))*Assumptions!$D$22 -> 9000 | I57: =IF(8<=3,Assumptions!$B$37,IF(8<=12,Assumptions!$B$38,Assumptions!$B$39))*Assumptions!$D$22 -> 9000 | J57: =IF(9<=3,Assumptions!$B$37,IF(9<=12,Assumptions!$B$38,Assumptions!$B$39))*Assumptions!$D$22 -> 9000 | K57: =IF(10<=3,Assumptions!$B$37,IF(10<=12,Assumptions!$B$38,Assumptions!$B$39))*Assumptions!$D$22 -> 9000 | L57: =IF(11<=3,Assumptions!$B$37,IF(11<=12,Assumptions!$B$38,Assumptions!$B$39))*Assumptions!$D$22 -> 9000 | M57: =IF(12<=3,Assumptions!$B$37,IF(12<=12,Assumptions!$B$38,Assumptions!$B$39))*Assumptions!$D$22 -> 9000 | N57: =IF(13<=3,Assumptions!$B$37,IF(13<=12,Assumptions!$B$38,Assumptions!$B$39))*Assumptions!$D$22 -> 12000 | O57: =IF(14<=3,Assumptions!$B$37,IF(14<=12,Assumptions!$B$38,Assumptions!$B$39))*Assumptions!$D$22 -> 12000 | P57: =IF(15<=3,Assumptions!$B$37,IF(15<=12,Assumptions!$B$38,Assumptions!$B$39))*Assumptions!$D$22 -> 12000 | Q57: =IF(16<=3,Assumptions!$B$37,IF(16<=12,Assumptions!$B$38,Assumptions!$B$39))*Assumptions!$D$22 -> 12000 | R57: =IF(17<=3,Assumptions!$B$37,IF(17<=12,Assumptions!$B$38,Assumptions!$B$39))*Assumptions!$D$22 -> 12000 | S57: =IF(18<=3,Assumptions!$B$37,IF(18<=12,Assumptions!$B$38,Assumptions!$B$39))*Assumptions!$D$22 -> 12000 | T57: =IF(19<=3,Assumptions!$B$37,IF(19<=12,Assumptions!$B$38,Assumptions!$B$39))*Assumptions!$D$22 -> 12000 | U57: =IF(20<=3,Assumptions!$B$37,IF(20<=12,Assumptions!$B$38,Assumptions!$B$39))*Assumptions!$D$22 -> 12000 | V57: =IF(21<=3,Assumptions!$B$37,IF(21<=12,Assumptions!$B$38,Assumptions!$B$39))*Assumptions!$D$22 -> 12000 | W57: =IF(22<=3,Assumptions!$B$37,IF(22<=12,Assumptions!$B$38,Assumptions!$B$39))*Assumptions!$D$22 -> 12000 | X57: =IF(23<=3,Assumptions!$B$37,IF(23<=12,Assumptions!$B$38,Assumptions!$B$39))*Assumptions!$D$22 -> 12000 | Y57: =IF(24<=3,Assumptions!$B$37,IF(24<=12,Assumptions!$B$38,Assumptions!$B$39))*Assumptions!$D$22 -> 12000 | Z57: =SUM(B57:Y57) -> 225000
A58: 社区活动与材料 | B58: =IF(1<=3,Assumptions!$B$40,IF(1<=12,Assumptions!$B$41,Assumptions!$B$42))*Assumptions!$D$22 -> 0 | C58: =IF(2<=3,Assumptions!$B$40,IF(2<=12,Assumptions!$B$41,Assumptions!$B$42))*Assumptions!$D$22 -> 0 | D58: =IF(3<=3,Assumptions!$B$40,IF(3<=12,Assumptions!$B$41,Assumptions!$B$42))*Assumptions!$D$22 -> 0 | E58: =IF(4<=3,Assumptions!$B$40,IF(4<=12,Assumptions!$B$41,Assumptions!$B$42))*Assumptions!$D$22 -> 4500 | F58: =IF(5<=3,Assumptions!$B$40,IF(5<=12,Assumptions!$B$41,Assumptions!$B$42))*Assumptions!$D$22 -> 4500 | G58: =IF(6<=3,Assumptions!$B$40,IF(6<=12,Assumptions!$B$41,Assumptions!$B$42))*Assumptions!$D$22 -> 4500 | H58: =IF(7<=3,Assumptions!$B$40,IF(7<=12,Assumptions!$B$41,Assumptions!$B$42))*Assumptions!$D$22 -> 4500 | I58: =IF(8<=3,Assumptions!$B$40,IF(8<=12,Assumptions!$B$41,Assumptions!$B$42))*Assumptions!$D$22 -> 4500 | J58: =IF(9<=3,Assumptions!$B$40,IF(9<=12,Assumptions!$B$41,Assumptions!$B$42))*Assumptions!$D$22 -> 4500 | K58: =IF(10<=3,Assumptions!$B$40,IF(10<=12,Assumptions!$B$41,Assumptions!$B$42))*Assumptions!$D$22 -> 4500 | L58: =IF(11<=3,Assumptions!$B$40,IF(11<=12,Assumptions!$B$41,Assumptions!$B$42))*Assumptions!$D$22 -> 4500 | M58: =IF(12<=3,Assumptions!$B$40,IF(12<=12,Assumptions!$B$41,Assumptions!$B$42))*Assumptions!$D$22 -> 4500 | N58: =IF(13<=3,Assumptions!$B$40,IF(13<=12,Assumptions!$B$41,Assumptions!$B$42))*Assumptions!$D$22 -> 9000 | O58: =IF(14<=3,Assumptions!$B$40,IF(14<=12,Assumptions!$B$41,Assumptions!$B$42))*Assumptions!$D$22 -> 9000 | P58: =IF(15<=3,Assumptions!$B$40,IF(15<=12,Assumptions!$B$41,Assumptions!$B$42))*Assumptions!$D$22 -> 9000 | Q58: =IF(16<=3,Assumptions!$B$40,IF(16<=12,Assumptions!$B$41,Assumptions!$B$42))*Assumptions!$D$22 -> 9000 | R58: =IF(17<=3,Assumptions!$B$40,IF(17<=12,Assumptions!$B$41,Assumptions!$B$42))*Assumptions!$D$22 -> 9000 | S58: =IF(18<=3,Assumptions!$B$40,IF(18<=12,Assumptions!$B$41,Assumptions!$B$42))*Assumptions!$D$22 -> 9000 | T58: =IF(19<=3,Assumptions!$B$40,IF(19<=12,Assumptions!$B$41,Assumptions!$B$42))*Assumptions!$D$22 -> 9000 | U58: =IF(20<=3,Assumptions!$B$40,IF(20<=12,Assumptions!$B$41,Assumptions!$B$42))*Assumptions!$D$22 -> 9000 | V58: =IF(21<=3,Assumptions!$B$40,IF(21<=12,Assumptions!$B$41,Assumptions!$B$42))*Assumptions!$D$22 -> 9000 | W58: =IF(22<=3,Assumptions!$B$40,IF(22<=12,Assumptions!$B$41,Assumptions!$B$42))*Assumptions!$D$22 -> 9000 | X58: =IF(23<=3,Assumptions!$B$40,IF(23<=12,Assumptions!$B$41,Assumptions!$B$42))*Assumptions!$D$22 -> 9000 | Y58: =IF(24<=3,Assumptions!$B$40,IF(24<=12,Assumptions!$B$41,Assumptions!$B$42))*Assumptions!$D$22 -> 9000 | Z58: =SUM(B58:Y58) -> 148500
A59: 一般运营与合规预算 | B59: =Assumptions!$B$43*Assumptions!$D$22 -> 4500 | C59: =Assumptions!$B$43*Assumptions!$D$22 -> 4500 | D59: =Assumptions!$B$43*Assumptions!$D$22 -> 4500 | E59: =Assumptions!$B$43*Assumptions!$D$22 -> 4500 | F59: =Assumptions!$B$43*Assumptions!$D$22 -> 4500 | G59: =Assumptions!$B$43*Assumptions!$D$22 -> 4500 | H59: =Assumptions!$B$43*Assumptions!$D$22 -> 4500 | I59: =Assumptions!$B$43*Assumptions!$D$22 -> 4500 | ... Y59: =Assumptions!$B$43*Assumptions!$D$22 -> 4500 | Z59: =SUM(B59:Y59) -> 108000
A60: 专项外部交付 | B60: =SUMIF(Assumptions!$F$47:$F$50,1,Assumptions!$G$47:$G$50)*Assumptions!$D$22 -> 0 | C60: =SUMIF(Assumptions!$F$47:$F$50,2,Assumptions!$G$47:$G$50)*Assumptions!$D$22 -> 0 | D60: =SUMIF(Assumptions!$F$47:$F$50,3,Assumptions!$G$47:$G$50)*Assumptions!$D$22 -> 0 | E60: =SUMIF(Assumptions!$F$47:$F$50,4,Assumptions!$G$47:$G$50)*Assumptions!$D$22 -> 0 | F60: =SUMIF(Assumptions!$F$47:$F$50,5,Assumptions!$G$47:$G$50)*Assumptions!$D$22 -> 0 | G60: =SUMIF(Assumptions!$F$47:$F$50,6,Assumptions!$G$47:$G$50)*Assumptions!$D$22 -> 45000 | H60: =SUMIF(Assumptions!$F$47:$F$50,7,Assumptions!$G$47:$G$50)*Assumptions!$D$22 -> 0 | I60: =SUMIF(Assumptions!$F$47:$F$50,8,Assumptions!$G$47:$G$50)*Assumptions!$D$22 -> 0 | J60: =SUMIF(Assumptions!$F$47:$F$50,9,Assumptions!$G$47:$G$50)*Assumptions!$D$22 -> 0 | K60: =SUMIF(Assumptions!$F$47:$F$50,10,Assumptions!$G$47:$G$50)*Assumptions!$D$22 -> 0 | L60: =SUMIF(Assumptions!$F$47:$F$50,11,Assumptions!$G$47:$G$50)*Assumptions!$D$22 -> 0 | M60: =SUMIF(Assumptions!$F$47:$F$50,12,Assumptions!$G$47:$G$50)*Assumptions!$D$22 -> 60000 | N60: =SUMIF(Assumptions!$F$47:$F$50,13,Assumptions!$G$47:$G$50)*Assumptions!$D$22 -> 0 | O60: =SUMIF(Assumptions!$F$47:$F$50,14,Assumptions!$G$47:$G$50)*Assumptions!$D$22 -> 0 | P60: =SUMIF(Assumptions!$F$47:$F$50,15,Assumptions!$G$47:$G$50)*Assumptions!$D$22 -> 0 | Q60: =SUMIF(Assumptions!$F$47:$F$50,16,Assumptions!$G$47:$G$50)*Assumptions!$D$22 -> 0 | R60: =SUMIF(Assumptions!$F$47:$F$50,17,Assumptions!$G$47:$G$50)*Assumptions!$D$22 -> 0 | S60: =SUMIF(Assumptions!$F$47:$F$50,18,Assumptions!$G$47:$G$50)*Assumptions!$D$22 -> 60000 | T60: =SUMIF(Assumptions!$F$47:$F$50,19,Assumptions!$G$47:$G$50)*Assumptions!$D$22 -> 0 | U60: =SUMIF(Assumptions!$F$47:$F$50,20,Assumptions!$G$47:$G$50)*Assumptions!$D$22 -> 0 | V60: =SUMIF(Assumptions!$F$47:$F$50,21,Assumptions!$G$47:$G$50)*Assumptions!$D$22 -> 0 | W60: =SUMIF(Assumptions!$F$47:$F$50,22,Assumptions!$G$47:$G$50)*Assumptions!$D$22 -> 0 | X60: =SUMIF(Assumptions!$F$47:$F$50,23,Assumptions!$G$47:$G$50)*Assumptions!$D$22 -> 0 | Y60: =SUMIF(Assumptions!$F$47:$F$50,24,Assumptions!$G$47:$G$50)*Assumptions!$D$22 -> 60000 | Z60: =SUM(B60:Y60) -> 225000
A61: 条件用户算力成本 | B61: =Cohorts!B38 -> 0 | C61: =Cohorts!C38 -> 0 | D61: =Cohorts!D38 -> 0 | E61: =Cohorts!E38 -> 0 | F61: =Cohorts!F38 -> 0 | G61: =Cohorts!G38 -> 0 | H61: =Cohorts!H38 -> 0 | I61: =Cohorts!I38 -> 0 | ... Y61: =Cohorts!Y38 -> 3383803.4 | Z61: =SUM(B61:Y61) -> 15230163
A62: 实际非退还合作费（未录入） | B62: =IF(1=Assumptions!$B$10,Assumptions!$B$7,0) -> 0 | C62: =IF(2=Assumptions!$B$10,Assumptions!$B$7,0) -> 0 | D62: =IF(3=Assumptions!$B$10,Assumptions!$B$7,0) -> 0 | E62: =IF(4=Assumptions!$B$10,Assumptions!$B$7,0) -> 0 | F62: =IF(5=Assumptions!$B$10,Assumptions!$B$7,0) -> 0 | G62: =IF(6=Assumptions!$B$10,Assumptions!$B$7,0) -> 0 | H62: =IF(7=Assumptions!$B$10,Assumptions!$B$7,0) -> 0 | I62: =IF(8=Assumptions!$B$10,Assumptions!$B$7,0) -> 0 | J62: =IF(9=Assumptions!$B$10,Assumptions!$B$7,0) -> 0 | K62: =IF(10=Assumptions!$B$10,Assumptions!$B$7,0) -> 0 | L62: =IF(11=Assumptions!$B$10,Assumptions!$B$7,0) -> 0 | M62: =IF(12=Assumptions!$B$10,Assumptions!$B$7,0) -> 0 | N62: =IF(13=Assumptions!$B$10,Assumptions!$B$7,0) -> 0 | O62: =IF(14=Assumptions!$B$10,Assumptions!$B$7,0) -> 0 | P62: =IF(15=Assumptions!$B$10,Assumptions!$B$7,0) -> 0 | Q62: =IF(16=Assumptions!$B$10,Assumptions!$B$7,0) -> 0 | R62: =IF(17=Assumptions!$B$10,Assumptions!$B$7,0) -> 0 | S62: =IF(18=Assumptions!$B$10,Assumptions!$B$7,0) -> 0 | T62: =IF(19=Assumptions!$B$10,Assumptions!$B$7,0) -> 0 | U62: =IF(20=Assumptions!$B$10,Assumptions!$B$7,0) -> 0 | V62: =IF(21=Assumptions!$B$10,Assumptions!$B$7,0) -> 0 | W62: =IF(22=Assumptions!$B$10,Assumptions!$B$7,0) -> 0 | X62: =IF(23=Assumptions!$B$10,Assumptions!$B$7,0) -> 0 | Y62: =IF(24=Assumptions!$B$10,Assumptions!$B$7,0) -> 0 | Z62: =SUM(B62:Y62) -> 0
A63: 费用现金合计（不含设备） | B63: =SUM(B54:B62) -> 116557.43 | C63: =SUM(C54:C62) -> 116557.43 | D63: =SUM(D54:D62) -> 116557.43 | E63: =SUM(E54:E62) -> 130057.43 | F63: =SUM(F54:F62) -> 130057.43 | G63: =SUM(G54:G62) -> 175057.43 | H63: =SUM(H54:H62) -> 161446.79 | I63: =SUM(I54:I62) -> 161446.79 | ... Y63: =SUM(Y54:Y62) -> 3617250.2 | Z63: =SUM(B63:Y63) -> 19245050
A64: 设备购置现金 | B64: =SUMIF(Assumptions!$F$54:$F$55,1,Assumptions!$G$54:$G$55)*Assumptions!$D$22 -> 75000 | C64: =SUMIF(Assumptions!$F$54:$F$55,2,Assumptions!$G$54:$G$55)*Assumptions!$D$22 -> 0 | D64: =SUMIF(Assumptions!$F$54:$F$55,3,Assumptions!$G$54:$G$55)*Assumptions!$D$22 -> 0 | E64: =SUMIF(Assumptions!$F$54:$F$55,4,Assumptions!$G$54:$G$55)*Assumptions!$D$22 -> 0 | F64: =SUMIF(Assumptions!$F$54:$F$55,5,Assumptions!$G$54:$G$55)*Assumptions!$D$22 -> 0 | G64: =SUMIF(Assumptions!$F$54:$F$55,6,Assumptions!$G$54:$G$55)*Assumptions!$D$22 -> 0 | H64: =SUMIF(Assumptions!$F$54:$F$55,7,Assumptions!$G$54:$G$55)*Assumptions!$D$22 -> 45000 | I64: =SUMIF(Assumptions!$F$54:$F$55,8,Assumptions!$G$54:$G$55)*Assumptions!$D$22 -> 0 | J64: =SUMIF(Assumptions!$F$54:$F$55,9,Assumptions!$G$54:$G$55)*Assumptions!$D$22 -> 0 | K64: =SUMIF(Assumptions!$F$54:$F$55,10,Assumptions!$G$54:$G$55)*Assumptions!$D$22 -> 0 | L64: =SUMIF(Assumptions!$F$54:$F$55,11,Assumptions!$G$54:$G$55)*Assumptions!$D$22 -> 0 | M64: =SUMIF(Assumptions!$F$54:$F$55,12,Assumptions!$G$54:$G$55)*Assumptions!$D$22 -> 0 | N64: =SUMIF(Assumptions!$F$54:$F$55,13,Assumptions!$G$54:$G$55)*Assumptions!$D$22 -> 0 | O64: =SUMIF(Assumptions!$F$54:$F$55,14,Assumptions!$G$54:$G$55)*Assumptions!$D$22 -> 0 | P64: =SUMIF(Assumptions!$F$54:$F$55,15,Assumptions!$G$54:$G$55)*Assumptions!$D$22 -> 0 | Q64: =SUMIF(Assumptions!$F$54:$F$55,16,Assumptions!$G$54:$G$55)*Assumptions!$D$22 -> 0 | R64: =SUMIF(Assumptions!$F$54:$F$55,17,Assumptions!$G$54:$G$55)*Assumptions!$D$22 -> 0 | S64: =SUMIF(Assumptions!$F$54:$F$55,18,Assumptions!$G$54:$G$55)*Assumptions!$D$22 -> 0 | T64: =SUMIF(Assumptions!$F$54:$F$55,19,Assumptions!$G$54:$G$55)*Assumptions!$D$22 -> 0 | U64: =SUMIF(Assumptions!$F$54:$F$55,20,Assumptions!$G$54:$G$55)*Assumptions!$D$22 -> 0 | V64: =SUMIF(Assumptions!$F$54:$F$55,21,Assumptions!$G$54:$G$55)*Assumptions!$D$22 -> 0 | W64: =SUMIF(Assumptions!$F$54:$F$55,22,Assumptions!$G$54:$G$55)*Assumptions!$D$22 -> 0 | X64: =SUMIF(Assumptions!$F$54:$F$55,23,Assumptions!$G$54:$G$55)*Assumptions!$D$22 -> 0 | Y64: =SUMIF(Assumptions!$F$54:$F$55,24,Assumptions!$G$54:$G$55)*Assumptions!$D$22 -> 0 | Z64: =SUM(B64:Y64) -> 120000
A65: 当月设备折旧 | B65: =SUMPRODUCT((1-Assumptions!$F$54:$F$55+1>0)*(1-Assumptions!$F$54:$F$55+1<=Assumptions!$B$11)*Assumptions!$G$54:$G$55)*Assumptions!$D$22/Assumptions!$B$11 -> 2083.3333 | C65: =SUMPRODUCT((2-Assumptions!$F$54:$F$55+1>0)*(2-Assumptions!$F$54:$F$55+1<=Assumptions!$B$11)*Assumptions!$G$54:$G$55)*Assumptions!$D$22/Assumptions!$B$11 -> 2083.3333 | D65: =SUMPRODUCT((3-Assumptions!$F$54:$F$55+1>0)*(3-Assumptions!$F$54:$F$55+1<=Assumptions!$B$11)*Assumptions!$G$54:$G$55)*Assumptions!$D$22/Assumptions!$B$11 -> 2083.3333 | E65: =SUMPRODUCT((4-Assumptions!$F$54:$F$55+1>0)*(4-Assumptions!$F$54:$F$55+1<=Assumptions!$B$11)*Assumptions!$G$54:$G$55)*Assumptions!$D$22/Assumptions!$B$11 -> 2083.3333 | F65: =SUMPRODUCT((5-Assumptions!$F$54:$F$55+1>0)*(5-Assumptions!$F$54:$F$55+1<=Assumptions!$B$11)*Assumptions!$G$54:$G$55)*Assumptions!$D$22/Assumptions!$B$11 -> 2083.3333 | G65: =SUMPRODUCT((6-Assumptions!$F$54:$F$55+1>0)*(6-Assumptions!$F$54:$F$55+1<=Assumptions!$B$11)*Assumptions!$G$54:$G$55)*Assumptions!$D$22/Assumptions!$B$11 -> 2083.3333 | H65: =SUMPRODUCT((7-Assumptions!$F$54:$F$55+1>0)*(7-Assumptions!$F$54:$F$55+1<=Assumptions!$B$11)*Assumptions!$G$54:$G$55)*Assumptions!$D$22/Assumptions!$B$11 -> 3333.3333 | I65: =SUMPRODUCT((8-Assumptions!$F$54:$F$55+1>0)*(8-Assumptions!$F$54:$F$55+1<=Assumptions!$B$11)*Assumptions!$G$54:$G$55)*Assumptions!$D$22/Assumptions!$B$11 -> 3333.3333 | J65: =SUMPRODUCT((9-Assumptions!$F$54:$F$55+1>0)*(9-Assumptions!$F$54:$F$55+1<=Assumptions!$B$11)*Assumptions!$G$54:$G$55)*Assumptions!$D$22/Assumptions!$B$11 -> 3333.3333 | K65: =SUMPRODUCT((10-Assumptions!$F$54:$F$55+1>0)*(10-Assumptions!$F$54:$F$55+1<=Assumptions!$B$11)*Assumptions!$G$54:$G$55)*Assumptions!$D$22/Assumptions!$B$11 -> 3333.3333 | L65: =SUMPRODUCT((11-Assumptions!$F$54:$F$55+1>0)*(11-Assumptions!$F$54:$F$55+1<=Assumptions!$B$11)*Assumptions!$G$54:$G$55)*Assumptions!$D$22/Assumptions!$B$11 -> 3333.3333 | M65: =SUMPRODUCT((12-Assumptions!$F$54:$F$55+1>0)*(12-Assumptions!$F$54:$F$55+1<=Assumptions!$B$11)*Assumptions!$G$54:$G$55)*Assumptions!$D$22/Assumptions!$B$11 -> 3333.3333 | N65: =SUMPRODUCT((13-Assumptions!$F$54:$F$55+1>0)*(13-Assumptions!$F$54:$F$55+1<=Assumptions!$B$11)*Assumptions!$G$54:$G$55)*Assumptions!$D$22/Assumptions!$B$11 -> 3333.3333 | O65: =SUMPRODUCT((14-Assumptions!$F$54:$F$55+1>0)*(14-Assumptions!$F$54:$F$55+1<=Assumptions!$B$11)*Assumptions!$G$54:$G$55)*Assumptions!$D$22/Assumptions!$B$11 -> 3333.3333 | P65: =SUMPRODUCT((15-Assumptions!$F$54:$F$55+1>0)*(15-Assumptions!$F$54:$F$55+1<=Assumptions!$B$11)*Assumptions!$G$54:$G$55)*Assumptions!$D$22/Assumptions!$B$11 -> 3333.3333 | Q65: =SUMPRODUCT((16-Assumptions!$F$54:$F$55+1>0)*(16-Assumptions!$F$54:$F$55+1<=Assumptions!$B$11)*Assumptions!$G$54:$G$55)*Assumptions!$D$22/Assumptions!$B$11 -> 3333.3333 | R65: =SUMPRODUCT((17-Assumptions!$F$54:$F$55+1>0)*(17-Assumptions!$F$54:$F$55+1<=Assumptions!$B$11)*Assumptions!$G$54:$G$55)*Assumptions!$D$22/Assumptions!$B$11 -> 3333.3333 | S65: =SUMPRODUCT((18-Assumptions!$F$54:$F$55+1>0)*(18-Assumptions!$F$54:$F$55+1<=Assumptions!$B$11)*Assumptions!$G$54:$G$55)*Assumptions!$D$22/Assumptions!$B$11 -> 3333.3333 | T65: =SUMPRODUCT((19-Assumptions!$F$54:$F$55+1>0)*(19-Assumptions!$F$54:$F$55+1<=Assumptions!$B$11)*Assumptions!$G$54:$G$55)*Assumptions!$D$22/Assumptions!$B$11 -> 3333.3333 | U65: =SUMPRODUCT((20-Assumptions!$F$54:$F$55+1>0)*(20-Assumptions!$F$54:$F$55+1<=Assumptions!$B$11)*Assumptions!$G$54:$G$55)*Assumptions!$D$22/Assumptions!$B$11 -> 3333.3333 | V65: =SUMPRODUCT((21-Assumptions!$F$54:$F$55+1>0)*(21-Assumptions!$F$54:$F$55+1<=Assumptions!$B$11)*Assumptions!$G$54:$G$55)*Assumptions!$D$22/Assumptions!$B$11 -> 3333.3333 | W65: =SUMPRODUCT((22-Assumptions!$F$54:$F$55+1>0)*(22-Assumptions!$F$54:$F$55+1<=Assumptions!$B$11)*Assumptions!$G$54:$G$55)*Assumptions!$D$22/Assumptions!$B$11 -> 3333.3333 | X65: =SUMPRODUCT((23-Assumptions!$F$54:$F$55+1>0)*(23-Assumptions!$F$54:$F$55+1<=Assumptions!$B$11)*Assumptions!$G$54:$G$55)*Assumptions!$D$22/Assumptions!$B$11 -> 3333.3333 | Y65: =SUMPRODUCT((24-Assumptions!$F$54:$F$55+1>0)*(24-Assumptions!$F$54:$F$55+1<=Assumptions!$B$11)*Assumptions!$G$54:$G$55)*Assumptions!$D$22/Assumptions!$B$11 -> 3333.3333 | Z65: =SUM(B65:Y65) -> 72500
A66: 损益费用合计 | B66: =B63+B65 -> 118640.76 | C66: =C63+C65 -> 118640.76 | D66: =D63+D65 -> 118640.76 | E66: =E63+E65 -> 132140.76 | F66: =F63+F65 -> 132140.76 | G66: =G63+G65 -> 177140.76 | H66: =H63+H65 -> 164780.12 | I66: =I63+I65 -> 164780.12 | ... Y66: =Y63+Y65 -> 3620583.5 | Z66: =SUM(B66:Y66) -> 19317550
A67: 常规固定与专项支出 | B67: =SUM(B54:B60) -> 116557.43 | C67: =SUM(C54:C60) -> 116557.43 | D67: =SUM(D54:D60) -> 116557.43 | E67: =SUM(E54:E60) -> 130057.43 | F67: =SUM(F54:F60) -> 130057.43 | G67: =SUM(G54:G60) -> 175057.43 | H67: =SUM(H54:H60) -> 161446.79 | I67: =SUM(I54:I60) -> 161446.79 | ... Y67: =SUM(Y54:Y60) -> 233446.79 | Z67: =SUM(B67:Y67) -> 4014886.8
A68: 常规经常性支出 | B68: =SUM(B54:B59) -> 116557.43 | C68: =SUM(C54:C59) -> 116557.43 | D68: =SUM(D54:D59) -> 116557.43 | E68: =SUM(E54:E59) -> 130057.43 | F68: =SUM(F54:F59) -> 130057.43 | G68: =SUM(G54:G59) -> 130057.43 | H68: =SUM(H54:H59) -> 161446.79 | I68: =SUM(I54:I59) -> 161446.79 | ... Y68: =SUM(Y54:Y59) -> 173446.79 | Z68: =SUM(B68:Y68) -> 3789886.8

Sheet Revenue
A1: 精简推进
A2: 月份 | B2: =EDATE(Assumptions!$B$3,0) -> 46327 | C2: =EDATE(Assumptions!$B$3,1) -> 46357 | D2: =EDATE(Assumptions!$B$3,2) -> 46388 | E2: =EDATE(Assumptions!$B$3,3) -> 46419 | F2: =EDATE(Assumptions!$B$3,4) -> 46447 | G2: =EDATE(Assumptions!$B$3,5) -> 46478 | H2: =EDATE(Assumptions!$B$3,6) -> 46508 | I2: =EDATE(Assumptions!$B$3,7) -> 46539 | J2: =EDATE(Assumptions!$B$3,8) -> 46569 | K2: =EDATE(Assumptions!$B$3,9) -> 46600 | L2: =EDATE(Assumptions!$B$3,10) -> 46631 | M2: =EDATE(Assumptions!$B$3,11) -> 46661 | N2: =EDATE(Assumptions!$B$3,12) -> 46692 | O2: =EDATE(Assumptions!$B$3,13) -> 46722 | P2: =EDATE(Assumptions!$B$3,14) -> 46753 | Q2: =EDATE(Assumptions!$B$3,15) -> 46784 | R2: =EDATE(Assumptions!$B$3,16) -> 46813 | S2: =EDATE(Assumptions!$B$3,17) -> 46844 | T2: =EDATE(Assumptions!$B$3,18) -> 46874 | U2: =EDATE(Assumptions!$B$3,19) -> 46905 | V2: =EDATE(Assumptions!$B$3,20) -> 46935 | W2: =EDATE(Assumptions!$B$3,21) -> 46966 | X2: =EDATE(Assumptions!$B$3,22) -> 46997 | Y2: =EDATE(Assumptions!$B$3,23) -> 47027 | Z2: 24个月合计 / 期末
A3: 条件用户算力成本 | B3: =Cohorts!B10 -> 0 | C3: =Cohorts!C10 -> 0 | D3: =Cohorts!D10 -> 0 | E3: =Cohorts!E10 -> 0 | F3: =Cohorts!F10 -> 0 | G3: =Cohorts!G10 -> 0 | H3: =Cohorts!H10 -> 0 | I3: =Cohorts!I10 -> 0 | ... Y3: =Cohorts!Y10 -> 203028.2 | Z3: =SUM(B3:Y3) -> 913809.77
A4: 规划成本回收额（不是正式售价） | B4: =B3*Assumptions!$B$5 -> 0 | C4: =C3*Assumptions!$B$5 -> 0 | D4: =D3*Assumptions!$B$5 -> 0 | E4: =E3*Assumptions!$B$5 -> 0 | F4: =F3*Assumptions!$B$5 -> 0 | G4: =G3*Assumptions!$B$5 -> 0 | H4: =H3*Assumptions!$B$5 -> 0 | I4: =I3*Assumptions!$B$5 -> 0 | ... Y4: =Y3*Assumptions!$B$5 -> 0 | Z4: =SUM(B4:Y4) -> 0
A5: 实际收款规划 | B5: =IF(1>Assumptions!$B$6,INDEX($B$4:$Y$4,1,1-Assumptions!$B$6),0) -> 0 | C5: =IF(2>Assumptions!$B$6,INDEX($B$4:$Y$4,1,2-Assumptions!$B$6),0) -> 0 | D5: =IF(3>Assumptions!$B$6,INDEX($B$4:$Y$4,1,3-Assumptions!$B$6),0) -> 0 | E5: =IF(4>Assumptions!$B$6,INDEX($B$4:$Y$4,1,4-Assumptions!$B$6),0) -> 0 | F5: =IF(5>Assumptions!$B$6,INDEX($B$4:$Y$4,1,5-Assumptions!$B$6),0) -> 0 | G5: =IF(6>Assumptions!$B$6,INDEX($B$4:$Y$4,1,6-Assumptions!$B$6),0) -> 0 | H5: =IF(7>Assumptions!$B$6,INDEX($B$4:$Y$4,1,7-Assumptions!$B$6),0) -> 0 | I5: =IF(8>Assumptions!$B$6,INDEX($B$4:$Y$4,1,8-Assumptions!$B$6),0) -> 0 | J5: =IF(9>Assumptions!$B$6,INDEX($B$4:$Y$4,1,9-Assumptions!$B$6),0) -> 0 | K5: =IF(10>Assumptions!$B$6,INDEX($B$4:$Y$4,1,10-Assumptions!$B$6),0) -> 0 | L5: =IF(11>Assumptions!$B$6,INDEX($B$4:$Y$4,1,11-Assumptions!$B$6),0) -> 0 | M5: =IF(12>Assumptions!$B$6,INDEX($B$4:$Y$4,1,12-Assumptions!$B$6),0) -> 0 | N5: =IF(13>Assumptions!$B$6,INDEX($B$4:$Y$4,1,13-Assumptions!$B$6),0) -> 0 | O5: =IF(14>Assumptions!$B$6,INDEX($B$4:$Y$4,1,14-Assumptions!$B$6),0) -> 0 | P5: =IF(15>Assumptions!$B$6,INDEX($B$4:$Y$4,1,15-Assumptions!$B$6),0) -> 0 | Q5: =IF(16>Assumptions!$B$6,INDEX($B$4:$Y$4,1,16-Assumptions!$B$6),0) -> 0 | R5: =IF(17>Assumptions!$B$6,INDEX($B$4:$Y$4,1,17-Assumptions!$B$6),0) -> 0 | S5: =IF(18>Assumptions!$B$6,INDEX($B$4:$Y$4,1,18-Assumptions!$B$6),0) -> 0 | T5: =IF(19>Assumptions!$B$6,INDEX($B$4:$Y$4,1,19-Assumptions!$B$6),0) -> 0 | U5: =IF(20>Assumptions!$B$6,INDEX($B$4:$Y$4,1,20-Assumptions!$B$6),0) -> 0 | V5: =IF(21>Assumptions!$B$6,INDEX($B$4:$Y$4,1,21-Assumptions!$B$6),0) -> 0 | W5: =IF(22>Assumptions!$B$6,INDEX($B$4:$Y$4,1,22-Assumptions!$B$6),0) -> 0 | X5: =IF(23>Assumptions!$B$6,INDEX($B$4:$Y$4,1,23-Assumptions!$B$6),0) -> 0 | Y5: =IF(24>Assumptions!$B$6,INDEX($B$4:$Y$4,1,24-Assumptions!$B$6),0) -> 0 | Z5: =SUM(B5:Y5) -> 0
A6: 期末待收回金额 | B6: =SUM($B4:B4)-SUM($B5:B5) -> 0 | C6: =SUM($B4:C4)-SUM($B5:C5) -> 0 | D6: =SUM($B4:D4)-SUM($B5:D5) -> 0 | E6: =SUM($B4:E4)-SUM($B5:E5) -> 0 | F6: =SUM($B4:F4)-SUM($B5:F5) -> 0 | G6: =SUM($B4:G4)-SUM($B5:G5) -> 0 | H6: =SUM($B4:H4)-SUM($B5:H5) -> 0 | I6: =SUM($B4:I4)-SUM($B5:I5) -> 0 | ... Y6: =SUM($B4:Y4)-SUM($B5:Y5) -> 0 | Z6: =Y6 -> 0
A13: 基准建设
A14: 月份 | B14: =EDATE(Assumptions!$B$3,0) -> 46327 | C14: =EDATE(Assumptions!$B$3,1) -> 46357 | D14: =EDATE(Assumptions!$B$3,2) -> 46388 | E14: =EDATE(Assumptions!$B$3,3) -> 46419 | F14: =EDATE(Assumptions!$B$3,4) -> 46447 | G14: =EDATE(Assumptions!$B$3,5) -> 46478 | H14: =EDATE(Assumptions!$B$3,6) -> 46508 | I14: =EDATE(Assumptions!$B$3,7) -> 46539 | J14: =EDATE(Assumptions!$B$3,8) -> 46569 | K14: =EDATE(Assumptions!$B$3,9) -> 46600 | L14: =EDATE(Assumptions!$B$3,10) -> 46631 | M14: =EDATE(Assumptions!$B$3,11) -> 46661 | N14: =EDATE(Assumptions!$B$3,12) -> 46692 | O14: =EDATE(Assumptions!$B$3,13) -> 46722 | P14: =EDATE(Assumptions!$B$3,14) -> 46753 | Q14: =EDATE(Assumptions!$B$3,15) -> 46784 | R14: =EDATE(Assumptions!$B$3,16) -> 46813 | S14: =EDATE(Assumptions!$B$3,17) -> 46844 | T14: =EDATE(Assumptions!$B$3,18) -> 46874 | U14: =EDATE(Assumptions!$B$3,19) -> 46905 | V14: =EDATE(Assumptions!$B$3,20) -> 46935 | W14: =EDATE(Assumptions!$B$3,21) -> 46966 | X14: =EDATE(Assumptions!$B$3,22) -> 46997 | Y14: =EDATE(Assumptions!$B$3,23) -> 47027 | Z14: 24个月合计 / 期末
A15: 条件用户算力成本 | B15: =Cohorts!B24 -> 0 | C15: =Cohorts!C24 -> 0 | D15: =Cohorts!D24 -> 0 | E15: =Cohorts!E24 -> 0 | F15: =Cohorts!F24 -> 0 | G15: =Cohorts!G24 -> 0 | H15: =Cohorts!H24 -> 0 | I15: =Cohorts!I24 -> 0 | ... Y15: =Cohorts!Y24 -> 676760.68 | Z15: =SUM(B15:Y15) -> 3046032.6
A16: 规划成本回收额（不是正式售价） | B16: =B15*Assumptions!$B$5 -> 0 | C16: =C15*Assumptions!$B$5 -> 0 | D16: =D15*Assumptions!$B$5 -> 0 | E16: =E15*Assumptions!$B$5 -> 0 | F16: =F15*Assumptions!$B$5 -> 0 | G16: =G15*Assumptions!$B$5 -> 0 | H16: =H15*Assumptions!$B$5 -> 0 | I16: =I15*Assumptions!$B$5 -> 0 | ... Y16: =Y15*Assumptions!$B$5 -> 0 | Z16: =SUM(B16:Y16) -> 0
A17: 实际收款规划 | B17: =IF(1>Assumptions!$B$6,INDEX($B$16:$Y$16,1,1-Assumptions!$B$6),0) -> 0 | C17: =IF(2>Assumptions!$B$6,INDEX($B$16:$Y$16,1,2-Assumptions!$B$6),0) -> 0 | D17: =IF(3>Assumptions!$B$6,INDEX($B$16:$Y$16,1,3-Assumptions!$B$6),0) -> 0 | E17: =IF(4>Assumptions!$B$6,INDEX($B$16:$Y$16,1,4-Assumptions!$B$6),0) -> 0 | F17: =IF(5>Assumptions!$B$6,INDEX($B$16:$Y$16,1,5-Assumptions!$B$6),0) -> 0 | G17: =IF(6>Assumptions!$B$6,INDEX($B$16:$Y$16,1,6-Assumptions!$B$6),0) -> 0 | H17: =IF(7>Assumptions!$B$6,INDEX($B$16:$Y$16,1,7-Assumptions!$B$6),0) -> 0 | I17: =IF(8>Assumptions!$B$6,INDEX($B$16:$Y$16,1,8-Assumptions!$B$6),0) -> 0 | J17: =IF(9>Assumptions!$B$6,INDEX($B$16:$Y$16,1,9-Assumptions!$B$6),0) -> 0 | K17: =IF(10>Assumptions!$B$6,INDEX($B$16:$Y$16,1,10-Assumptions!$B$6),0) -> 0 | L17: =IF(11>Assumptions!$B$6,INDEX($B$16:$Y$16,1,11-Assumptions!$B$6),0) -> 0 | M17: =IF(12>Assumptions!$B$6,INDEX($B$16:$Y$16,1,12-Assumptions!$B$6),0) -> 0 | N17: =IF(13>Assumptions!$B$6,INDEX($B$16:$Y$16,1,13-Assumptions!$B$6),0) -> 0 | O17: =IF(14>Assumptions!$B$6,INDEX($B$16:$Y$16,1,14-Assumptions!$B$6),0) -> 0 | P17: =IF(15>Assumptions!$B$6,INDEX($B$16:$Y$16,1,15-Assumptions!$B$6),0) -> 0 | Q17: =IF(16>Assumptions!$B$6,INDEX($B$16:$Y$16,1,16-Assumptions!$B$6),0) -> 0 | R17: =IF(17>Assumptions!$B$6,INDEX($B$16:$Y$16,1,17-Assumptions!$B$6),0) -> 0 | S17: =IF(18>Assumptions!$B$6,INDEX($B$16:$Y$16,1,18-Assumptions!$B$6),0) -> 0 | T17: =IF(19>Assumptions!$B$6,INDEX($B$16:$Y$16,1,19-Assumptions!$B$6),0) -> 0 | U17: =IF(20>Assumptions!$B$6,INDEX($B$16:$Y$16,1,20-Assumptions!$B$6),0) -> 0 | V17: =IF(21>Assumptions!$B$6,INDEX($B$16:$Y$16,1,21-Assumptions!$B$6),0) -> 0 | W17: =IF(22>Assumptions!$B$6,INDEX($B$16:$Y$16,1,22-Assumptions!$B$6),0) -> 0 | X17: =IF(23>Assumptions!$B$6,INDEX($B$16:$Y$16,1,23-Assumptions!$B$6),0) -> 0 | Y17: =IF(24>Assumptions!$B$6,INDEX($B$16:$Y$16,1,24-Assumptions!$B$6),0) -> 0 | Z17: =SUM(B17:Y17) -> 0
A18: 期末待收回金额 | B18: =SUM($B16:B16)-SUM($B17:B17) -> 0 | C18: =SUM($B16:C16)-SUM($B17:C17) -> 0 | D18: =SUM($B16:D16)-SUM($B17:D17) -> 0 | E18: =SUM($B16:E16)-SUM($B17:E17) -> 0 | F18: =SUM($B16:F16)-SUM($B17:F17) -> 0 | G18: =SUM($B16:G16)-SUM($B17:G17) -> 0 | H18: =SUM($B16:H16)-SUM($B17:H17) -> 0 | I18: =SUM($B16:I16)-SUM($B17:I17) -> 0 | ... Y18: =SUM($B16:Y16)-SUM($B17:Y17) -> 0 | Z18: =Y18 -> 0
A25: 高用量压力
A26: 月份 | B26: =EDATE(Assumptions!$B$3,0) -> 46327 | C26: =EDATE(Assumptions!$B$3,1) -> 46357 | D26: =EDATE(Assumptions!$B$3,2) -> 46388 | E26: =EDATE(Assumptions!$B$3,3) -> 46419 | F26: =EDATE(Assumptions!$B$3,4) -> 46447 | G26: =EDATE(Assumptions!$B$3,5) -> 46478 | H26: =EDATE(Assumptions!$B$3,6) -> 46508 | I26: =EDATE(Assumptions!$B$3,7) -> 46539 | J26: =EDATE(Assumptions!$B$3,8) -> 46569 | K26: =EDATE(Assumptions!$B$3,9) -> 46600 | L26: =EDATE(Assumptions!$B$3,10) -> 46631 | M26: =EDATE(Assumptions!$B$3,11) -> 46661 | N26: =EDATE(Assumptions!$B$3,12) -> 46692 | O26: =EDATE(Assumptions!$B$3,13) -> 46722 | P26: =EDATE(Assumptions!$B$3,14) -> 46753 | Q26: =EDATE(Assumptions!$B$3,15) -> 46784 | R26: =EDATE(Assumptions!$B$3,16) -> 46813 | S26: =EDATE(Assumptions!$B$3,17) -> 46844 | T26: =EDATE(Assumptions!$B$3,18) -> 46874 | U26: =EDATE(Assumptions!$B$3,19) -> 46905 | V26: =EDATE(Assumptions!$B$3,20) -> 46935 | W26: =EDATE(Assumptions!$B$3,21) -> 46966 | X26: =EDATE(Assumptions!$B$3,22) -> 46997 | Y26: =EDATE(Assumptions!$B$3,23) -> 47027 | Z26: 24个月合计 / 期末
A27: 条件用户算力成本 | B27: =Cohorts!B38 -> 0 | C27: =Cohorts!C38 -> 0 | D27: =Cohorts!D38 -> 0 | E27: =Cohorts!E38 -> 0 | F27: =Cohorts!F38 -> 0 | G27: =Cohorts!G38 -> 0 | H27: =Cohorts!H38 -> 0 | I27: =Cohorts!I38 -> 0 | ... Y27: =Cohorts!Y38 -> 3383803.4 | Z27: =SUM(B27:Y27) -> 15230163
A28: 规划成本回收额（不是正式售价） | B28: =B27*Assumptions!$B$5 -> 0 | C28: =C27*Assumptions!$B$5 -> 0 | D28: =D27*Assumptions!$B$5 -> 0 | E28: =E27*Assumptions!$B$5 -> 0 | F28: =F27*Assumptions!$B$5 -> 0 | G28: =G27*Assumptions!$B$5 -> 0 | H28: =H27*Assumptions!$B$5 -> 0 | I28: =I27*Assumptions!$B$5 -> 0 | ... Y28: =Y27*Assumptions!$B$5 -> 0 | Z28: =SUM(B28:Y28) -> 0
A29: 实际收款规划 | B29: =IF(1>Assumptions!$B$6,INDEX($B$28:$Y$28,1,1-Assumptions!$B$6),0) -> 0 | C29: =IF(2>Assumptions!$B$6,INDEX($B$28:$Y$28,1,2-Assumptions!$B$6),0) -> 0 | D29: =IF(3>Assumptions!$B$6,INDEX($B$28:$Y$28,1,3-Assumptions!$B$6),0) -> 0 | E29: =IF(4>Assumptions!$B$6,INDEX($B$28:$Y$28,1,4-Assumptions!$B$6),0) -> 0 | F29: =IF(5>Assumptions!$B$6,INDEX($B$28:$Y$28,1,5-Assumptions!$B$6),0) -> 0 | G29: =IF(6>Assumptions!$B$6,INDEX($B$28:$Y$28,1,6-Assumptions!$B$6),0) -> 0 | H29: =IF(7>Assumptions!$B$6,INDEX($B$28:$Y$28,1,7-Assumptions!$B$6),0) -> 0 | I29: =IF(8>Assumptions!$B$6,INDEX($B$28:$Y$28,1,8-Assumptions!$B$6),0) -> 0 | J29: =IF(9>Assumptions!$B$6,INDEX($B$28:$Y$28,1,9-Assumptions!$B$6),0) -> 0 | K29: =IF(10>Assumptions!$B$6,INDEX($B$28:$Y$28,1,10-Assumptions!$B$6),0) -> 0 | L29: =IF(11>Assumptions!$B$6,INDEX($B$28:$Y$28,1,11-Assumptions!$B$6),0) -> 0 | M29: =IF(12>Assumptions!$B$6,INDEX($B$28:$Y$28,1,12-Assumptions!$B$6),0) -> 0 | N29: =IF(13>Assumptions!$B$6,INDEX($B$28:$Y$28,1,13-Assumptions!$B$6),0) -> 0 | O29: =IF(14>Assumptions!$B$6,INDEX($B$28:$Y$28,1,14-Assumptions!$B$6),0) -> 0 | P29: =IF(15>Assumptions!$B$6,INDEX($B$28:$Y$28,1,15-Assumptions!$B$6),0) -> 0 | Q29: =IF(16>Assumptions!$B$6,INDEX($B$28:$Y$28,1,16-Assumptions!$B$6),0) -> 0 | R29: =IF(17>Assumptions!$B$6,INDEX($B$28:$Y$28,1,17-Assumptions!$B$6),0) -> 0 | S29: =IF(18>Assumptions!$B$6,INDEX($B$28:$Y$28,1,18-Assumptions!$B$6),0) -> 0 | T29: =IF(19>Assumptions!$B$6,INDEX($B$28:$Y$28,1,19-Assumptions!$B$6),0) -> 0 | U29: =IF(20>Assumptions!$B$6,INDEX($B$28:$Y$28,1,20-Assumptions!$B$6),0) -> 0 | V29: =IF(21>Assumptions!$B$6,INDEX($B$28:$Y$28,1,21-Assumptions!$B$6),0) -> 0 | W29: =IF(22>Assumptions!$B$6,INDEX($B$28:$Y$28,1,22-Assumptions!$B$6),0) -> 0 | X29: =IF(23>Assumptions!$B$6,INDEX($B$28:$Y$28,1,23-Assumptions!$B$6),0) -> 0 | Y29: =IF(24>Assumptions!$B$6,INDEX($B$28:$Y$28,1,24-Assumptions!$B$6),0) -> 0 | Z29: =SUM(B29:Y29) -> 0
A30: 期末待收回金额 | B30: =SUM($B28:B28)-SUM($B29:B29) -> 0 | C30: =SUM($B28:C28)-SUM($B29:C29) -> 0 | D30: =SUM($B28:D28)-SUM($B29:D29) -> 0 | E30: =SUM($B28:E28)-SUM($B29:E29) -> 0 | F30: =SUM($B28:F28)-SUM($B29:F29) -> 0 | G30: =SUM($B28:G28)-SUM($B29:G29) -> 0 | H30: =SUM($B28:H28)-SUM($B29:H29) -> 0 | I30: =SUM($B28:I28)-SUM($B29:I29) -> 0 | ... Y30: =SUM($B28:Y28)-SUM($B29:Y29) -> 0 | Z30: =Y30 -> 0

Sheet Income Statement
A1: 精简推进
A2: 月份 | B2: =EDATE(Assumptions!$B$3,0) -> 46327 | C2: =EDATE(Assumptions!$B$3,1) -> 46357 | D2: =EDATE(Assumptions!$B$3,2) -> 46388 | E2: =EDATE(Assumptions!$B$3,3) -> 46419 | F2: =EDATE(Assumptions!$B$3,4) -> 46447 | G2: =EDATE(Assumptions!$B$3,5) -> 46478 | H2: =EDATE(Assumptions!$B$3,6) -> 46508 | I2: =EDATE(Assumptions!$B$3,7) -> 46539 | J2: =EDATE(Assumptions!$B$3,8) -> 46569 | K2: =EDATE(Assumptions!$B$3,9) -> 46600 | L2: =EDATE(Assumptions!$B$3,10) -> 46631 | M2: =EDATE(Assumptions!$B$3,11) -> 46661 | N2: =EDATE(Assumptions!$B$3,12) -> 46692 | O2: =EDATE(Assumptions!$B$3,13) -> 46722 | P2: =EDATE(Assumptions!$B$3,14) -> 46753 | Q2: =EDATE(Assumptions!$B$3,15) -> 46784 | R2: =EDATE(Assumptions!$B$3,16) -> 46813 | S2: =EDATE(Assumptions!$B$3,17) -> 46844 | T2: =EDATE(Assumptions!$B$3,18) -> 46874 | U2: =EDATE(Assumptions!$B$3,19) -> 46905 | V2: =EDATE(Assumptions!$B$3,20) -> 46935 | W2: =EDATE(Assumptions!$B$3,21) -> 46966 | X2: =EDATE(Assumptions!$B$3,22) -> 46997 | Y2: =EDATE(Assumptions!$B$3,23) -> 47027 | Z2: 24个月合计 / 期末
A3: 规划成本回收收入 | B3: =Revenue!B4 -> 0 | C3: =Revenue!C4 -> 0 | D3: =Revenue!D4 -> 0 | E3: =Revenue!E4 -> 0 | F3: =Revenue!F4 -> 0 | G3: =Revenue!G4 -> 0 | H3: =Revenue!H4 -> 0 | I3: =Revenue!I4 -> 0 | ... Y3: =Revenue!Y4 -> 0 | Z3: =SUM(B3:Y3) -> 0
A4: 外部用户算力成本 | B4: =Costs!B11 -> 0 | C4: =Costs!C11 -> 0 | D4: =Costs!D11 -> 0 | E4: =Costs!E11 -> 0 | F4: =Costs!F11 -> 0 | G4: =Costs!G11 -> 0 | H4: =Costs!H11 -> 0 | I4: =Costs!I11 -> 0 | ... Y4: =Costs!Y11 -> 203028.2 | Z4: =SUM(B4:Y4) -> 913809.77
A5: 算力贡献 | B5: =B3-B4 -> 0 | C5: =C3-C4 -> 0 | D5: =D3-D4 -> 0 | E5: =E3-E4 -> 0 | F5: =F3-F4 -> 0 | G5: =G3-G4 -> 0 | H5: =H3-H4 -> 0 | I5: =I3-I4 -> 0 | ... Y5: =Y3-Y4 -> -203028.2 | Z5: =SUM(B5:Y5) -> -913809.77
A6: 常规与专项运营费用 | B6: =Costs!B17 -> 39389.358 | C6: =Costs!C17 -> 39389.358 | D6: =Costs!D17 -> 39389.358 | E6: =Costs!E17 -> 46139.358 | F6: =Costs!F17 -> 46139.358 | G6: =Costs!G17 -> 68639.358 | H6: =Costs!H17 -> 65834.037 | I6: =Costs!I17 -> 65834.037 | ... Y6: =Costs!Y17 -> 101834.04 | Z6: =SUM(B6:Y6) -> 1626098.8
A7: 非退还合作费 | B7: =Costs!B12 -> 0 | C7: =Costs!C12 -> 0 | D7: =Costs!D12 -> 0 | E7: =Costs!E12 -> 0 | F7: =Costs!F12 -> 0 | G7: =Costs!G12 -> 0 | H7: =Costs!H12 -> 0 | I7: =Costs!I12 -> 0 | ... Y7: =Costs!Y12 -> 0 | Z7: =SUM(B7:Y7) -> 0
A8: 折旧 | B8: =Costs!B15 -> 1041.6667 | C8: =Costs!C15 -> 1041.6667 | D8: =Costs!D15 -> 1041.6667 | E8: =Costs!E15 -> 1041.6667 | F8: =Costs!F15 -> 1041.6667 | G8: =Costs!G15 -> 1041.6667 | H8: =Costs!H15 -> 1666.6667 | I8: =Costs!I15 -> 1666.6667 | ... Y8: =Costs!Y15 -> 1666.6667 | Z8: =SUM(B8:Y8) -> 36250
A9: 损益（零收入覆盖预算） | B9: =B5-B6-B7-B8 -> -40431.025 | C9: =C5-C6-C7-C8 -> -40431.025 | D9: =D5-D6-D7-D8 -> -40431.025 | E9: =E5-E6-E7-E8 -> -47181.025 | F9: =F5-F6-F7-F8 -> -47181.025 | G9: =G5-G6-G7-G8 -> -69681.025 | H9: =H5-H6-H7-H8 -> -67500.704 | I9: =I5-I6-I7-I8 -> -67500.704 | ... Y9: =Y5-Y6-Y7-Y8 -> -306528.91 | Z9: =SUM(B9:Y9) -> -2576158.6
A19: 基准建设
A20: 月份 | B20: =EDATE(Assumptions!$B$3,0) -> 46327 | C20: =EDATE(Assumptions!$B$3,1) -> 46357 | D20: =EDATE(Assumptions!$B$3,2) -> 46388 | E20: =EDATE(Assumptions!$B$3,3) -> 46419 | F20: =EDATE(Assumptions!$B$3,4) -> 46447 | G20: =EDATE(Assumptions!$B$3,5) -> 46478 | H20: =EDATE(Assumptions!$B$3,6) -> 46508 | I20: =EDATE(Assumptions!$B$3,7) -> 46539 | J20: =EDATE(Assumptions!$B$3,8) -> 46569 | K20: =EDATE(Assumptions!$B$3,9) -> 46600 | L20: =EDATE(Assumptions!$B$3,10) -> 46631 | M20: =EDATE(Assumptions!$B$3,11) -> 46661 | N20: =EDATE(Assumptions!$B$3,12) -> 46692 | O20: =EDATE(Assumptions!$B$3,13) -> 46722 | P20: =EDATE(Assumptions!$B$3,14) -> 46753 | Q20: =EDATE(Assumptions!$B$3,15) -> 46784 | R20: =EDATE(Assumptions!$B$3,16) -> 46813 | S20: =EDATE(Assumptions!$B$3,17) -> 46844 | T20: =EDATE(Assumptions!$B$3,18) -> 46874 | U20: =EDATE(Assumptions!$B$3,19) -> 46905 | V20: =EDATE(Assumptions!$B$3,20) -> 46935 | W20: =EDATE(Assumptions!$B$3,21) -> 46966 | X20: =EDATE(Assumptions!$B$3,22) -> 46997 | Y20: =EDATE(Assumptions!$B$3,23) -> 47027 | Z20: 24个月合计 / 期末
A21: 规划成本回收收入 | B21: =Revenue!B16 -> 0 | C21: =Revenue!C16 -> 0 | D21: =Revenue!D16 -> 0 | E21: =Revenue!E16 -> 0 | F21: =Revenue!F16 -> 0 | G21: =Revenue!G16 -> 0 | H21: =Revenue!H16 -> 0 | I21: =Revenue!I16 -> 0 | ... Y21: =Revenue!Y16 -> 0 | Z21: =SUM(B21:Y21) -> 0
A22: 外部用户算力成本 | B22: =Costs!B36 -> 0 | C22: =Costs!C36 -> 0 | D22: =Costs!D36 -> 0 | E22: =Costs!E36 -> 0 | F22: =Costs!F36 -> 0 | G22: =Costs!G36 -> 0 | H22: =Costs!H36 -> 0 | I22: =Costs!I36 -> 0 | ... Y22: =Costs!Y36 -> 676760.68 | Z22: =SUM(B22:Y22) -> 3046032.6
A23: 算力贡献 | B23: =B21-B22 -> 0 | C23: =C21-C22 -> 0 | D23: =D21-D22 -> 0 | E23: =E21-E22 -> 0 | F23: =F21-F22 -> 0 | G23: =G21-G22 -> 0 | H23: =H21-H22 -> 0 | I23: =I21-I22 -> 0 | ... Y23: =Y21-Y22 -> -676760.68 | Z23: =SUM(B23:Y23) -> -3046032.6
A24: 常规与专项运营费用 | B24: =Costs!B42 -> 71778.716 | C24: =Costs!C42 -> 71778.716 | D24: =Costs!D42 -> 71778.716 | E24: =Costs!E42 -> 80778.716 | F24: =Costs!F42 -> 80778.716 | G24: =Costs!G42 -> 110778.72 | H24: =Costs!H42 -> 105704.95 | I24: =Costs!I42 -> 105704.95 | ... Y24: =Costs!Y42 -> 153704.95 | Z24: =SUM(B24:Y24) -> 2606361.5
A25: 非退还合作费 | B25: =Costs!B37 -> 0 | C25: =Costs!C37 -> 0 | D25: =Costs!D37 -> 0 | E25: =Costs!E37 -> 0 | F25: =Costs!F37 -> 0 | G25: =Costs!G37 -> 0 | H25: =Costs!H37 -> 0 | I25: =Costs!I37 -> 0 | ... Y25: =Costs!Y37 -> 0 | Z25: =SUM(B25:Y25) -> 0
A26: 折旧 | B26: =Costs!B40 -> 1388.8889 | C26: =Costs!C40 -> 1388.8889 | D26: =Costs!D40 -> 1388.8889 | E26: =Costs!E40 -> 1388.8889 | F26: =Costs!F40 -> 1388.8889 | G26: =Costs!G40 -> 1388.8889 | H26: =Costs!H40 -> 2222.2222 | I26: =Costs!I40 -> 2222.2222 | ... Y26: =Costs!Y40 -> 2222.2222 | Z26: =SUM(B26:Y26) -> 48333.333
A27: 损益（零收入覆盖预算） | B27: =B23-B24-B25-B26 -> -73167.605 | C27: =C23-C24-C25-C26 -> -73167.605 | D27: =D23-D24-D25-D26 -> -73167.605 | E27: =E23-E24-E25-E26 -> -82167.605 | F27: =F23-F24-F25-F26 -> -82167.605 | G27: =G23-G24-G25-G26 -> -112167.6 | H27: =H23-H24-H25-H26 -> -107927.18 | I27: =I23-I24-I25-I26 -> -107927.18 | ... Y27: =Y23-Y24-Y25-Y26 -> -832687.86 | Z27: =SUM(B27:Y27) -> -5700727.4
A37: 高用量压力
A38: 月份 | B38: =EDATE(Assumptions!$B$3,0) -> 46327 | C38: =EDATE(Assumptions!$B$3,1) -> 46357 | D38: =EDATE(Assumptions!$B$3,2) -> 46388 | E38: =EDATE(Assumptions!$B$3,3) -> 46419 | F38: =EDATE(Assumptions!$B$3,4) -> 46447 | G38: =EDATE(Assumptions!$B$3,5) -> 46478 | H38: =EDATE(Assumptions!$B$3,6) -> 46508 | I38: =EDATE(Assumptions!$B$3,7) -> 46539 | J38: =EDATE(Assumptions!$B$3,8) -> 46569 | K38: =EDATE(Assumptions!$B$3,9) -> 46600 | L38: =EDATE(Assumptions!$B$3,10) -> 46631 | M38: =EDATE(Assumptions!$B$3,11) -> 46661 | N38: =EDATE(Assumptions!$B$3,12) -> 46692 | O38: =EDATE(Assumptions!$B$3,13) -> 46722 | P38: =EDATE(Assumptions!$B$3,14) -> 46753 | Q38: =EDATE(Assumptions!$B$3,15) -> 46784 | R38: =EDATE(Assumptions!$B$3,16) -> 46813 | S38: =EDATE(Assumptions!$B$3,17) -> 46844 | T38: =EDATE(Assumptions!$B$3,18) -> 46874 | U38: =EDATE(Assumptions!$B$3,19) -> 46905 | V38: =EDATE(Assumptions!$B$3,20) -> 46935 | W38: =EDATE(Assumptions!$B$3,21) -> 46966 | X38: =EDATE(Assumptions!$B$3,22) -> 46997 | Y38: =EDATE(Assumptions!$B$3,23) -> 47027 | Z38: 24个月合计 / 期末
A39: 规划成本回收收入 | B39: =Revenue!B28 -> 0 | C39: =Revenue!C28 -> 0 | D39: =Revenue!D28 -> 0 | E39: =Revenue!E28 -> 0 | F39: =Revenue!F28 -> 0 | G39: =Revenue!G28 -> 0 | H39: =Revenue!H28 -> 0 | I39: =Revenue!I28 -> 0 | ... Y39: =Revenue!Y28 -> 0 | Z39: =SUM(B39:Y39) -> 0
A40: 外部用户算力成本 | B40: =Costs!B61 -> 0 | C40: =Costs!C61 -> 0 | D40: =Costs!D61 -> 0 | E40: =Costs!E61 -> 0 | F40: =Costs!F61 -> 0 | G40: =Costs!G61 -> 0 | H40: =Costs!H61 -> 0 | I40: =Costs!I61 -> 0 | ... Y40: =Costs!Y61 -> 3383803.4 | Z40: =SUM(B40:Y40) -> 15230163
A41: 算力贡献 | B41: =B39-B40 -> 0 | C41: =C39-C40 -> 0 | D41: =D39-D40 -> 0 | E41: =E39-E40 -> 0 | F41: =F39-F40 -> 0 | G41: =G39-G40 -> 0 | H41: =H39-H40 -> 0 | I41: =I39-I40 -> 0 | ... Y41: =Y39-Y40 -> -3383803.4 | Z41: =SUM(B41:Y41) -> -15230163
A42: 常规与专项运营费用 | B42: =Costs!B67 -> 116557.43 | C42: =Costs!C67 -> 116557.43 | D42: =Costs!D67 -> 116557.43 | E42: =Costs!E67 -> 130057.43 | F42: =Costs!F67 -> 130057.43 | G42: =Costs!G67 -> 175057.43 | H42: =Costs!H67 -> 161446.79 | I42: =Costs!I67 -> 161446.79 | ... Y42: =Costs!Y67 -> 233446.79 | Z42: =SUM(B42:Y42) -> 4014886.8
A43: 非退还合作费 | B43: =Costs!B62 -> 0 | C43: =Costs!C62 -> 0 | D43: =Costs!D62 -> 0 | E43: =Costs!E62 -> 0 | F43: =Costs!F62 -> 0 | G43: =Costs!G62 -> 0 | H43: =Costs!H62 -> 0 | I43: =Costs!I62 -> 0 | ... Y43: =Costs!Y62 -> 0 | Z43: =SUM(B43:Y43) -> 0
A44: 折旧 | B44: =Costs!B65 -> 2083.3333 | C44: =Costs!C65 -> 2083.3333 | D44: =Costs!D65 -> 2083.3333 | E44: =Costs!E65 -> 2083.3333 | F44: =Costs!F65 -> 2083.3333 | G44: =Costs!G65 -> 2083.3333 | H44: =Costs!H65 -> 3333.3333 | I44: =Costs!I65 -> 3333.3333 | ... Y44: =Costs!Y65 -> 3333.3333 | Z44: =SUM(B44:Y44) -> 72500
A45: 损益（零收入覆盖预算） | B45: =B41-B42-B43-B44 -> -118640.76 | C45: =C41-C42-C43-C44 -> -118640.76 | D45: =D41-D42-D43-D44 -> -118640.76 | E45: =E41-E42-E43-E44 -> -132140.76 | F45: =F41-F42-F43-F44 -> -132140.76 | G45: =G41-G42-G43-G44 -> -177140.76 | H45: =H41-H42-H43-H44 -> -164780.12 | I45: =I41-I42-I43-I44 -> -164780.12 | ... Y45: =Y41-Y42-Y43-Y44 -> -3620583.5 | Z45: =SUM(B45:Y45) -> -19317550

Sheet Balance Sheet
A1: 精简推进
A2: 月份 | B2: =EDATE(Assumptions!$B$3,0) -> 46327 | C2: =EDATE(Assumptions!$B$3,1) -> 46357 | D2: =EDATE(Assumptions!$B$3,2) -> 46388 | E2: =EDATE(Assumptions!$B$3,3) -> 46419 | F2: =EDATE(Assumptions!$B$3,4) -> 46447 | G2: =EDATE(Assumptions!$B$3,5) -> 46478 | H2: =EDATE(Assumptions!$B$3,6) -> 46508 | I2: =EDATE(Assumptions!$B$3,7) -> 46539 | J2: =EDATE(Assumptions!$B$3,8) -> 46569 | K2: =EDATE(Assumptions!$B$3,9) -> 46600 | L2: =EDATE(Assumptions!$B$3,10) -> 46631 | M2: =EDATE(Assumptions!$B$3,11) -> 46661 | N2: =EDATE(Assumptions!$B$3,12) -> 46692 | O2: =EDATE(Assumptions!$B$3,13) -> 46722 | P2: =EDATE(Assumptions!$B$3,14) -> 46753 | Q2: =EDATE(Assumptions!$B$3,15) -> 46784 | R2: =EDATE(Assumptions!$B$3,16) -> 46813 | S2: =EDATE(Assumptions!$B$3,17) -> 46844 | T2: =EDATE(Assumptions!$B$3,18) -> 46874 | U2: =EDATE(Assumptions!$B$3,19) -> 46905 | V2: =EDATE(Assumptions!$B$3,20) -> 46935 | W2: =EDATE(Assumptions!$B$3,21) -> 46966 | X2: =EDATE(Assumptions!$B$3,22) -> 46997 | Y2: =EDATE(Assumptions!$B$3,23) -> 47027 | Z2: 24个月合计 / 期末
A3: 现金（规划资金足额补入） | B3: ='Cash Flow'!B20 -> 3923110.6 | C3: ='Cash Flow'!C20 -> 3883721.3 | D3: ='Cash Flow'!D20 -> 3844331.9 | E3: ='Cash Flow'!E20 -> 3798192.6 | F3: ='Cash Flow'!F20 -> 3752053.2 | G3: ='Cash Flow'!G20 -> 3683413.9 | H3: ='Cash Flow'!H20 -> 3595079.8 | I3: ='Cash Flow'!I20 -> 3529245.8 | ... Y3: ='Cash Flow'!Y20 -> 1400091.4 | Z3: =Y3 -> 1400091.4
A4: 待收回金额 | B4: ='Cash Flow'!B23 -> 0 | C4: ='Cash Flow'!C23 -> 0 | D4: ='Cash Flow'!D23 -> 0 | E4: ='Cash Flow'!E23 -> 0 | F4: ='Cash Flow'!F23 -> 0 | G4: ='Cash Flow'!G23 -> 0 | H4: ='Cash Flow'!H23 -> 0 | I4: ='Cash Flow'!I23 -> 0 | ... Y4: ='Cash Flow'!Y23 -> 0 | Z4: =Y4 -> 0
A5: 厂商预付额度资产 | B5: ='Cash Flow'!B22 -> 0 | C5: ='Cash Flow'!C22 -> 0 | D5: ='Cash Flow'!D22 -> 0 | E5: ='Cash Flow'!E22 -> 0 | F5: ='Cash Flow'!F22 -> 0 | G5: ='Cash Flow'!G22 -> 0 | H5: ='Cash Flow'!H22 -> 0 | I5: ='Cash Flow'!I22 -> 0 | ... Y5: ='Cash Flow'!Y22 -> 0 | Z5: =Y5 -> 0
A6: 保证金资产 | B6: ='Cash Flow'!B21 -> 0 | C6: ='Cash Flow'!C21 -> 0 | D6: ='Cash Flow'!D21 -> 0 | E6: ='Cash Flow'!E21 -> 0 | F6: ='Cash Flow'!F21 -> 0 | G6: ='Cash Flow'!G21 -> 0 | H6: ='Cash Flow'!H21 -> 0 | I6: ='Cash Flow'!I21 -> 0 | ... Y6: ='Cash Flow'!Y21 -> 0 | Z6: =Y6 -> 0
A7: 设备净值 | B7: ='Cash Flow'!B24 -> 36458.333 | C7: ='Cash Flow'!C24 -> 35416.667 | D7: ='Cash Flow'!D24 -> 34375 | E7: ='Cash Flow'!E24 -> 33333.333 | F7: ='Cash Flow'!F24 -> 32291.667 | G7: ='Cash Flow'!G24 -> 31250 | H7: ='Cash Flow'!H24 -> 52083.333 | I7: ='Cash Flow'!I24 -> 50416.667 | ... Y7: ='Cash Flow'!Y24 -> 23750 | Z7: =Y7 -> 23750
A8: 资产合计 | B8: =SUM(B3:B7) -> 3959569 | C8: =SUM(C3:C7) -> 3919138 | D8: =SUM(D3:D7) -> 3878706.9 | E8: =SUM(E3:E7) -> 3831525.9 | F8: =SUM(F3:F7) -> 3784344.9 | G8: =SUM(G3:G7) -> 3714663.9 | H8: =SUM(H3:H7) -> 3647163.1 | I8: =SUM(I3:I7) -> 3579662.4 | ... Y8: =SUM(Y3:Y7) -> 1423841.4 | Z8: =Y8 -> 1423841.4
A9: 计划投入资本（非融资承诺） | B9: =Assumptions!$B$4+Summary!B$19 -> 4000000 | C9: =Assumptions!$B$4+Summary!B$19 -> 4000000 | D9: =Assumptions!$B$4+Summary!B$19 -> 4000000 | E9: =Assumptions!$B$4+Summary!B$19 -> 4000000 | F9: =Assumptions!$B$4+Summary!B$19 -> 4000000 | G9: =Assumptions!$B$4+Summary!B$19 -> 4000000 | H9: =Assumptions!$B$4+Summary!B$19 -> 4000000 | I9: =Assumptions!$B$4+Summary!B$19 -> 4000000 | J9: =Assumptions!$B$4+Summary!B$19 -> 4000000 | K9: =Assumptions!$B$4+Summary!B$19 -> 4000000 | L9: =Assumptions!$B$4+Summary!B$19 -> 4000000 | M9: =Assumptions!$B$4+Summary!B$19 -> 4000000 | N9: =Assumptions!$B$4+Summary!B$19 -> 4000000 | O9: =Assumptions!$B$4+Summary!B$19 -> 4000000 | P9: =Assumptions!$B$4+Summary!B$19 -> 4000000 | Q9: =Assumptions!$B$4+Summary!B$19 -> 4000000 | R9: =Assumptions!$B$4+Summary!B$19 -> 4000000 | S9: =Assumptions!$B$4+Summary!B$19 -> 4000000 | T9: =Assumptions!$B$4+Summary!B$19 -> 4000000 | U9: =Assumptions!$B$4+Summary!B$19 -> 4000000 | V9: =Assumptions!$B$4+Summary!B$19 -> 4000000 | W9: =Assumptions!$B$4+Summary!B$19 -> 4000000 | X9: =Assumptions!$B$4+Summary!B$19 -> 4000000 | Y9: =Assumptions!$B$4+Summary!B$19 -> 4000000 | Z9: =Y9 -> 4000000
A10: 累计规划损益 | B10: =SUM('Income Statement'!B9:'Income Statement'!B9) -> -40431.025 | C10: =SUM('Income Statement'!B9:'Income Statement'!C9) -> -80862.049 | D10: =SUM('Income Statement'!B9:'Income Statement'!D9) -> -121293.07 | E10: =SUM('Income Statement'!B9:'Income Statement'!E9) -> -168474.1 | F10: =SUM('Income Statement'!B9:'Income Statement'!F9) -> -215655.12 | G10: =SUM('Income Statement'!B9:'Income Statement'!G9) -> -285336.15 | H10: =SUM('Income Statement'!B9:'Income Statement'!H9) -> -352836.85 | I10: =SUM('Income Statement'!B9:'Income Statement'!I9) -> -420337.55 | J10: =SUM('Income Statement'!B9:'Income Statement'!J9) -> -487838.26 | K10: =SUM('Income Statement'!B9:'Income Statement'!K9) -> -555338.96 | L10: =SUM('Income Statement'!B9:'Income Statement'!L9) -> -622839.66 | M10: =SUM('Income Statement'!B9:'Income Statement'!M9) -> -720340.37 | N10: =SUM('Income Statement'!B9:'Income Statement'!N9) -> -793841.07 | O10: =SUM('Income Statement'!B9:'Income Statement'!O9) -> -867341.78 | P10: =SUM('Income Statement'!B9:'Income Statement'!P9) -> -940842.48 | Q10: =SUM('Income Statement'!B9:'Income Statement'!Q9) -> -1014343.2 | R10: =SUM('Income Statement'!B9:'Income Statement'!R9) -> -1087843.9 | S10: =SUM('Income Statement'!B9:'Income Statement'!S9) -> -1191344.6 | T10: =SUM('Income Statement'!B9:'Income Statement'!T9) -> -1366420.3 | U10: =SUM('Income Statement'!B9:'Income Statement'!U9) -> -1541496.1 | V10: =SUM('Income Statement'!B9:'Income Statement'!V9) -> -1716571.9 | W10: =SUM('Income Statement'!B9:'Income Statement'!W9) -> -1993100.8 | X10: =SUM('Income Statement'!B9:'Income Statement'!X9) -> -2269629.7 | Y10: =SUM('Income Statement'!B9:'Income Statement'!Y9) -> -2576158.6 | Z10: =Y10 -> -2576158.6
A11: 资产负债勾稽 | B11: =B8-B9-B10 -> 0 | C11: =C8-C9-C10 -> -5.0931703e-10 | D11: =D8-D9-D10 -> -5.2386895e-10 | E11: =E8-E9-E10 -> -5.5297278e-10 | F11: =F8-F9-F10 -> -1.0477379e-09 | G11: =G8-G9-G10 -> -1.0477379e-09 | H11: =H8-H9-H10 -> -6.9849193e-10 | I11: =I8-I9-I10 -> -8.1490725e-10 | ... Y11: =Y8-Y9-Y10 -> 0 | Z11: =Y11 -> 0
A19: 基准建设
A20: 月份 | B20: =EDATE(Assumptions!$B$3,0) -> 46327 | C20: =EDATE(Assumptions!$B$3,1) -> 46357 | D20: =EDATE(Assumptions!$B$3,2) -> 46388 | E20: =EDATE(Assumptions!$B$3,3) -> 46419 | F20: =EDATE(Assumptions!$B$3,4) -> 46447 | G20: =EDATE(Assumptions!$B$3,5) -> 46478 | H20: =EDATE(Assumptions!$B$3,6) -> 46508 | I20: =EDATE(Assumptions!$B$3,7) -> 46539 | J20: =EDATE(Assumptions!$B$3,8) -> 46569 | K20: =EDATE(Assumptions!$B$3,9) -> 46600 | L20: =EDATE(Assumptions!$B$3,10) -> 46631 | M20: =EDATE(Assumptions!$B$3,11) -> 46661 | N20: =EDATE(Assumptions!$B$3,12) -> 46692 | O20: =EDATE(Assumptions!$B$3,13) -> 46722 | P20: =EDATE(Assumptions!$B$3,14) -> 46753 | Q20: =EDATE(Assumptions!$B$3,15) -> 46784 | R20: =EDATE(Assumptions!$B$3,16) -> 46813 | S20: =EDATE(Assumptions!$B$3,17) -> 46844 | T20: =EDATE(Assumptions!$B$3,18) -> 46874 | U20: =EDATE(Assumptions!$B$3,19) -> 46905 | V20: =EDATE(Assumptions!$B$3,20) -> 46935 | W20: =EDATE(Assumptions!$B$3,21) -> 46966 | X20: =EDATE(Assumptions!$B$3,22) -> 46997 | Y20: =EDATE(Assumptions!$B$3,23) -> 47027 | Z20: 24个月合计 / 期末
A21: 现金（规划资金足额补入） | B21: ='Cash Flow'!B53 -> 8878221.3 | C21: ='Cash Flow'!C53 -> 8806442.6 | D21: ='Cash Flow'!D53 -> 8734663.9 | E21: ='Cash Flow'!E53 -> 8653885.1 | F21: ='Cash Flow'!F53 -> 8573106.4 | G21: ='Cash Flow'!G53 -> 8462327.7 | H21: ='Cash Flow'!H53 -> 8326622.8 | I21: ='Cash Flow'!I53 -> 8220917.8 | ... Y21: ='Cash Flow'!Y53 -> 3267606 | Z21: =Y21 -> 3267606
A22: 待收回金额 | B22: ='Cash Flow'!B56 -> 0 | C22: ='Cash Flow'!C56 -> 0 | D22: ='Cash Flow'!D56 -> 0 | E22: ='Cash Flow'!E56 -> 0 | F22: ='Cash Flow'!F56 -> 0 | G22: ='Cash Flow'!G56 -> 0 | H22: ='Cash Flow'!H56 -> 0 | I22: ='Cash Flow'!I56 -> 0 | ... Y22: ='Cash Flow'!Y56 -> 0 | Z22: =Y22 -> 0
A23: 厂商预付额度资产 | B23: ='Cash Flow'!B55 -> 0 | C23: ='Cash Flow'!C55 -> 0 | D23: ='Cash Flow'!D55 -> 0 | E23: ='Cash Flow'!E55 -> 0 | F23: ='Cash Flow'!F55 -> 0 | G23: ='Cash Flow'!G55 -> 0 | H23: ='Cash Flow'!H55 -> 0 | I23: ='Cash Flow'!I55 -> 0 | ... Y23: ='Cash Flow'!Y55 -> 0 | Z23: =Y23 -> 0
A24: 保证金资产 | B24: ='Cash Flow'!B54 -> 0 | C24: ='Cash Flow'!C54 -> 0 | D24: ='Cash Flow'!D54 -> 0 | E24: ='Cash Flow'!E54 -> 0 | F24: ='Cash Flow'!F54 -> 0 | G24: ='Cash Flow'!G54 -> 0 | H24: ='Cash Flow'!H54 -> 0 | I24: ='Cash Flow'!I54 -> 0 | ... Y24: ='Cash Flow'!Y54 -> 0 | Z24: =Y24 -> 0
A25: 设备净值 | B25: ='Cash Flow'!B57 -> 48611.111 | C25: ='Cash Flow'!C57 -> 47222.222 | D25: ='Cash Flow'!D57 -> 45833.333 | E25: ='Cash Flow'!E57 -> 44444.444 | F25: ='Cash Flow'!F57 -> 43055.556 | G25: ='Cash Flow'!G57 -> 41666.667 | H25: ='Cash Flow'!H57 -> 69444.444 | I25: ='Cash Flow'!I57 -> 67222.222 | ... Y25: ='Cash Flow'!Y57 -> 31666.667 | Z25: =Y25 -> 31666.667
A26: 资产合计 | B26: =SUM(B21:B25) -> 8926832.4 | C26: =SUM(C21:C25) -> 8853664.8 | D26: =SUM(D21:D25) -> 8780497.2 | E26: =SUM(E21:E25) -> 8698329.6 | F26: =SUM(F21:F25) -> 8616162 | G26: =SUM(G21:G25) -> 8503994.4 | H26: =SUM(H21:H25) -> 8396067.2 | I26: =SUM(I21:I25) -> 8288140 | ... Y26: =SUM(Y21:Y25) -> 3299272.6 | Z26: =Y26 -> 3299272.6
A27: 计划投入资本（非融资承诺） | B27: =Assumptions!$B$4+Summary!C$19 -> 9000000 | C27: =Assumptions!$B$4+Summary!C$19 -> 9000000 | D27: =Assumptions!$B$4+Summary!C$19 -> 9000000 | E27: =Assumptions!$B$4+Summary!C$19 -> 9000000 | F27: =Assumptions!$B$4+Summary!C$19 -> 9000000 | G27: =Assumptions!$B$4+Summary!C$19 -> 9000000 | H27: =Assumptions!$B$4+Summary!C$19 -> 9000000 | I27: =Assumptions!$B$4+Summary!C$19 -> 9000000 | J27: =Assumptions!$B$4+Summary!C$19 -> 9000000 | K27: =Assumptions!$B$4+Summary!C$19 -> 9000000 | L27: =Assumptions!$B$4+Summary!C$19 -> 9000000 | M27: =Assumptions!$B$4+Summary!C$19 -> 9000000 | N27: =Assumptions!$B$4+Summary!C$19 -> 9000000 | O27: =Assumptions!$B$4+Summary!C$19 -> 9000000 | P27: =Assumptions!$B$4+Summary!C$19 -> 9000000 | Q27: =Assumptions!$B$4+Summary!C$19 -> 9000000 | R27: =Assumptions!$B$4+Summary!C$19 -> 9000000 | S27: =Assumptions!$B$4+Summary!C$19 -> 9000000 | T27: =Assumptions!$B$4+Summary!C$19 -> 9000000 | U27: =Assumptions!$B$4+Summary!C$19 -> 9000000 | V27: =Assumptions!$B$4+Summary!C$19 -> 9000000 | W27: =Assumptions!$B$4+Summary!C$19 -> 9000000 | X27: =Assumptions!$B$4+Summary!C$19 -> 9000000 | Y27: =Assumptions!$B$4+Summary!C$19 -> 9000000 | Z27: =Y27 -> 9000000
A28: 累计规划损益 | B28: =SUM('Income Statement'!B27:'Income Statement'!B27) -> -73167.605 | C28: =SUM('Income Statement'!B27:'Income Statement'!C27) -> -146335.21 | D28: =SUM('Income Statement'!B27:'Income Statement'!D27) -> -219502.81 | E28: =SUM('Income Statement'!B27:'Income Statement'!E27) -> -301670.42 | F28: =SUM('Income Statement'!B27:'Income Statement'!F27) -> -383838.02 | G28: =SUM('Income Statement'!B27:'Income Statement'!G27) -> -496005.63 | H28: =SUM('Income Statement'!B27:'Income Statement'!H27) -> -603932.8 | I28: =SUM('Income Statement'!B27:'Income Statement'!I27) -> -711859.98 | J28: =SUM('Income Statement'!B27:'Income Statement'!J27) -> -819787.16 | K28: =SUM('Income Statement'!B27:'Income Statement'!K27) -> -927714.33 | L28: =SUM('Income Statement'!B27:'Income Statement'!L27) -> -1035641.5 | M28: =SUM('Income Statement'!B27:'Income Statement'!M27) -> -1183568.7 | N28: =SUM('Income Statement'!B27:'Income Statement'!N27) -> -1299495.9 | O28: =SUM('Income Statement'!B27:'Income Statement'!O27) -> -1415423 | P28: =SUM('Income Statement'!B27:'Income Statement'!P27) -> -1531350.2 | Q28: =SUM('Income Statement'!B27:'Income Statement'!Q27) -> -1647277.4 | R28: =SUM('Income Statement'!B27:'Income Statement'!R27) -> -1763204.6 | S28: =SUM('Income Statement'!B27:'Income Statement'!S27) -> -1919131.7 | T28: =SUM('Income Statement'!B27:'Income Statement'!T27) -> -2373642.4 | U28: =SUM('Income Statement'!B27:'Income Statement'!U27) -> -2828153.1 | V28: =SUM('Income Statement'!B27:'Income Statement'!V27) -> -3282663.8 | W28: =SUM('Income Statement'!B27:'Income Statement'!W27) -> -4075351.7 | X28: =SUM('Income Statement'!B27:'Income Statement'!X27) -> -4868039.5 | Y28: =SUM('Income Statement'!B27:'Income Statement'!Y27) -> -5700727.4 | Z28: =Y28 -> -5700727.4
A29: 资产负债勾稽 | B29: =B26-B27-B28 -> 4.802132e-10 | C29: =C26-C27-C28 -> -9.0221874e-10 | D29: =D26-D27-D28 -> -4.0745363e-10 | E29: =E26-E27-E28 -> -1.8044375e-09 | F29: =F26-F27-F28 -> -1.3387762e-09 | G29: =G26-G27-G28 -> -2.7357601e-09 | H29: =H26-H27-H28 -> -1.7462298e-09 | I29: =I26-I27-I28 -> -2.6775524e-09 | ... Y29: =Y26-Y27-Y28 -> 0 | Z29: =Y29 -> 0
A37: 高用量压力
A38: 月份 | B38: =EDATE(Assumptions!$B$3,0) -> 46327 | C38: =EDATE(Assumptions!$B$3,1) -> 46357 | D38: =EDATE(Assumptions!$B$3,2) -> 46388 | E38: =EDATE(Assumptions!$B$3,3) -> 46419 | F38: =EDATE(Assumptions!$B$3,4) -> 46447 | G38: =EDATE(Assumptions!$B$3,5) -> 46478 | H38: =EDATE(Assumptions!$B$3,6) -> 46508 | I38: =EDATE(Assumptions!$B$3,7) -> 46539 | J38: =EDATE(Assumptions!$B$3,8) -> 46569 | K38: =EDATE(Assumptions!$B$3,9) -> 46600 | L38: =EDATE(Assumptions!$B$3,10) -> 46631 | M38: =EDATE(Assumptions!$B$3,11) -> 46661 | N38: =EDATE(Assumptions!$B$3,12) -> 46692 | O38: =EDATE(Assumptions!$B$3,13) -> 46722 | P38: =EDATE(Assumptions!$B$3,14) -> 46753 | Q38: =EDATE(Assumptions!$B$3,15) -> 46784 | R38: =EDATE(Assumptions!$B$3,16) -> 46813 | S38: =EDATE(Assumptions!$B$3,17) -> 46844 | T38: =EDATE(Assumptions!$B$3,18) -> 46874 | U38: =EDATE(Assumptions!$B$3,19) -> 46905 | V38: =EDATE(Assumptions!$B$3,20) -> 46935 | W38: =EDATE(Assumptions!$B$3,21) -> 46966 | X38: =EDATE(Assumptions!$B$3,22) -> 46997 | Y38: =EDATE(Assumptions!$B$3,23) -> 47027 | Z38: 24个月合计 / 期末
A39: 现金（规划资金足额补入） | B39: ='Cash Flow'!B86 -> 31308443 | C39: ='Cash Flow'!C86 -> 31191885 | D39: ='Cash Flow'!D86 -> 31075328 | E39: ='Cash Flow'!E86 -> 30945270 | F39: ='Cash Flow'!F86 -> 30815213 | G39: ='Cash Flow'!G86 -> 30640155 | H39: ='Cash Flow'!H86 -> 30433709 | I39: ='Cash Flow'!I86 -> 30272262 | ... Y39: ='Cash Flow'!Y86 -> 12134950 | Z39: =Y39 -> 12134950
A40: 待收回金额 | B40: ='Cash Flow'!B89 -> 0 | C40: ='Cash Flow'!C89 -> 0 | D40: ='Cash Flow'!D89 -> 0 | E40: ='Cash Flow'!E89 -> 0 | F40: ='Cash Flow'!F89 -> 0 | G40: ='Cash Flow'!G89 -> 0 | H40: ='Cash Flow'!H89 -> 0 | I40: ='Cash Flow'!I89 -> 0 | ... Y40: ='Cash Flow'!Y89 -> 0 | Z40: =Y40 -> 0
A41: 厂商预付额度资产 | B41: ='Cash Flow'!B88 -> 0 | C41: ='Cash Flow'!C88 -> 0 | D41: ='Cash Flow'!D88 -> 0 | E41: ='Cash Flow'!E88 -> 0 | F41: ='Cash Flow'!F88 -> 0 | G41: ='Cash Flow'!G88 -> 0 | H41: ='Cash Flow'!H88 -> 0 | I41: ='Cash Flow'!I88 -> 0 | ... Y41: ='Cash Flow'!Y88 -> 0 | Z41: =Y41 -> 0
A42: 保证金资产 | B42: ='Cash Flow'!B87 -> 0 | C42: ='Cash Flow'!C87 -> 0 | D42: ='Cash Flow'!D87 -> 0 | E42: ='Cash Flow'!E87 -> 0 | F42: ='Cash Flow'!F87 -> 0 | G42: ='Cash Flow'!G87 -> 0 | H42: ='Cash Flow'!H87 -> 0 | I42: ='Cash Flow'!I87 -> 0 | ... Y42: ='Cash Flow'!Y87 -> 0 | Z42: =Y42 -> 0
A43: 设备净值 | B43: ='Cash Flow'!B90 -> 72916.667 | C43: ='Cash Flow'!C90 -> 70833.333 | D43: ='Cash Flow'!D90 -> 68750 | E43: ='Cash Flow'!E90 -> 66666.667 | F43: ='Cash Flow'!F90 -> 64583.333 | G43: ='Cash Flow'!G90 -> 62500 | H43: ='Cash Flow'!H90 -> 104166.67 | I43: ='Cash Flow'!I90 -> 100833.33 | ... Y43: ='Cash Flow'!Y90 -> 47500 | Z43: =Y43 -> 47500
A44: 资产合计 | B44: =SUM(B39:B43) -> 31381359 | C44: =SUM(C39:C43) -> 31262718 | D44: =SUM(D39:D43) -> 31144078 | E44: =SUM(E39:E43) -> 31011937 | F44: =SUM(F39:F43) -> 30879796 | G44: =SUM(G39:G43) -> 30702655 | H44: =SUM(H39:H43) -> 30537875 | I44: =SUM(I39:I43) -> 30373095 | ... Y44: =SUM(Y39:Y43) -> 12182450 | Z44: =Y44 -> 12182450
A45: 计划投入资本（非融资承诺） | B45: =Assumptions!$B$4+Summary!D$19 -> 31500000 | C45: =Assumptions!$B$4+Summary!D$19 -> 31500000 | D45: =Assumptions!$B$4+Summary!D$19 -> 31500000 | E45: =Assumptions!$B$4+Summary!D$19 -> 31500000 | F45: =Assumptions!$B$4+Summary!D$19 -> 31500000 | G45: =Assumptions!$B$4+Summary!D$19 -> 31500000 | H45: =Assumptions!$B$4+Summary!D$19 -> 31500000 | I45: =Assumptions!$B$4+Summary!D$19 -> 31500000 | J45: =Assumptions!$B$4+Summary!D$19 -> 31500000 | K45: =Assumptions!$B$4+Summary!D$19 -> 31500000 | L45: =Assumptions!$B$4+Summary!D$19 -> 31500000 | M45: =Assumptions!$B$4+Summary!D$19 -> 31500000 | N45: =Assumptions!$B$4+Summary!D$19 -> 31500000 | O45: =Assumptions!$B$4+Summary!D$19 -> 31500000 | P45: =Assumptions!$B$4+Summary!D$19 -> 31500000 | Q45: =Assumptions!$B$4+Summary!D$19 -> 31500000 | R45: =Assumptions!$B$4+Summary!D$19 -> 31500000 | S45: =Assumptions!$B$4+Summary!D$19 -> 31500000 | T45: =Assumptions!$B$4+Summary!D$19 -> 31500000 | U45: =Assumptions!$B$4+Summary!D$19 -> 31500000 | V45: =Assumptions!$B$4+Summary!D$19 -> 31500000 | W45: =Assumptions!$B$4+Summary!D$19 -> 31500000 | X45: =Assumptions!$B$4+Summary!D$19 -> 31500000 | Y45: =Assumptions!$B$4+Summary!D$19 -> 31500000 | Z45: =Y45 -> 31500000
A46: 累计规划损益 | B46: =SUM('Income Statement'!B45:'Income Statement'!B45) -> -118640.76 | C46: =SUM('Income Statement'!B45:'Income Statement'!C45) -> -237281.53 | D46: =SUM('Income Statement'!B45:'Income Statement'!D45) -> -355922.29 | E46: =SUM('Income Statement'!B45:'Income Statement'!E45) -> -488063.06 | F46: =SUM('Income Statement'!B45:'Income Statement'!F45) -> -620203.82 | G46: =SUM('Income Statement'!B45:'Income Statement'!G45) -> -797344.59 | H46: =SUM('Income Statement'!B45:'Income Statement'!H45) -> -962124.71 | I46: =SUM('Income Statement'!B45:'Income Statement'!I45) -> -1126904.8 | J46: =SUM('Income Statement'!B45:'Income Statement'!J45) -> -1291685 | K46: =SUM('Income Statement'!B45:'Income Statement'!K45) -> -1456465.1 | L46: =SUM('Income Statement'!B45:'Income Statement'!L45) -> -1621245.2 | M46: =SUM('Income Statement'!B45:'Income Statement'!M45) -> -1846025.3 | N46: =SUM('Income Statement'!B45:'Income Statement'!N45) -> -2022805.4 | O46: =SUM('Income Statement'!B45:'Income Statement'!O45) -> -2199585.6 | P46: =SUM('Income Statement'!B45:'Income Statement'!P45) -> -2376365.7 | Q46: =SUM('Income Statement'!B45:'Income Statement'!Q45) -> -2553145.8 | R46: =SUM('Income Statement'!B45:'Income Statement'!R45) -> -2729925.9 | S46: =SUM('Income Statement'!B45:'Income Statement'!S45) -> -2966706.1 | T46: =SUM('Income Statement'!B45:'Income Statement'!T45) -> -4836403.7 | U46: =SUM('Income Statement'!B45:'Income Statement'!U45) -> -6706101.4 | V46: =SUM('Income Statement'!B45:'Income Statement'!V45) -> -8575799 | W46: =SUM('Income Statement'!B45:'Income Statement'!W45) -> -12136383 | X46: =SUM('Income Statement'!B45:'Income Statement'!X45) -> -15696966 | Y46: =SUM('Income Statement'!B45:'Income Statement'!Y45) -> -19317550 | Z46: =Y46 -> -19317550
A47: 资产负债勾稽 | B47: =B44-B45-B46 -> 5.2386895e-10 | C47: =C44-C45-C46 -> -2.6775524e-09 | D47: =D44-D45-D46 -> -2.1536835e-09 | E47: =E44-E45-E46 -> -1.6298145e-09 | F47: =F44-F45-F46 -> -4.8894435e-09 | G47: =G44-G45-G46 -> -4.3073669e-09 | H47: =H44-H45-H46 -> -4.8894435e-09 | I47: =I44-I45-I46 -> -9.0803951e-09 | ... Y47: =Y44-Y45-Y46 -> 0 | Z47: =Y47 -> 0

Sheet Cash Flow
A1: 精简推进
A2: 月份 | B2: =EDATE(Assumptions!$B$3,0) -> 46327 | C2: =EDATE(Assumptions!$B$3,1) -> 46357 | D2: =EDATE(Assumptions!$B$3,2) -> 46388 | E2: =EDATE(Assumptions!$B$3,3) -> 46419 | F2: =EDATE(Assumptions!$B$3,4) -> 46447 | G2: =EDATE(Assumptions!$B$3,5) -> 46478 | H2: =EDATE(Assumptions!$B$3,6) -> 46508 | I2: =EDATE(Assumptions!$B$3,7) -> 46539 | J2: =EDATE(Assumptions!$B$3,8) -> 46569 | K2: =EDATE(Assumptions!$B$3,9) -> 46600 | L2: =EDATE(Assumptions!$B$3,10) -> 46631 | M2: =EDATE(Assumptions!$B$3,11) -> 46661 | N2: =EDATE(Assumptions!$B$3,12) -> 46692 | O2: =EDATE(Assumptions!$B$3,13) -> 46722 | P2: =EDATE(Assumptions!$B$3,14) -> 46753 | Q2: =EDATE(Assumptions!$B$3,15) -> 46784 | R2: =EDATE(Assumptions!$B$3,16) -> 46813 | S2: =EDATE(Assumptions!$B$3,17) -> 46844 | T2: =EDATE(Assumptions!$B$3,18) -> 46874 | U2: =EDATE(Assumptions!$B$3,19) -> 46905 | V2: =EDATE(Assumptions!$B$3,20) -> 46935 | W2: =EDATE(Assumptions!$B$3,21) -> 46966 | X2: =EDATE(Assumptions!$B$3,22) -> 46997 | Y2: =EDATE(Assumptions!$B$3,23) -> 47027 | Z2: 24个月合计 / 期末
A3: 月初现金（未补资） | B3: =Assumptions!$B$4 -> 0 | C3: =B17 -> -76889.358 | D3: =C17 -> -116278.72 | E3: =D17 -> -155668.07 | F3: =E17 -> -201807.43 | G3: =F17 -> -247946.79 | H3: =G17 -> -316586.15 | I3: =H17 -> -404920.18 | J3: =I17 -> -470754.22 | ... Y3: =X17 -> -2295046.3 | Z3: =Y3 -> -2295046.3
A4: 收回的算力成本现金 | B4: =Revenue!B5 -> 0 | C4: =Revenue!C5 -> 0 | D4: =Revenue!D5 -> 0 | E4: =Revenue!E5 -> 0 | F4: =Revenue!F5 -> 0 | G4: =Revenue!G5 -> 0 | H4: =Revenue!H5 -> 0 | I4: =Revenue!I5 -> 0 | ... Y4: =Revenue!Y5 -> 0 | Z4: =SUM(B4:Y4) -> 0
A5: 常规固定与专项现金 | B5: =Costs!B17 -> 39389.358 | C5: =Costs!C17 -> 39389.358 | D5: =Costs!D17 -> 39389.358 | E5: =Costs!E17 -> 46139.358 | F5: =Costs!F17 -> 46139.358 | G5: =Costs!G17 -> 68639.358 | H5: =Costs!H17 -> 65834.037 | I5: =Costs!I17 -> 65834.037 | ... Y5: =Costs!Y17 -> 101834.04 | Z5: =SUM(B5:Y5) -> 1626098.8
A6: 用户Token消耗（费用口径） | B6: =Costs!B11 -> 0 | C6: =Costs!C11 -> 0 | D6: =Costs!D11 -> 0 | E6: =Costs!E11 -> 0 | F6: =Costs!F11 -> 0 | G6: =Costs!G11 -> 0 | H6: =Costs!H11 -> 0 | I6: =Costs!I11 -> 0 | ... Y6: =Costs!Y11 -> 203028.2 | Z6: =SUM(B6:Y6) -> 913809.77
A7: 厂商额度充值（现金时点） | B7: =IF(1=Assumptions!$B$10,Assumptions!$B$8,0) -> 0 | C7: =IF(2=Assumptions!$B$10,Assumptions!$B$8,0) -> 0 | D7: =IF(3=Assumptions!$B$10,Assumptions!$B$8,0) -> 0 | E7: =IF(4=Assumptions!$B$10,Assumptions!$B$8,0) -> 0 | F7: =IF(5=Assumptions!$B$10,Assumptions!$B$8,0) -> 0 | G7: =IF(6=Assumptions!$B$10,Assumptions!$B$8,0) -> 0 | H7: =IF(7=Assumptions!$B$10,Assumptions!$B$8,0) -> 0 | I7: =IF(8=Assumptions!$B$10,Assumptions!$B$8,0) -> 0 | J7: =IF(9=Assumptions!$B$10,Assumptions!$B$8,0) -> 0 | K7: =IF(10=Assumptions!$B$10,Assumptions!$B$8,0) -> 0 | L7: =IF(11=Assumptions!$B$10,Assumptions!$B$8,0) -> 0 | M7: =IF(12=Assumptions!$B$10,Assumptions!$B$8,0) -> 0 | N7: =IF(13=Assumptions!$B$10,Assumptions!$B$8,0) -> 0 | O7: =IF(14=Assumptions!$B$10,Assumptions!$B$8,0) -> 0 | P7: =IF(15=Assumptions!$B$10,Assumptions!$B$8,0) -> 0 | Q7: =IF(16=Assumptions!$B$10,Assumptions!$B$8,0) -> 0 | R7: =IF(17=Assumptions!$B$10,Assumptions!$B$8,0) -> 0 | S7: =IF(18=Assumptions!$B$10,Assumptions!$B$8,0) -> 0 | T7: =IF(19=Assumptions!$B$10,Assumptions!$B$8,0) -> 0 | U7: =IF(20=Assumptions!$B$10,Assumptions!$B$8,0) -> 0 | V7: =IF(21=Assumptions!$B$10,Assumptions!$B$8,0) -> 0 | W7: =IF(22=Assumptions!$B$10,Assumptions!$B$8,0) -> 0 | X7: =IF(23=Assumptions!$B$10,Assumptions!$B$8,0) -> 0 | Y7: =IF(24=Assumptions!$B$10,Assumptions!$B$8,0) -> 0 | Z7: =SUM(B7:Y7) -> 0
A8: 月初预付额度资产 | B8: =0 -> 0 | C8: =B10 -> 0 | D8: =C10 -> 0 | E8: =D10 -> 0 | F8: =E10 -> 0 | G8: =F10 -> 0 | H8: =G10 -> 0 | I8: =H10 -> 0 | J8: =I10 -> 0 | ... Y8: =X10 -> 0 | Z8: =Y8 -> 0
A9: 抵扣已购额度 | B9: =MIN(B8+B7,B6) -> 0 | C9: =MIN(C8+C7,C6) -> 0 | D9: =MIN(D8+D7,D6) -> 0 | E9: =MIN(E8+E7,E6) -> 0 | F9: =MIN(F8+F7,F6) -> 0 | G9: =MIN(G8+G7,G6) -> 0 | H9: =MIN(H8+H7,H6) -> 0 | I9: =MIN(I8+I7,I6) -> 0 | ... Y9: =MIN(Y8+Y7,Y6) -> 0 | Z9: =SUM(B9:Y9) -> 0
A10: 月末预付额度资产 | B10: =B8+B7-B9 -> 0 | C10: =C8+C7-C9 -> 0 | D10: =D8+D7-D9 -> 0 | E10: =E8+E7-E9 -> 0 | F10: =F8+F7-F9 -> 0 | G10: =G8+G7-G9 -> 0 | H10: =H8+H7-H9 -> 0 | I10: =I8+I7-I9 -> 0 | ... Y10: =Y8+Y7-Y9 -> 0 | Z10: =Y10 -> 0
A11: 用户Token实际支付现金 | B11: =B6-B9+B7 -> 0 | C11: =C6-C9+C7 -> 0 | D11: =D6-D9+D7 -> 0 | E11: =E6-E9+E7 -> 0 | F11: =F6-F9+F7 -> 0 | G11: =G6-G9+G7 -> 0 | H11: =H6-H9+H7 -> 0 | I11: =I6-I9+I7 -> 0 | ... Y11: =Y6-Y9+Y7 -> 203028.2 | Z11: =SUM(B11:Y11) -> 913809.77
A12: 非退还合作费用 | B12: =Costs!B12 -> 0 | C12: =Costs!C12 -> 0 | D12: =Costs!D12 -> 0 | E12: =Costs!E12 -> 0 | F12: =Costs!F12 -> 0 | G12: =Costs!G12 -> 0 | H12: =Costs!H12 -> 0 | I12: =Costs!I12 -> 0 | ... Y12: =Costs!Y12 -> 0 | Z12: =SUM(B12:Y12) -> 0
A13: 可退保证金现金 | B13: =IF(1=Assumptions!$B$10,Assumptions!$B$9,0) -> 0 | C13: =IF(2=Assumptions!$B$10,Assumptions!$B$9,0) -> 0 | D13: =IF(3=Assumptions!$B$10,Assumptions!$B$9,0) -> 0 | E13: =IF(4=Assumptions!$B$10,Assumptions!$B$9,0) -> 0 | F13: =IF(5=Assumptions!$B$10,Assumptions!$B$9,0) -> 0 | G13: =IF(6=Assumptions!$B$10,Assumptions!$B$9,0) -> 0 | H13: =IF(7=Assumptions!$B$10,Assumptions!$B$9,0) -> 0 | I13: =IF(8=Assumptions!$B$10,Assumptions!$B$9,0) -> 0 | J13: =IF(9=Assumptions!$B$10,Assumptions!$B$9,0) -> 0 | K13: =IF(10=Assumptions!$B$10,Assumptions!$B$9,0) -> 0 | L13: =IF(11=Assumptions!$B$10,Assumptions!$B$9,0) -> 0 | M13: =IF(12=Assumptions!$B$10,Assumptions!$B$9,0) -> 0 | N13: =IF(13=Assumptions!$B$10,Assumptions!$B$9,0) -> 0 | O13: =IF(14=Assumptions!$B$10,Assumptions!$B$9,0) -> 0 | P13: =IF(15=Assumptions!$B$10,Assumptions!$B$9,0) -> 0 | Q13: =IF(16=Assumptions!$B$10,Assumptions!$B$9,0) -> 0 | R13: =IF(17=Assumptions!$B$10,Assumptions!$B$9,0) -> 0 | S13: =IF(18=Assumptions!$B$10,Assumptions!$B$9,0) -> 0 | T13: =IF(19=Assumptions!$B$10,Assumptions!$B$9,0) -> 0 | U13: =IF(20=Assumptions!$B$10,Assumptions!$B$9,0) -> 0 | V13: =IF(21=Assumptions!$B$10,Assumptions!$B$9,0) -> 0 | W13: =IF(22=Assumptions!$B$10,Assumptions!$B$9,0) -> 0 | X13: =IF(23=Assumptions!$B$10,Assumptions!$B$9,0) -> 0 | Y13: =IF(24=Assumptions!$B$10,Assumptions!$B$9,0) -> 0 | Z13: =SUM(B13:Y13) -> 0
A14: 设备购置现金 | B14: =Costs!B14 -> 37500 | C14: =Costs!C14 -> 0 | D14: =Costs!D14 -> 0 | E14: =Costs!E14 -> 0 | F14: =Costs!F14 -> 0 | G14: =Costs!G14 -> 0 | H14: =Costs!H14 -> 22500 | I14: =Costs!I14 -> 0 | ... Y14: =Costs!Y14 -> 0 | Z14: =SUM(B14:Y14) -> 60000
A15: 现金支付总计 | B15: =B5+B11+B12+B13+B14 -> 76889.358 | C15: =C5+C11+C12+C13+C14 -> 39389.358 | D15: =D5+D11+D12+D13+D14 -> 39389.358 | E15: =E5+E11+E12+E13+E14 -> 46139.358 | F15: =F5+F11+F12+F13+F14 -> 46139.358 | G15: =G5+G11+G12+G13+G14 -> 68639.358 | H15: =H5+H11+H12+H13+H14 -> 88334.037 | I15: =I5+I11+I12+I13+I14 -> 65834.037 | ... Y15: =Y5+Y11+Y12+Y13+Y14 -> 304862.24 | Z15: =SUM(B15:Y15) -> 2599908.6
A16: 当月净现金流 | B16: =B4-B15 -> -76889.358 | C16: =C4-C15 -> -39389.358 | D16: =D4-D15 -> -39389.358 | E16: =E4-E15 -> -46139.358 | F16: =F4-F15 -> -46139.358 | G16: =G4-G15 -> -68639.358 | H16: =H4-H15 -> -88334.037 | I16: =I4-I15 -> -65834.037 | ... Y16: =Y4-Y15 -> -304862.24 | Z16: =SUM(B16:Y16) -> -2599908.6
A17: 月末现金（未补资） | B17: =B3+B16 -> -76889.358 | C17: =C3+C16 -> -116278.72 | D17: =D3+D16 -> -155668.07 | E17: =E3+E16 -> -201807.43 | F17: =F3+F16 -> -247946.79 | G17: =G3+G16 -> -316586.15 | H17: =H3+H16 -> -404920.18 | I17: =I3+I16 -> -470754.22 | ... Y17: =Y3+Y16 -> -2599908.6 | Z17: =Y17 -> -2599908.6
A18: 假设足额补入规划资金 | B18: =IF(1=1,Summary!B$19,0) -> 4000000 | C18: =IF(2=1,Summary!B$19,0) -> 0 | D18: =IF(3=1,Summary!B$19,0) -> 0 | E18: =IF(4=1,Summary!B$19,0) -> 0 | F18: =IF(5=1,Summary!B$19,0) -> 0 | G18: =IF(6=1,Summary!B$19,0) -> 0 | H18: =IF(7=1,Summary!B$19,0) -> 0 | I18: =IF(8=1,Summary!B$19,0) -> 0 | J18: =IF(9=1,Summary!B$19,0) -> 0 | K18: =IF(10=1,Summary!B$19,0) -> 0 | L18: =IF(11=1,Summary!B$19,0) -> 0 | M18: =IF(12=1,Summary!B$19,0) -> 0 | N18: =IF(13=1,Summary!B$19,0) -> 0 | O18: =IF(14=1,Summary!B$19,0) -> 0 | P18: =IF(15=1,Summary!B$19,0) -> 0 | Q18: =IF(16=1,Summary!B$19,0) -> 0 | R18: =IF(17=1,Summary!B$19,0) -> 0 | S18: =IF(18=1,Summary!B$19,0) -> 0 | T18: =IF(19=1,Summary!B$19,0) -> 0 | U18: =IF(20=1,Summary!B$19,0) -> 0 | V18: =IF(21=1,Summary!B$19,0) -> 0 | W18: =IF(22=1,Summary!B$19,0) -> 0 | X18: =IF(23=1,Summary!B$19,0) -> 0 | Y18: =IF(24=1,Summary!B$19,0) -> 0 | Z18: =SUM(B18:Y18) -> 4000000
A19: 月初现金（假设补足） | B19: =Assumptions!$B$4 -> 0 | C19: =B20 -> 3923110.6 | D19: =C20 -> 3883721.3 | E19: =D20 -> 3844331.9 | F19: =E20 -> 3798192.6 | G19: =F20 -> 3752053.2 | H19: =G20 -> 3683413.9 | I19: =H20 -> 3595079.8 | J19: =I20 -> 3529245.8 | ... Y19: =X20 -> 1704953.7 | Z19: =Y19 -> 1704953.7
A20: 月末现金（假设补足） | B20: =B19+B4+B18-B15 -> 3923110.6 | C20: =C19+C4+C18-C15 -> 3883721.3 | D20: =D19+D4+D18-D15 -> 3844331.9 | E20: =E19+E4+E18-E15 -> 3798192.6 | F20: =F19+F4+F18-F15 -> 3752053.2 | G20: =G19+G4+G18-G15 -> 3683413.9 | H20: =H19+H4+H18-H15 -> 3595079.8 | I20: =I19+I4+I18-I15 -> 3529245.8 | ... Y20: =Y19+Y4+Y18-Y15 -> 1400091.4 | Z20: =Y20 -> 1400091.4
A21: 保证金资产 | B21: =SUM($B13:B13) -> 0 | C21: =SUM($B13:C13) -> 0 | D21: =SUM($B13:D13) -> 0 | E21: =SUM($B13:E13) -> 0 | F21: =SUM($B13:F13) -> 0 | G21: =SUM($B13:G13) -> 0 | H21: =SUM($B13:H13) -> 0 | I21: =SUM($B13:I13) -> 0 | ... Y21: =SUM($B13:Y13) -> 0 | Z21: =Y21 -> 0
A22: 额度资产 | B22: =B10 -> 0 | C22: =C10 -> 0 | D22: =D10 -> 0 | E22: =E10 -> 0 | F22: =F10 -> 0 | G22: =G10 -> 0 | H22: =H10 -> 0 | I22: =I10 -> 0 | ... Y22: =Y10 -> 0 | Z22: =Y22 -> 0
A23: 待收回金额 | B23: =Revenue!B6 -> 0 | C23: =Revenue!C6 -> 0 | D23: =Revenue!D6 -> 0 | E23: =Revenue!E6 -> 0 | F23: =Revenue!F6 -> 0 | G23: =Revenue!G6 -> 0 | H23: =Revenue!H6 -> 0 | I23: =Revenue!I6 -> 0 | ... Y23: =Revenue!Y6 -> 0 | Z23: =Y23 -> 0
A24: 设备净值 | B24: =SUM(Costs!B14:'Costs'!B14)-SUM(Costs!B15:'Costs'!B15) -> 36458.333 | C24: =SUM(Costs!B14:'Costs'!C14)-SUM(Costs!B15:'Costs'!C15) -> 35416.667 | D24: =SUM(Costs!B14:'Costs'!D14)-SUM(Costs!B15:'Costs'!D15) -> 34375 | E24: =SUM(Costs!B14:'Costs'!E14)-SUM(Costs!B15:'Costs'!E15) -> 33333.333 | F24: =SUM(Costs!B14:'Costs'!F14)-SUM(Costs!B15:'Costs'!F15) -> 32291.667 | G24: =SUM(Costs!B14:'Costs'!G14)-SUM(Costs!B15:'Costs'!G15) -> 31250 | H24: =SUM(Costs!B14:'Costs'!H14)-SUM(Costs!B15:'Costs'!H15) -> 52083.333 | I24: =SUM(Costs!B14:'Costs'!I14)-SUM(Costs!B15:'Costs'!I15) -> 50416.667 | J24: =SUM(Costs!B14:'Costs'!J14)-SUM(Costs!B15:'Costs'!J15) -> 48750 | K24: =SUM(Costs!B14:'Costs'!K14)-SUM(Costs!B15:'Costs'!K15) -> 47083.333 | L24: =SUM(Costs!B14:'Costs'!L14)-SUM(Costs!B15:'Costs'!L15) -> 45416.667 | M24: =SUM(Costs!B14:'Costs'!M14)-SUM(Costs!B15:'Costs'!M15) -> 43750 | N24: =SUM(Costs!B14:'Costs'!N14)-SUM(Costs!B15:'Costs'!N15) -> 42083.333 | O24: =SUM(Costs!B14:'Costs'!O14)-SUM(Costs!B15:'Costs'!O15) -> 40416.667 | P24: =SUM(Costs!B14:'Costs'!P14)-SUM(Costs!B15:'Costs'!P15) -> 38750 | Q24: =SUM(Costs!B14:'Costs'!Q14)-SUM(Costs!B15:'Costs'!Q15) -> 37083.333 | R24: =SUM(Costs!B14:'Costs'!R14)-SUM(Costs!B15:'Costs'!R15) -> 35416.667 | S24: =SUM(Costs!B14:'Costs'!S14)-SUM(Costs!B15:'Costs'!S15) -> 33750 | T24: =SUM(Costs!B14:'Costs'!T14)-SUM(Costs!B15:'Costs'!T15) -> 32083.333 | U24: =SUM(Costs!B14:'Costs'!U14)-SUM(Costs!B15:'Costs'!U15) -> 30416.667 | V24: =SUM(Costs!B14:'Costs'!V14)-SUM(Costs!B15:'Costs'!V15) -> 28750 | W24: =SUM(Costs!B14:'Costs'!W14)-SUM(Costs!B15:'Costs'!W15) -> 27083.333 | X24: =SUM(Costs!B14:'Costs'!X14)-SUM(Costs!B15:'Costs'!X15) -> 25416.667 | Y24: =SUM(Costs!B14:'Costs'!Y14)-SUM(Costs!B15:'Costs'!Y15) -> 23750 | Z24: =Y24 -> 23750
A25: 充值/消耗现金恒等检查 | B25: =B11-B6-B7+B9 -> 0 | C25: =C11-C6-C7+C9 -> 0 | D25: =D11-D6-D7+D9 -> 0 | E25: =E11-E6-E7+E9 -> 0 | F25: =F11-F6-F7+F9 -> 0 | G25: =G11-G6-G7+G9 -> 0 | H25: =H11-H6-H7+H9 -> 0 | I25: =I11-I6-I7+I9 -> 0 | ... Y25: =Y11-Y6-Y7+Y9 -> 0 | Z25: =SUM(B25:Y25) -> 0
A34: 基准建设
A35: 月份 | B35: =EDATE(Assumptions!$B$3,0) -> 46327 | C35: =EDATE(Assumptions!$B$3,1) -> 46357 | D35: =EDATE(Assumptions!$B$3,2) -> 46388 | E35: =EDATE(Assumptions!$B$3,3) -> 46419 | F35: =EDATE(Assumptions!$B$3,4) -> 46447 | G35: =EDATE(Assumptions!$B$3,5) -> 46478 | H35: =EDATE(Assumptions!$B$3,6) -> 46508 | I35: =EDATE(Assumptions!$B$3,7) -> 46539 | J35: =EDATE(Assumptions!$B$3,8) -> 46569 | K35: =EDATE(Assumptions!$B$3,9) -> 46600 | L35: =EDATE(Assumptions!$B$3,10) -> 46631 | M35: =EDATE(Assumptions!$B$3,11) -> 46661 | N35: =EDATE(Assumptions!$B$3,12) -> 46692 | O35: =EDATE(Assumptions!$B$3,13) -> 46722 | P35: =EDATE(Assumptions!$B$3,14) -> 46753 | Q35: =EDATE(Assumptions!$B$3,15) -> 46784 | R35: =EDATE(Assumptions!$B$3,16) -> 46813 | S35: =EDATE(Assumptions!$B$3,17) -> 46844 | T35: =EDATE(Assumptions!$B$3,18) -> 46874 | U35: =EDATE(Assumptions!$B$3,19) -> 46905 | V35: =EDATE(Assumptions!$B$3,20) -> 46935 | W35: =EDATE(Assumptions!$B$3,21) -> 46966 | X35: =EDATE(Assumptions!$B$3,22) -> 46997 | Y35: =EDATE(Assumptions!$B$3,23) -> 47027 | Z35: 24个月合计 / 期末
A36: 月初现金（未补资） | B36: =Assumptions!$B$4 -> 0 | C36: =B50 -> -121778.72 | D36: =C50 -> -193557.43 | E36: =D50 -> -265336.15 | F36: =E50 -> -346114.86 | G36: =F50 -> -426893.58 | H36: =G50 -> -537672.29 | I36: =H50 -> -673377.25 | J36: =I50 -> -779082.2 | ... Y36: =X50 -> -4901928.4 | Z36: =Y36 -> -4901928.4
A37: 收回的算力成本现金 | B37: =Revenue!B17 -> 0 | C37: =Revenue!C17 -> 0 | D37: =Revenue!D17 -> 0 | E37: =Revenue!E17 -> 0 | F37: =Revenue!F17 -> 0 | G37: =Revenue!G17 -> 0 | H37: =Revenue!H17 -> 0 | I37: =Revenue!I17 -> 0 | ... Y37: =Revenue!Y17 -> 0 | Z37: =SUM(B37:Y37) -> 0
A38: 常规固定与专项现金 | B38: =Costs!B42 -> 71778.716 | C38: =Costs!C42 -> 71778.716 | D38: =Costs!D42 -> 71778.716 | E38: =Costs!E42 -> 80778.716 | F38: =Costs!F42 -> 80778.716 | G38: =Costs!G42 -> 110778.72 | H38: =Costs!H42 -> 105704.95 | I38: =Costs!I42 -> 105704.95 | ... Y38: =Costs!Y42 -> 153704.95 | Z38: =SUM(B38:Y38) -> 2606361.5
A39: 用户Token消耗（费用口径） | B39: =Costs!B36 -> 0 | C39: =Costs!C36 -> 0 | D39: =Costs!D36 -> 0 | E39: =Costs!E36 -> 0 | F39: =Costs!F36 -> 0 | G39: =Costs!G36 -> 0 | H39: =Costs!H36 -> 0 | I39: =Costs!I36 -> 0 | ... Y39: =Costs!Y36 -> 676760.68 | Z39: =SUM(B39:Y39) -> 3046032.6
A40: 厂商额度充值（现金时点） | B40: =IF(1=Assumptions!$B$10,Assumptions!$B$8,0) -> 0 | C40: =IF(2=Assumptions!$B$10,Assumptions!$B$8,0) -> 0 | D40: =IF(3=Assumptions!$B$10,Assumptions!$B$8,0) -> 0 | E40: =IF(4=Assumptions!$B$10,Assumptions!$B$8,0) -> 0 | F40: =IF(5=Assumptions!$B$10,Assumptions!$B$8,0) -> 0 | G40: =IF(6=Assumptions!$B$10,Assumptions!$B$8,0) -> 0 | H40: =IF(7=Assumptions!$B$10,Assumptions!$B$8,0) -> 0 | I40: =IF(8=Assumptions!$B$10,Assumptions!$B$8,0) -> 0 | J40: =IF(9=Assumptions!$B$10,Assumptions!$B$8,0) -> 0 | K40: =IF(10=Assumptions!$B$10,Assumptions!$B$8,0) -> 0 | L40: =IF(11=Assumptions!$B$10,Assumptions!$B$8,0) -> 0 | M40: =IF(12=Assumptions!$B$10,Assumptions!$B$8,0) -> 0 | N40: =IF(13=Assumptions!$B$10,Assumptions!$B$8,0) -> 0 | O40: =IF(14=Assumptions!$B$10,Assumptions!$B$8,0) -> 0 | P40: =IF(15=Assumptions!$B$10,Assumptions!$B$8,0) -> 0 | Q40: =IF(16=Assumptions!$B$10,Assumptions!$B$8,0) -> 0 | R40: =IF(17=Assumptions!$B$10,Assumptions!$B$8,0) -> 0 | S40: =IF(18=Assumptions!$B$10,Assumptions!$B$8,0) -> 0 | T40: =IF(19=Assumptions!$B$10,Assumptions!$B$8,0) -> 0 | U40: =IF(20=Assumptions!$B$10,Assumptions!$B$8,0) -> 0 | V40: =IF(21=Assumptions!$B$10,Assumptions!$B$8,0) -> 0 | W40: =IF(22=Assumptions!$B$10,Assumptions!$B$8,0) -> 0 | X40: =IF(23=Assumptions!$B$10,Assumptions!$B$8,0) -> 0 | Y40: =IF(24=Assumptions!$B$10,Assumptions!$B$8,0) -> 0 | Z40: =SUM(B40:Y40) -> 0
A41: 月初预付额度资产 | B41: =0 -> 0 | C41: =B43 -> 0 | D41: =C43 -> 0 | E41: =D43 -> 0 | F41: =E43 -> 0 | G41: =F43 -> 0 | H41: =G43 -> 0 | I41: =H43 -> 0 | J41: =I43 -> 0 | ... Y41: =X43 -> 0 | Z41: =Y41 -> 0
A42: 抵扣已购额度 | B42: =MIN(B41+B40,B39) -> 0 | C42: =MIN(C41+C40,C39) -> 0 | D42: =MIN(D41+D40,D39) -> 0 | E42: =MIN(E41+E40,E39) -> 0 | F42: =MIN(F41+F40,F39) -> 0 | G42: =MIN(G41+G40,G39) -> 0 | H42: =MIN(H41+H40,H39) -> 0 | I42: =MIN(I41+I40,I39) -> 0 | ... Y42: =MIN(Y41+Y40,Y39) -> 0 | Z42: =SUM(B42:Y42) -> 0
A43: 月末预付额度资产 | B43: =B41+B40-B42 -> 0 | C43: =C41+C40-C42 -> 0 | D43: =D41+D40-D42 -> 0 | E43: =E41+E40-E42 -> 0 | F43: =F41+F40-F42 -> 0 | G43: =G41+G40-G42 -> 0 | H43: =H41+H40-H42 -> 0 | I43: =I41+I40-I42 -> 0 | ... Y43: =Y41+Y40-Y42 -> 0 | Z43: =Y43 -> 0
A44: 用户Token实际支付现金 | B44: =B39-B42+B40 -> 0 | C44: =C39-C42+C40 -> 0 | D44: =D39-D42+D40 -> 0 | E44: =E39-E42+E40 -> 0 | F44: =F39-F42+F40 -> 0 | G44: =G39-G42+G40 -> 0 | H44: =H39-H42+H40 -> 0 | I44: =I39-I42+I40 -> 0 | ... Y44: =Y39-Y42+Y40 -> 676760.68 | Z44: =SUM(B44:Y44) -> 3046032.6
A45: 非退还合作费用 | B45: =Costs!B37 -> 0 | C45: =Costs!C37 -> 0 | D45: =Costs!D37 -> 0 | E45: =Costs!E37 -> 0 | F45: =Costs!F37 -> 0 | G45: =Costs!G37 -> 0 | H45: =Costs!H37 -> 0 | I45: =Costs!I37 -> 0 | ... Y45: =Costs!Y37 -> 0 | Z45: =SUM(B45:Y45) -> 0
A46: 可退保证金现金 | B46: =IF(1=Assumptions!$B$10,Assumptions!$B$9,0) -> 0 | C46: =IF(2=Assumptions!$B$10,Assumptions!$B$9,0) -> 0 | D46: =IF(3=Assumptions!$B$10,Assumptions!$B$9,0) -> 0 | E46: =IF(4=Assumptions!$B$10,Assumptions!$B$9,0) -> 0 | F46: =IF(5=Assumptions!$B$10,Assumptions!$B$9,0) -> 0 | G46: =IF(6=Assumptions!$B$10,Assumptions!$B$9,0) -> 0 | H46: =IF(7=Assumptions!$B$10,Assumptions!$B$9,0) -> 0 | I46: =IF(8=Assumptions!$B$10,Assumptions!$B$9,0) -> 0 | J46: =IF(9=Assumptions!$B$10,Assumptions!$B$9,0) -> 0 | K46: =IF(10=Assumptions!$B$10,Assumptions!$B$9,0) -> 0 | L46: =IF(11=Assumptions!$B$10,Assumptions!$B$9,0) -> 0 | M46: =IF(12=Assumptions!$B$10,Assumptions!$B$9,0) -> 0 | N46: =IF(13=Assumptions!$B$10,Assumptions!$B$9,0) -> 0 | O46: =IF(14=Assumptions!$B$10,Assumptions!$B$9,0) -> 0 | P46: =IF(15=Assumptions!$B$10,Assumptions!$B$9,0) -> 0 | Q46: =IF(16=Assumptions!$B$10,Assumptions!$B$9,0) -> 0 | R46: =IF(17=Assumptions!$B$10,Assumptions!$B$9,0) -> 0 | S46: =IF(18=Assumptions!$B$10,Assumptions!$B$9,0) -> 0 | T46: =IF(19=Assumptions!$B$10,Assumptions!$B$9,0) -> 0 | U46: =IF(20=Assumptions!$B$10,Assumptions!$B$9,0) -> 0 | V46: =IF(21=Assumptions!$B$10,Assumptions!$B$9,0) -> 0 | W46: =IF(22=Assumptions!$B$10,Assumptions!$B$9,0) -> 0 | X46: =IF(23=Assumptions!$B$10,Assumptions!$B$9,0) -> 0 | Y46: =IF(24=Assumptions!$B$10,Assumptions!$B$9,0) -> 0 | Z46: =SUM(B46:Y46) -> 0
A47: 设备购置现金 | B47: =Costs!B39 -> 50000 | C47: =Costs!C39 -> 0 | D47: =Costs!D39 -> 0 | E47: =Costs!E39 -> 0 | F47: =Costs!F39 -> 0 | G47: =Costs!G39 -> 0 | H47: =Costs!H39 -> 30000 | I47: =Costs!I39 -> 0 | ... Y47: =Costs!Y39 -> 0 | Z47: =SUM(B47:Y47) -> 80000
A48: 现金支付总计 | B48: =B38+B44+B45+B46+B47 -> 121778.72 | C48: =C38+C44+C45+C46+C47 -> 71778.716 | D48: =D38+D44+D45+D46+D47 -> 71778.716 | E48: =E38+E44+E45+E46+E47 -> 80778.716 | F48: =F38+F44+F45+F46+F47 -> 80778.716 | G48: =G38+G44+G45+G46+G47 -> 110778.72 | H48: =H38+H44+H45+H46+H47 -> 135704.95 | I48: =I38+I44+I45+I46+I47 -> 105704.95 | ... Y48: =Y38+Y44+Y45+Y46+Y47 -> 830465.63 | Z48: =SUM(B48:Y48) -> 5732394
A49: 当月净现金流 | B49: =B37-B48 -> -121778.72 | C49: =C37-C48 -> -71778.716 | D49: =D37-D48 -> -71778.716 | E49: =E37-E48 -> -80778.716 | F49: =F37-F48 -> -80778.716 | G49: =G37-G48 -> -110778.72 | H49: =H37-H48 -> -135704.95 | I49: =I37-I48 -> -105704.95 | ... Y49: =Y37-Y48 -> -830465.63 | Z49: =SUM(B49:Y49) -> -5732394
A50: 月末现金（未补资） | B50: =B36+B49 -> -121778.72 | C50: =C36+C49 -> -193557.43 | D50: =D36+D49 -> -265336.15 | E50: =E36+E49 -> -346114.86 | F50: =F36+F49 -> -426893.58 | G50: =G36+G49 -> -537672.29 | H50: =H36+H49 -> -673377.25 | I50: =I36+I49 -> -779082.2 | ... Y50: =Y36+Y49 -> -5732394 | Z50: =Y50 -> -5732394
A51: 假设足额补入规划资金 | B51: =IF(1=1,Summary!C$19,0) -> 9000000 | C51: =IF(2=1,Summary!C$19,0) -> 0 | D51: =IF(3=1,Summary!C$19,0) -> 0 | E51: =IF(4=1,Summary!C$19,0) -> 0 | F51: =IF(5=1,Summary!C$19,0) -> 0 | G51: =IF(6=1,Summary!C$19,0) -> 0 | H51: =IF(7=1,Summary!C$19,0) -> 0 | I51: =IF(8=1,Summary!C$19,0) -> 0 | J51: =IF(9=1,Summary!C$19,0) -> 0 | K51: =IF(10=1,Summary!C$19,0) -> 0 | L51: =IF(11=1,Summary!C$19,0) -> 0 | M51: =IF(12=1,Summary!C$19,0) -> 0 | N51: =IF(13=1,Summary!C$19,0) -> 0 | O51: =IF(14=1,Summary!C$19,0) -> 0 | P51: =IF(15=1,Summary!C$19,0) -> 0 | Q51: =IF(16=1,Summary!C$19,0) -> 0 | R51: =IF(17=1,Summary!C$19,0) -> 0 | S51: =IF(18=1,Summary!C$19,0) -> 0 | T51: =IF(19=1,Summary!C$19,0) -> 0 | U51: =IF(20=1,Summary!C$19,0) -> 0 | V51: =IF(21=1,Summary!C$19,0) -> 0 | W51: =IF(22=1,Summary!C$19,0) -> 0 | X51: =IF(23=1,Summary!C$19,0) -> 0 | Y51: =IF(24=1,Summary!C$19,0) -> 0 | Z51: =SUM(B51:Y51) -> 9000000
A52: 月初现金（假设补足） | B52: =Assumptions!$B$4 -> 0 | C52: =B53 -> 8878221.3 | D52: =C53 -> 8806442.6 | E52: =D53 -> 8734663.9 | F52: =E53 -> 8653885.1 | G52: =F53 -> 8573106.4 | H52: =G53 -> 8462327.7 | I52: =H53 -> 8326622.8 | J52: =I53 -> 8220917.8 | ... Y52: =X53 -> 4098071.6 | Z52: =Y52 -> 4098071.6
A53: 月末现金（假设补足） | B53: =B52+B37+B51-B48 -> 8878221.3 | C53: =C52+C37+C51-C48 -> 8806442.6 | D53: =D52+D37+D51-D48 -> 8734663.9 | E53: =E52+E37+E51-E48 -> 8653885.1 | F53: =F52+F37+F51-F48 -> 8573106.4 | G53: =G52+G37+G51-G48 -> 8462327.7 | H53: =H52+H37+H51-H48 -> 8326622.8 | I53: =I52+I37+I51-I48 -> 8220917.8 | ... Y53: =Y52+Y37+Y51-Y48 -> 3267606 | Z53: =Y53 -> 3267606
A54: 保证金资产 | B54: =SUM($B46:B46) -> 0 | C54: =SUM($B46:C46) -> 0 | D54: =SUM($B46:D46) -> 0 | E54: =SUM($B46:E46) -> 0 | F54: =SUM($B46:F46) -> 0 | G54: =SUM($B46:G46) -> 0 | H54: =SUM($B46:H46) -> 0 | I54: =SUM($B46:I46) -> 0 | ... Y54: =SUM($B46:Y46) -> 0 | Z54: =Y54 -> 0
A55: 额度资产 | B55: =B43 -> 0 | C55: =C43 -> 0 | D55: =D43 -> 0 | E55: =E43 -> 0 | F55: =F43 -> 0 | G55: =G43 -> 0 | H55: =H43 -> 0 | I55: =I43 -> 0 | ... Y55: =Y43 -> 0 | Z55: =Y55 -> 0
A56: 待收回金额 | B56: =Revenue!B18 -> 0 | C56: =Revenue!C18 -> 0 | D56: =Revenue!D18 -> 0 | E56: =Revenue!E18 -> 0 | F56: =Revenue!F18 -> 0 | G56: =Revenue!G18 -> 0 | H56: =Revenue!H18 -> 0 | I56: =Revenue!I18 -> 0 | ... Y56: =Revenue!Y18 -> 0 | Z56: =Y56 -> 0
A57: 设备净值 | B57: =SUM(Costs!B39:'Costs'!B39)-SUM(Costs!B40:'Costs'!B40) -> 48611.111 | C57: =SUM(Costs!B39:'Costs'!C39)-SUM(Costs!B40:'Costs'!C40) -> 47222.222 | D57: =SUM(Costs!B39:'Costs'!D39)-SUM(Costs!B40:'Costs'!D40) -> 45833.333 | E57: =SUM(Costs!B39:'Costs'!E39)-SUM(Costs!B40:'Costs'!E40) -> 44444.444 | F57: =SUM(Costs!B39:'Costs'!F39)-SUM(Costs!B40:'Costs'!F40) -> 43055.556 | G57: =SUM(Costs!B39:'Costs'!G39)-SUM(Costs!B40:'Costs'!G40) -> 41666.667 | H57: =SUM(Costs!B39:'Costs'!H39)-SUM(Costs!B40:'Costs'!H40) -> 69444.444 | I57: =SUM(Costs!B39:'Costs'!I39)-SUM(Costs!B40:'Costs'!I40) -> 67222.222 | J57: =SUM(Costs!B39:'Costs'!J39)-SUM(Costs!B40:'Costs'!J40) -> 65000 | K57: =SUM(Costs!B39:'Costs'!K39)-SUM(Costs!B40:'Costs'!K40) -> 62777.778 | L57: =SUM(Costs!B39:'Costs'!L39)-SUM(Costs!B40:'Costs'!L40) -> 60555.556 | M57: =SUM(Costs!B39:'Costs'!M39)-SUM(Costs!B40:'Costs'!M40) -> 58333.333 | N57: =SUM(Costs!B39:'Costs'!N39)-SUM(Costs!B40:'Costs'!N40) -> 56111.111 | O57: =SUM(Costs!B39:'Costs'!O39)-SUM(Costs!B40:'Costs'!O40) -> 53888.889 | P57: =SUM(Costs!B39:'Costs'!P39)-SUM(Costs!B40:'Costs'!P40) -> 51666.667 | Q57: =SUM(Costs!B39:'Costs'!Q39)-SUM(Costs!B40:'Costs'!Q40) -> 49444.444 | R57: =SUM(Costs!B39:'Costs'!R39)-SUM(Costs!B40:'Costs'!R40) -> 47222.222 | S57: =SUM(Costs!B39:'Costs'!S39)-SUM(Costs!B40:'Costs'!S40) -> 45000 | T57: =SUM(Costs!B39:'Costs'!T39)-SUM(Costs!B40:'Costs'!T40) -> 42777.778 | U57: =SUM(Costs!B39:'Costs'!U39)-SUM(Costs!B40:'Costs'!U40) -> 40555.556 | V57: =SUM(Costs!B39:'Costs'!V39)-SUM(Costs!B40:'Costs'!V40) -> 38333.333 | W57: =SUM(Costs!B39:'Costs'!W39)-SUM(Costs!B40:'Costs'!W40) -> 36111.111 | X57: =SUM(Costs!B39:'Costs'!X39)-SUM(Costs!B40:'Costs'!X40) -> 33888.889 | Y57: =SUM(Costs!B39:'Costs'!Y39)-SUM(Costs!B40:'Costs'!Y40) -> 31666.667 | Z57: =Y57 -> 31666.667
A58: 充值/消耗现金恒等检查 | B58: =B44-B39-B40+B42 -> 0 | C58: =C44-C39-C40+C42 -> 0 | D58: =D44-D39-D40+D42 -> 0 | E58: =E44-E39-E40+E42 -> 0 | F58: =F44-F39-F40+F42 -> 0 | G58: =G44-G39-G40+G42 -> 0 | H58: =H44-H39-H40+H42 -> 0 | I58: =I44-I39-I40+I42 -> 0 | ... Y58: =Y44-Y39-Y40+Y42 -> 0 | Z58: =SUM(B58:Y58) -> 0
A67: 高用量压力
A68: 月份 | B68: =EDATE(Assumptions!$B$3,0) -> 46327 | C68: =EDATE(Assumptions!$B$3,1) -> 46357 | D68: =EDATE(Assumptions!$B$3,2) -> 46388 | E68: =EDATE(Assumptions!$B$3,3) -> 46419 | F68: =EDATE(Assumptions!$B$3,4) -> 46447 | G68: =EDATE(Assumptions!$B$3,5) -> 46478 | H68: =EDATE(Assumptions!$B$3,6) -> 46508 | I68: =EDATE(Assumptions!$B$3,7) -> 46539 | J68: =EDATE(Assumptions!$B$3,8) -> 46569 | K68: =EDATE(Assumptions!$B$3,9) -> 46600 | L68: =EDATE(Assumptions!$B$3,10) -> 46631 | M68: =EDATE(Assumptions!$B$3,11) -> 46661 | N68: =EDATE(Assumptions!$B$3,12) -> 46692 | O68: =EDATE(Assumptions!$B$3,13) -> 46722 | P68: =EDATE(Assumptions!$B$3,14) -> 46753 | Q68: =EDATE(Assumptions!$B$3,15) -> 46784 | R68: =EDATE(Assumptions!$B$3,16) -> 46813 | S68: =EDATE(Assumptions!$B$3,17) -> 46844 | T68: =EDATE(Assumptions!$B$3,18) -> 46874 | U68: =EDATE(Assumptions!$B$3,19) -> 46905 | V68: =EDATE(Assumptions!$B$3,20) -> 46935 | W68: =EDATE(Assumptions!$B$3,21) -> 46966 | X68: =EDATE(Assumptions!$B$3,22) -> 46997 | Y68: =EDATE(Assumptions!$B$3,23) -> 47027 | Z68: 24个月合计 / 期末
A69: 月初现金（未补资） | B69: =Assumptions!$B$4 -> 0 | C69: =B83 -> -191557.43 | D69: =C83 -> -308114.86 | E69: =D83 -> -424672.29 | F69: =E83 -> -554729.73 | G69: =F83 -> -684787.16 | H69: =G83 -> -859844.59 | I69: =H83 -> -1066291.4 | J69: =I83 -> -1227738.2 | ... Y69: =X83 -> -15747799 | Z69: =Y69 -> -15747799
A70: 收回的算力成本现金 | B70: =Revenue!B29 -> 0 | C70: =Revenue!C29 -> 0 | D70: =Revenue!D29 -> 0 | E70: =Revenue!E29 -> 0 | F70: =Revenue!F29 -> 0 | G70: =Revenue!G29 -> 0 | H70: =Revenue!H29 -> 0 | I70: =Revenue!I29 -> 0 | ... Y70: =Revenue!Y29 -> 0 | Z70: =SUM(B70:Y70) -> 0
A71: 常规固定与专项现金 | B71: =Costs!B67 -> 116557.43 | C71: =Costs!C67 -> 116557.43 | D71: =Costs!D67 -> 116557.43 | E71: =Costs!E67 -> 130057.43 | F71: =Costs!F67 -> 130057.43 | G71: =Costs!G67 -> 175057.43 | H71: =Costs!H67 -> 161446.79 | I71: =Costs!I67 -> 161446.79 | ... Y71: =Costs!Y67 -> 233446.79 | Z71: =SUM(B71:Y71) -> 4014886.8
A72: 用户Token消耗（费用口径） | B72: =Costs!B61 -> 0 | C72: =Costs!C61 -> 0 | D72: =Costs!D61 -> 0 | E72: =Costs!E61 -> 0 | F72: =Costs!F61 -> 0 | G72: =Costs!G61 -> 0 | H72: =Costs!H61 -> 0 | I72: =Costs!I61 -> 0 | ... Y72: =Costs!Y61 -> 3383803.4 | Z72: =SUM(B72:Y72) -> 15230163
A73: 厂商额度充值（现金时点） | B73: =IF(1=Assumptions!$B$10,Assumptions!$B$8,0) -> 0 | C73: =IF(2=Assumptions!$B$10,Assumptions!$B$8,0) -> 0 | D73: =IF(3=Assumptions!$B$10,Assumptions!$B$8,0) -> 0 | E73: =IF(4=Assumptions!$B$10,Assumptions!$B$8,0) -> 0 | F73: =IF(5=Assumptions!$B$10,Assumptions!$B$8,0) -> 0 | G73: =IF(6=Assumptions!$B$10,Assumptions!$B$8,0) -> 0 | H73: =IF(7=Assumptions!$B$10,Assumptions!$B$8,0) -> 0 | I73: =IF(8=Assumptions!$B$10,Assumptions!$B$8,0) -> 0 | J73: =IF(9=Assumptions!$B$10,Assumptions!$B$8,0) -> 0 | K73: =IF(10=Assumptions!$B$10,Assumptions!$B$8,0) -> 0 | L73: =IF(11=Assumptions!$B$10,Assumptions!$B$8,0) -> 0 | M73: =IF(12=Assumptions!$B$10,Assumptions!$B$8,0) -> 0 | N73: =IF(13=Assumptions!$B$10,Assumptions!$B$8,0) -> 0 | O73: =IF(14=Assumptions!$B$10,Assumptions!$B$8,0) -> 0 | P73: =IF(15=Assumptions!$B$10,Assumptions!$B$8,0) -> 0 | Q73: =IF(16=Assumptions!$B$10,Assumptions!$B$8,0) -> 0 | R73: =IF(17=Assumptions!$B$10,Assumptions!$B$8,0) -> 0 | S73: =IF(18=Assumptions!$B$10,Assumptions!$B$8,0) -> 0 | T73: =IF(19=Assumptions!$B$10,Assumptions!$B$8,0) -> 0 | U73: =IF(20=Assumptions!$B$10,Assumptions!$B$8,0) -> 0 | V73: =IF(21=Assumptions!$B$10,Assumptions!$B$8,0) -> 0 | W73: =IF(22=Assumptions!$B$10,Assumptions!$B$8,0) -> 0 | X73: =IF(23=Assumptions!$B$10,Assumptions!$B$8,0) -> 0 | Y73: =IF(24=Assumptions!$B$10,Assumptions!$B$8,0) -> 0 | Z73: =SUM(B73:Y73) -> 0
A74: 月初预付额度资产 | B74: =0 -> 0 | C74: =B76 -> 0 | D74: =C76 -> 0 | E74: =D76 -> 0 | F74: =E76 -> 0 | G74: =F76 -> 0 | H74: =G76 -> 0 | I74: =H76 -> 0 | J74: =I76 -> 0 | ... Y74: =X76 -> 0 | Z74: =Y74 -> 0
A75: 抵扣已购额度 | B75: =MIN(B74+B73,B72) -> 0 | C75: =MIN(C74+C73,C72) -> 0 | D75: =MIN(D74+D73,D72) -> 0 | E75: =MIN(E74+E73,E72) -> 0 | F75: =MIN(F74+F73,F72) -> 0 | G75: =MIN(G74+G73,G72) -> 0 | H75: =MIN(H74+H73,H72) -> 0 | I75: =MIN(I74+I73,I72) -> 0 | ... Y75: =MIN(Y74+Y73,Y72) -> 0 | Z75: =SUM(B75:Y75) -> 0
A76: 月末预付额度资产 | B76: =B74+B73-B75 -> 0 | C76: =C74+C73-C75 -> 0 | D76: =D74+D73-D75 -> 0 | E76: =E74+E73-E75 -> 0 | F76: =F74+F73-F75 -> 0 | G76: =G74+G73-G75 -> 0 | H76: =H74+H73-H75 -> 0 | I76: =I74+I73-I75 -> 0 | ... Y76: =Y74+Y73-Y75 -> 0 | Z76: =Y76 -> 0
A77: 用户Token实际支付现金 | B77: =B72-B75+B73 -> 0 | C77: =C72-C75+C73 -> 0 | D77: =D72-D75+D73 -> 0 | E77: =E72-E75+E73 -> 0 | F77: =F72-F75+F73 -> 0 | G77: =G72-G75+G73 -> 0 | H77: =H72-H75+H73 -> 0 | I77: =I72-I75+I73 -> 0 | ... Y77: =Y72-Y75+Y73 -> 3383803.4 | Z77: =SUM(B77:Y77) -> 15230163
A78: 非退还合作费用 | B78: =Costs!B62 -> 0 | C78: =Costs!C62 -> 0 | D78: =Costs!D62 -> 0 | E78: =Costs!E62 -> 0 | F78: =Costs!F62 -> 0 | G78: =Costs!G62 -> 0 | H78: =Costs!H62 -> 0 | I78: =Costs!I62 -> 0 | ... Y78: =Costs!Y62 -> 0 | Z78: =SUM(B78:Y78) -> 0
A79: 可退保证金现金 | B79: =IF(1=Assumptions!$B$10,Assumptions!$B$9,0) -> 0 | C79: =IF(2=Assumptions!$B$10,Assumptions!$B$9,0) -> 0 | D79: =IF(3=Assumptions!$B$10,Assumptions!$B$9,0) -> 0 | E79: =IF(4=Assumptions!$B$10,Assumptions!$B$9,0) -> 0 | F79: =IF(5=Assumptions!$B$10,Assumptions!$B$9,0) -> 0 | G79: =IF(6=Assumptions!$B$10,Assumptions!$B$9,0) -> 0 | H79: =IF(7=Assumptions!$B$10,Assumptions!$B$9,0) -> 0 | I79: =IF(8=Assumptions!$B$10,Assumptions!$B$9,0) -> 0 | J79: =IF(9=Assumptions!$B$10,Assumptions!$B$9,0) -> 0 | K79: =IF(10=Assumptions!$B$10,Assumptions!$B$9,0) -> 0 | L79: =IF(11=Assumptions!$B$10,Assumptions!$B$9,0) -> 0 | M79: =IF(12=Assumptions!$B$10,Assumptions!$B$9,0) -> 0 | N79: =IF(13=Assumptions!$B$10,Assumptions!$B$9,0) -> 0 | O79: =IF(14=Assumptions!$B$10,Assumptions!$B$9,0) -> 0 | P79: =IF(15=Assumptions!$B$10,Assumptions!$B$9,0) -> 0 | Q79: =IF(16=Assumptions!$B$10,Assumptions!$B$9,0) -> 0 | R79: =IF(17=Assumptions!$B$10,Assumptions!$B$9,0) -> 0 | S79: =IF(18=Assumptions!$B$10,Assumptions!$B$9,0) -> 0 | T79: =IF(19=Assumptions!$B$10,Assumptions!$B$9,0) -> 0 | U79: =IF(20=Assumptions!$B$10,Assumptions!$B$9,0) -> 0 | V79: =IF(21=Assumptions!$B$10,Assumptions!$B$9,0) -> 0 | W79: =IF(22=Assumptions!$B$10,Assumptions!$B$9,0) -> 0 | X79: =IF(23=Assumptions!$B$10,Assumptions!$B$9,0) -> 0 | Y79: =IF(24=Assumptions!$B$10,Assumptions!$B$9,0) -> 0 | Z79: =SUM(B79:Y79) -> 0
A80: 设备购置现金 | B80: =Costs!B64 -> 75000 | C80: =Costs!C64 -> 0 | D80: =Costs!D64 -> 0 | E80: =Costs!E64 -> 0 | F80: =Costs!F64 -> 0 | G80: =Costs!G64 -> 0 | H80: =Costs!H64 -> 45000 | I80: =Costs!I64 -> 0 | ... Y80: =Costs!Y64 -> 0 | Z80: =SUM(B80:Y80) -> 120000
A81: 现金支付总计 | B81: =B71+B77+B78+B79+B80 -> 191557.43 | C81: =C71+C77+C78+C79+C80 -> 116557.43 | D81: =D71+D77+D78+D79+D80 -> 116557.43 | E81: =E71+E77+E78+E79+E80 -> 130057.43 | F81: =F71+F77+F78+F79+F80 -> 130057.43 | G81: =G71+G77+G78+G79+G80 -> 175057.43 | H81: =H71+H77+H78+H79+H80 -> 206446.79 | I81: =I71+I77+I78+I79+I80 -> 161446.79 | ... Y81: =Y71+Y77+Y78+Y79+Y80 -> 3617250.2 | Z81: =SUM(B81:Y81) -> 19365050
A82: 当月净现金流 | B82: =B70-B81 -> -191557.43 | C82: =C70-C81 -> -116557.43 | D82: =D70-D81 -> -116557.43 | E82: =E70-E81 -> -130057.43 | F82: =F70-F81 -> -130057.43 | G82: =G70-G81 -> -175057.43 | H82: =H70-H81 -> -206446.79 | I82: =I70-I81 -> -161446.79 | ... Y82: =Y70-Y81 -> -3617250.2 | Z82: =SUM(B82:Y82) -> -19365050
A83: 月末现金（未补资） | B83: =B69+B82 -> -191557.43 | C83: =C69+C82 -> -308114.86 | D83: =D69+D82 -> -424672.29 | E83: =E69+E82 -> -554729.73 | F83: =F69+F82 -> -684787.16 | G83: =G69+G82 -> -859844.59 | H83: =H69+H82 -> -1066291.4 | I83: =I69+I82 -> -1227738.2 | ... Y83: =Y69+Y82 -> -19365050 | Z83: =Y83 -> -19365050
A84: 假设足额补入规划资金 | B84: =IF(1=1,Summary!D$19,0) -> 31500000 | C84: =IF(2=1,Summary!D$19,0) -> 0 | D84: =IF(3=1,Summary!D$19,0) -> 0 | E84: =IF(4=1,Summary!D$19,0) -> 0 | F84: =IF(5=1,Summary!D$19,0) -> 0 | G84: =IF(6=1,Summary!D$19,0) -> 0 | H84: =IF(7=1,Summary!D$19,0) -> 0 | I84: =IF(8=1,Summary!D$19,0) -> 0 | J84: =IF(9=1,Summary!D$19,0) -> 0 | K84: =IF(10=1,Summary!D$19,0) -> 0 | L84: =IF(11=1,Summary!D$19,0) -> 0 | M84: =IF(12=1,Summary!D$19,0) -> 0 | N84: =IF(13=1,Summary!D$19,0) -> 0 | O84: =IF(14=1,Summary!D$19,0) -> 0 | P84: =IF(15=1,Summary!D$19,0) -> 0 | Q84: =IF(16=1,Summary!D$19,0) -> 0 | R84: =IF(17=1,Summary!D$19,0) -> 0 | S84: =IF(18=1,Summary!D$19,0) -> 0 | T84: =IF(19=1,Summary!D$19,0) -> 0 | U84: =IF(20=1,Summary!D$19,0) -> 0 | V84: =IF(21=1,Summary!D$19,0) -> 0 | W84: =IF(22=1,Summary!D$19,0) -> 0 | X84: =IF(23=1,Summary!D$19,0) -> 0 | Y84: =IF(24=1,Summary!D$19,0) -> 0 | Z84: =SUM(B84:Y84) -> 31500000
A85: 月初现金（假设补足） | B85: =Assumptions!$B$4 -> 0 | C85: =B86 -> 31308443 | D85: =C86 -> 31191885 | E85: =D86 -> 31075328 | F85: =E86 -> 30945270 | G85: =F86 -> 30815213 | H85: =G86 -> 30640155 | I85: =H86 -> 30433709 | J85: =I86 -> 30272262 | ... Y85: =X86 -> 15752201 | Z85: =Y85 -> 15752201
A86: 月末现金（假设补足） | B86: =B85+B70+B84-B81 -> 31308443 | C86: =C85+C70+C84-C81 -> 31191885 | D86: =D85+D70+D84-D81 -> 31075328 | E86: =E85+E70+E84-E81 -> 30945270 | F86: =F85+F70+F84-F81 -> 30815213 | G86: =G85+G70+G84-G81 -> 30640155 | H86: =H85+H70+H84-H81 -> 30433709 | I86: =I85+I70+I84-I81 -> 30272262 | ... Y86: =Y85+Y70+Y84-Y81 -> 12134950 | Z86: =Y86 -> 12134950
A87: 保证金资产 | B87: =SUM($B79:B79) -> 0 | C87: =SUM($B79:C79) -> 0 | D87: =SUM($B79:D79) -> 0 | E87: =SUM($B79:E79) -> 0 | F87: =SUM($B79:F79) -> 0 | G87: =SUM($B79:G79) -> 0 | H87: =SUM($B79:H79) -> 0 | I87: =SUM($B79:I79) -> 0 | ... Y87: =SUM($B79:Y79) -> 0 | Z87: =Y87 -> 0
A88: 额度资产 | B88: =B76 -> 0 | C88: =C76 -> 0 | D88: =D76 -> 0 | E88: =E76 -> 0 | F88: =F76 -> 0 | G88: =G76 -> 0 | H88: =H76 -> 0 | I88: =I76 -> 0 | ... Y88: =Y76 -> 0 | Z88: =Y88 -> 0
A89: 待收回金额 | B89: =Revenue!B30 -> 0 | C89: =Revenue!C30 -> 0 | D89: =Revenue!D30 -> 0 | E89: =Revenue!E30 -> 0 | F89: =Revenue!F30 -> 0 | G89: =Revenue!G30 -> 0 | H89: =Revenue!H30 -> 0 | I89: =Revenue!I30 -> 0 | ... Y89: =Revenue!Y30 -> 0 | Z89: =Y89 -> 0
A90: 设备净值 | B90: =SUM(Costs!B64:'Costs'!B64)-SUM(Costs!B65:'Costs'!B65) -> 72916.667 | C90: =SUM(Costs!B64:'Costs'!C64)-SUM(Costs!B65:'Costs'!C65) -> 70833.333 | D90: =SUM(Costs!B64:'Costs'!D64)-SUM(Costs!B65:'Costs'!D65) -> 68750 | E90: =SUM(Costs!B64:'Costs'!E64)-SUM(Costs!B65:'Costs'!E65) -> 66666.667 | F90: =SUM(Costs!B64:'Costs'!F64)-SUM(Costs!B65:'Costs'!F65) -> 64583.333 | G90: =SUM(Costs!B64:'Costs'!G64)-SUM(Costs!B65:'Costs'!G65) -> 62500 | H90: =SUM(Costs!B64:'Costs'!H64)-SUM(Costs!B65:'Costs'!H65) -> 104166.67 | I90: =SUM(Costs!B64:'Costs'!I64)-SUM(Costs!B65:'Costs'!I65) -> 100833.33 | J90: =SUM(Costs!B64:'Costs'!J64)-SUM(Costs!B65:'Costs'!J65) -> 97500 | K90: =SUM(Costs!B64:'Costs'!K64)-SUM(Costs!B65:'Costs'!K65) -> 94166.667 | L90: =SUM(Costs!B64:'Costs'!L64)-SUM(Costs!B65:'Costs'!L65) -> 90833.333 | M90: =SUM(Costs!B64:'Costs'!M64)-SUM(Costs!B65:'Costs'!M65) -> 87500 | N90: =SUM(Costs!B64:'Costs'!N64)-SUM(Costs!B65:'Costs'!N65) -> 84166.667 | O90: =SUM(Costs!B64:'Costs'!O64)-SUM(Costs!B65:'Costs'!O65) -> 80833.333 | P90: =SUM(Costs!B64:'Costs'!P64)-SUM(Costs!B65:'Costs'!P65) -> 77500 | Q90: =SUM(Costs!B64:'Costs'!Q64)-SUM(Costs!B65:'Costs'!Q65) -> 74166.667 | R90: =SUM(Costs!B64:'Costs'!R64)-SUM(Costs!B65:'Costs'!R65) -> 70833.333 | S90: =SUM(Costs!B64:'Costs'!S64)-SUM(Costs!B65:'Costs'!S65) -> 67500 | T90: =SUM(Costs!B64:'Costs'!T64)-SUM(Costs!B65:'Costs'!T65) -> 64166.667 | U90: =SUM(Costs!B64:'Costs'!U64)-SUM(Costs!B65:'Costs'!U65) -> 60833.333 | V90: =SUM(Costs!B64:'Costs'!V64)-SUM(Costs!B65:'Costs'!V65) -> 57500 | W90: =SUM(Costs!B64:'Costs'!W64)-SUM(Costs!B65:'Costs'!W65) -> 54166.667 | X90: =SUM(Costs!B64:'Costs'!X64)-SUM(Costs!B65:'Costs'!X65) -> 50833.333 | Y90: =SUM(Costs!B64:'Costs'!Y64)-SUM(Costs!B65:'Costs'!Y65) -> 47500 | Z90: =Y90 -> 47500
A91: 充值/消耗现金恒等检查 | B91: =B77-B72-B73+B75 -> 0 | C91: =C77-C72-C73+C75 -> 0 | D91: =D77-D72-D73+D75 -> 0 | E91: =E77-E72-E73+E75 -> 0 | F91: =F77-F72-F73+F75 -> 0 | G91: =G77-G72-G73+G75 -> 0 | H91: =H77-H72-H73+H75 -> 0 | I91: =I77-I72-I73+I75 -> 0 | ... Y91: =Y77-Y72-Y73+Y75 -> 0 | Z91: =SUM(B91:Y91) -> 0

Sheet Financing
A1: 资金来源与用途｜全部融资仅为规划演算，不代表到账、估值或贷款
B3: 精简推进 | C3: 基准建设 | D3: 高用量压力
A4: 假设外部资金补入 | B4: =Summary!B19 -> 4000000 | C4: =Summary!C19 -> 9000000 | D4: =Summary!D19 -> 31500000
A5: 确认自有资金 | B5: =Summary!B13 -> 0 | C5: =Summary!C13 -> 0 | D5: =Summary!D13 -> 0
A6: 规划运营收款 | B6: =Summary!B12 -> 0 | C6: =Summary!C12 -> 0 | D6: =Summary!D12 -> 0
A7: 现金来源合计 | B7: =SUM(B4:B6) -> 4000000 | C7: =SUM(C4:C6) -> 9000000 | D7: =SUM(D4:D6) -> 31500000
A9: 研发/教研运营等效人力 | B9: =Summary!B8 -> 1056000 | C9: =Summary!C8 -> 1800000 | D9: =Summary!D8 -> 2736000
A10: 内部研发Agent预算 | B10: =Summary!B7 -> 95348.811 | C10: =Summary!C7 -> 173361.47 | D10: =Summary!D7 -> 329386.8
A11: 外部用户Token实际现金 | B11: =SUM('Cash Flow'!B11:Y11) -> 913809.77 | C11: =SUM('Cash Flow'!B44:Y44) -> 3046032.6 | D11: =SUM('Cash Flow'!B77:Y77) -> 15230163
A12: 基础设施/教学/社区/运营/专项 | B12: =Summary!B9 -> 474750 | C12: =Summary!C9 -> 633000 | D12: =Summary!D9 -> 949500
A13: 设备采购 | B13: =Summary!B10 -> 60000 | C13: =Summary!C10 -> 80000 | D13: =Summary!D10 -> 120000
A14: 合作费及保证金现金 | B14: =SUM('Cash Flow'!B12:Y13) -> 0 | C14: =SUM('Cash Flow'!B45:Y46) -> 0 | D14: =SUM('Cash Flow'!B78:Y79) -> 0
A15: 24个月现金支付 | B15: =SUM(B9:B14) -> 2599908.6 | C15: =SUM(C9:C14) -> 5732394 | D15: =SUM(D9:D14) -> 19365050
A17: 期末现金（含储备与预留） | B17: =Summary!B20 -> 1400091.4 | C17: =Summary!C20 -> 3267606 | D17: =Summary!D20 -> 12134950
A18: 现金用途合计 | B18: =B15+B17 -> 4000000 | C18: =C15+C17 -> 9000000 | D18: =D15+D17 -> 31500000
A19: 来源减用途 | B19: =B7-B18 -> 0 | C19: =C7-C18 -> 0 | D19: =D7-D18 -> 0
A21: 风险预留（不提前确认为费用） | B21: =Summary!B15 -> 162609.88 | C21: =Summary!C15 -> 260636.15 | D21: =Summary!D15 -> 602233.02
A22: 合作现金预留余额 | B22: =Summary!B16 -> 100000 | C22: =Summary!C16 -> 300000 | D22: =Summary!D16 -> 800000
A23: 正常运营储备 | B23: =Summary!B17 -> 824586.72 | C23: =Summary!C17 -> 2371396.9 | D23: =Summary!D17 -> 10671751
A24: 资金取整余量 | B24: =Summary!B19-Summary!B18 -> 312894.82 | C24: =Summary!C19-Summary!C18 -> 335572.92 | D24: =Summary!D19-Summary!D18 -> 60966.835
A26: 最低追加需求 | B26: =Summary!B18 -> 3687105.2 | C26: =Summary!C18 -> 8664427.1 | D26: =Summary!D18 -> 31439033

Sheet Checks
A1: 原生重算后的勾稽｜任何FAIL都阻止交付
B3: 精简推进 | C3: 基准建设 | D3: 高用量压力
A4: 现金来源与用途差额 | B4: =ABS(Financing!B19) -> 0 | C4: =ABS(Financing!C19) -> 0 | D4: =ABS(Financing!D19) -> 0
A5: 资金需求与取整差额 | B5: =ABS(Summary!B19-Summary!B18-Financing!B24) -> 0 | C5: =ABS(Summary!C19-Summary!C18-Financing!C24) -> 0 | D5: =ABS(Summary!D19-Summary!D18-Financing!D24) -> 0
A6: 预付抵扣恒等最大误差 | B6: =MAX(MAX('Cash Flow'!B25:Y25),-MIN('Cash Flow'!B25:Y25)) -> 0 | C6: =MAX(MAX('Cash Flow'!B58:Y58),-MIN('Cash Flow'!B58:Y58)) -> 0 | D6: =MAX(MAX('Cash Flow'!B91:Y91),-MIN('Cash Flow'!B91:Y91)) -> 0
A7: 逐月资产负债最大误差 | B7: =MAX(MAX('Balance Sheet'!B11:Y11),-MIN('Balance Sheet'!B11:Y11)) -> 1.0477379e-09 | C7: =MAX(MAX('Balance Sheet'!B29:Y29),-MIN('Balance Sheet'!B29:Y29)) -> 5.1222742e-09 | D7: =MAX(MAX('Balance Sheet'!B47:Y47),-MIN('Balance Sheet'!B47:Y47)) -> 2.514571e-08
A8: 状态 | B8: =IF(MAX(B4:B7)<0.01,"PASS","FAIL") -> PASS | C8: =IF(MAX(C4:C7)<0.01,"PASS","FAIL") -> PASS | D8: =IF(MAX(D4:D7)<0.01,"PASS","FAIL") -> PASS

Sheet Sources
A1: 参数来源和假设登记｜访问日期2026-10-03｜人民币
A3: ID | B3: 类型 | C3: 参数/事实 | D3: 依据和边界 | E3: 置信度 | F3: 公开来源
A4: F01 | B4: 规划要求 | C4: 24个月；Token按人头；合作费用未知 | D4: 24个月持续发展规划 | E4: 高（范围）
A5: F02 | B5: 规划判断 | C5: 第19月后条件容量/期末1160人 | D5: 产品准备关口后；不代表上线或增长承诺 | E5: 低
A6: F05 | B6: 资源预算 | C6: 3→4等效人力，综合人月2万元 | D6: 覆盖研发、教研与运营，非现有人员履历 | E6: 低
A7: F06 | B7: 任务与公开使用统计 | C7: 短任务实测Token与专业150–250美元/月分别使用 | D7: 频次和专业预算中点为假设；不是售价或真实账单 | E7: 中（来源）/低（频次）
A8: F07 | B8: 厂商条件 | C8: 实际费/额度预付/保证金待报价 | D8: 0是未录入；合作现金预留30万元为预算判断 | E8: 低
A9: F08 | B9: 现金政策 | C9: 3个月正常运营储备+10%常规支出风险预留 | D9: 风险预留不含用户Token、设备及未知合作费 | E9: 低
A10: F09 | B10: 收入与资金 | C10: 默认成本回收0、自有现金0 | D10: 不以未确认收款或自有投入压低资金；外部补资仅规划 | E10: 低
A11: F10 | B11: 设备与会计 | C11: 36个月折旧；预付和保证金为资产 | D11: 现金、费用与折旧分别核算；无融资税务承诺 | E11: 低
A12: F03 | B12: 官方单价 | C12: DeepSeek Pro高峰人民币输入未命中9元/百万、缓存命中0.30元/百万、输出27元/百万；短任务缓存拆分未知按未命中重定价，不代表息壤账单。 | D12: 来源类别及边界见原说明；USD按2026-09-30参考汇率换算 | E12: 高（机制） | F12: https://api-docs.deepseek.com/zh-cn/quick_start/pricing/
A13: F11 | B13: 项目脱敏用量样本 | C13: 2026-10-02十个取得可读回执的任务、30响应，输入76845/输出5738；其他任务用量不完整，样本不能证明课堂或完整模板成本。 | D13: 来源类别及边界见原说明；USD按2026-09-30参考汇率换算 | E13: 高（机制）
A14: F12 | B14: 厂商公开使用统计 | C14: Claude Code企业开发者典型150–250美元/月、活跃日均约13美元；专业预算选200美元中点，研发活跃天数假设22。不是Blocky用户实测，不套用于小学生。 | D14: 来源类别及边界见原说明；USD按2026-09-30参考汇率换算 | E14: 高（机制） | F14: https://code.claude.com/docs/en/costs
A15: F13 | B15: 历史汇率参考 | C15: 中国外汇交易中心主办中国货币网2026-09-30 9:15美元中间价6.7351，官方网页索引读回；非实际支付成交汇率。 | D15: 来源类别及边界见原说明；USD按2026-09-30参考汇率换算 | E15: 高（机制） | F15: https://www.chinamoney.com.cn/chinese/index.html
A16: F14 | B16: 官方价格 | C16: Claude Sonnet/Opus及缓存、长上下文分项单价支持模型成本差异；本模型专业档采用公开使用统计，不能与API价格再次叠加。 | D16: 来源类别及边界见原说明；USD按2026-09-30参考汇率换算 | E16: 高（机制） | F16: https://platform.claude.com/docs/en/about-claude/pricing
A17: F15 | B17: 供应商公开套餐 | C17: 息壤积分套餐公开，Pro输入输出与缓存兑换比例及平台托管适用性未明确；本项目实际采购费用仍需合同与账单。 | D17: 来源类别及边界见原说明；USD按2026-09-30参考汇率换算 | E17: 高（机制） | F17: https://www.ctyun.cn/act/AI/zhuanxiang
